Workbook

Sheet Dados
A1: cod_ibge7 | B1: cod_ibge6 | C1: municipio | D1: uf | E1: co_regiao_saude | F1: no_regiao_saude | G1: populacao_2025 | H1: municipio_pequeno | I1: fp_total | J1: fp_so_hipertensao | K1: fp_so_diabetes | L1: fp_hipertensao_e_diabetes | M1: fp_asma | N1: alto_custo_pacientes | O1: quimioterapia_pacientes | P1: radioterapia_pacientes | Q1: hiv_pessoas_em_tratamento_2022 | R1: fp_total_por_mil_hab | S1: fp_so_hipertensao_por_mil_hab | T1: fp_so_diabetes_por_mil_hab | U1: fp_hipertensao_e_diabetes_por_mil_hab | V1: fp_asma_por_mil_hab | W1: alto_custo_pacientes_por_mil_hab | X1: quimioterapia_pacientes_por_mil_hab | Y1: fp_total_regiao_saude | Z1: fp_so_hipertensao_regiao_saude | AA1: fp_so_diabetes_regiao_saude | AB1: fp_hipertensao_e_diabetes_regiao_saude | AC1: fp_asma_regiao_saude | AD1: alto_custo_pacientes_regiao_saude | AE1: quimioterapia_pacientes_regiao_saude | AF1: radioterapia_pacientes_regiao_saude | AG1: fp_total_por_mil_hab_regiao_saude | AH1: bolso_anual_minimo_rs | AI1: bolso_anual_mediano_rs | AJ1: txt_farmacia_popular | AK1: txt_bolso
A2: 1100015 | B2: 110001 | C2: Alta Floresta D'Oeste | D2: RO | E2: 11005 | F2: Zona da Mata | G2: 22787 | H2: =G2<'Programas e Observações'!$C$11 -> FALSE | I2: 344 | J2: 204 | K2: 21 | L2: 74 | M2: 2 | N2: 361 | O2: 59 | P2: 1 | R2: =IF(G2>0,1000*I2/G2,0) -> 15.096327 | S2: =IF(G2>0,1000*J2/G2,0) -> 8.9524729 | T2: =IF(G2>0,1000*K2/G2,0) -> 0.92157809 | U2: =IF(G2>0,1000*L2/G2,0) -> 3.2474657 | V2: =IF(G2>0,1000*M2/G2,0) -> 0.087769342 | W2: =IF(G2>0,1000*N2/G2,0) -> 15.842366 | X2: =IF(G2>0,1000*O2/G2,0) -> 2.5891956 | Y2: =SUMIFS($I$2:$I$5572,$E$2:$E$5572,E2) -> 3387 | Z2: =SUMIFS($J$2:$J$5572,$E$2:$E$5572,E2) -> 1912 | AA2: =SUMIFS($K$2:$K$5572,$E$2:$E$5572,E2) -> 196 | AB2: =SUMIFS($L$2:$L$5572,$E$2:$E$5572,E2) -> 835 | AC2: =SUMIFS($M$2:$M$5572,$E$2:$E$5572,E2) -> 38 | AD2: =SUMIFS($N$2:$N$5572,$E$2:$E$5572,E2) -> 1751 | AE2: =SUMIFS($O$2:$O$5572,$E$2:$E$5572,E2) -> 314 | AF2: =SUMIFS($P$2:$P$5572,$E$2:$E$5572,E2) -> 7 | AG2: =IF(SUMIFS($G$2:$G$5572,$E$2:$E$5572,E2)>0,1000*Y2/SUMIFS($G$2:$G$5572,$E$2:$E$5572,E2),0) -> 24.545613 | AH2: =12*(J2*'Programas e Observações'!$C$8+K2*'Programas e Observações'!$C$9+L2*('Programas e Observações'!$C$8+'Programas e Observações'!$C$9)+M2*'Programas e Observações'!$C$10) -> 104658.36 | AI2: =12*(J2*'Programas e Observações'!$D$8+K2*'Programas e Observações'!$D$9+L2*('Programas e Observações'!$D$8+'Programas e Observações'!$D$9)+M2*'Programas e Observações'!$D$10) -> 206718.84 | AJ2: 299 moradores pegam remédio de pressão ou diabetes de graça na Farmácia Popular | AK2: Sem o programa, gastariam pelo menos R$ 105 mil por ano
A3: 1100023 | B3: 110002 | C3: Ariquemes | D3: RO | E3: 11001 | F3: Vale do Jamari | G3: 109170 | H3: =G3<'Programas e Observações'!$C$11 -> FALSE | I3: 1537 | J3: 633 | K3: 114 | L3: 234 | M3: 44 | N3: 963 | O3: 182 | P3: 6 | Q3: 335 | R3: =IF(G3>0,1000*I3/G3,0) -> 14.078959 | S3: =IF(G3>0,1000*J3/G3,0) -> 5.7982962 | T3: =IF(G3>0,1000*K3/G3,0) -> 1.0442429 | U3: =IF(G3>0,1000*L3/G3,0) -> 2.143446 | V3: =IF(G3>0,1000*M3/G3,0) -> 0.40304113 | W3: =IF(G3>0,1000*N3/G3,0) -> 8.8211047 | X3: =IF(G3>0,1000*O3/G3,0) -> 1.6671247 | Y3: =SUMIFS($I$2:$I$5572,$E$2:$E$5572,E3) -> 3070 | Z3: =SUMIFS($J$2:$J$5572,$E$2:$E$5572,E3) -> 1523 | AA3: =SUMIFS($K$2:$K$5572,$E$2:$E$5572,E3) -> 232 | AB3: =SUMIFS($L$2:$L$5572,$E$2:$E$5572,E3) -> 477 | AC3: =SUMIFS($M$2:$M$5572,$E$2:$E$5572,E3) -> 83 | AD3: =SUMIFS($N$2:$N$5572,$E$2:$E$5572,E3) -> 2055 | AE3: =SUMIFS($O$2:$O$5572,$E$2:$E$5572,E3) -> 401 | AF3: =SUMIFS($P$2:$P$5572,$E$2:$E$5572,E3) -> 13 | AG3: =IF(SUMIFS($G$2:$G$5572,$E$2:$E$5572,E3)>0,1000*Y3/SUMIFS($G$2:$G$5572,$E$2:$E$5572,E3),0) -> 12.973622 | AH3: =12*(J3*'Programas e Observações'!$C$8+K3*'Programas e Observações'!$C$9+L3*('Programas e Observações'!$C$8+'Programas e Observações'!$C$9)+M3*'Programas e Observações'!$C$10) -> 372657.72 | AI3: =12*(J3*'Programas e Observações'!$D$8+K3*'Programas e Observações'!$D$9+L3*('Programas e Observações'!$D$8+'Programas e Observações'!$D$9)+M3*'Programas e Observações'!$D$10) -> 692610.72 | AJ3: 981 moradores pegam remédio de pressão ou diabetes de graça na Farmácia Popular | AK3: Sem o programa, gastariam pelo menos R$ 373 mil por ano
A4: 1100031 | B4: 110003 | C4: Cabixi | D4: RO | E4: 11006 | F4: Cone Sul | G4: 5664 | H4: =G4<'Programas e Observações'!$C$11 -> TRUE | I4: 465 | J4: 220 | K4: 22 | L4: 179 | M4: 147 | N4: 25 | O4: 9 | P4: 0 | R4: =IF(G4>0,1000*I4/G4,0) -> 82.097458 | S4: =IF(G4>0,1000*J4/G4,0) -> 38.841808 | T4: =IF(G4>0,1000*K4/G4,0) -> 3.8841808 | U4: =IF(G4>0,1000*L4/G4,0) -> 31.603107 | V4: =IF(G4>0,1000*M4/G4,0) -> 25.95339 | W4: =IF(G4>0,1000*N4/G4,0) -> 4.4138418 | X4: =IF(G4>0,1000*O4/G4,0) -> 1.5889831 | Y4: =SUMIFS($I$2:$I$5572,$E$2:$E$5572,E4) -> 6176 | Z4: =SUMIFS($J$2:$J$5572,$E$2:$E$5572,E4) -> 3173 | AA4: =SUMIFS($K$2:$K$5572,$E$2:$E$5572,E4) -> 544 | AB4: =SUMIFS($L$2:$L$5572,$E$2:$E$5572,E4) -> 1434 | AC4: =SUMIFS($M$2:$M$5572,$E$2:$E$5572,E4) -> 238 | AD4: =SUMIFS($N$2:$N$5572,$E$2:$E$5572,E4) -> 1653 | AE4: =SUMIFS($O$2:$O$5572,$E$2:$E$5572,E4) -> 277 | AF4: =SUMIFS($P$2:$P$5572,$E$2:$E$5572,E4) -> 5 | AG4: =IF(SUMIFS($G$2:$G$5572,$E$2:$E$5572,E4)>0,1000*Y4/SUMIFS($G$2:$G$5572,$E$2:$E$5572,E4),0) -> 36.48889 | AH4: =12*(J4*'Programas e Observações'!$C$8+K4*'Programas e Observações'!$C$9+L4*('Programas e Observações'!$C$8+'Programas e Observações'!$C$9)+M4*'Programas e Observações'!$C$10) -> 259140.96 | AI4: =12*(J4*'Programas e Observações'!$D$8+K4*'Programas e Observações'!$D$9+L4*('Programas e Observações'!$D$8+'Programas e Observações'!$D$9)+M4*'Programas e Observações'!$D$10) -> 409078.08 | AJ4: 421 moradores pegam remédio de pressão ou diabetes de graça na Farmácia Popular | AK4: Sem o programa, gastariam pelo menos R$ 259 mil por ano
A5: 1100049 | B5: 110004 | C5: Cacoal | D5: RO | E5: 11002 | F5: Café | G5: 98280 | H5: =G5<'Programas e Observações'!$C$11 -> FALSE | I5: 3290 | J5: 1754 | K5: 214 | L5: 847 | M5: 156 | N5: 1116 | O5: 271 | P5: 7 | Q5: 215 | R5: =IF(G5>0,1000*I5/G5,0) -> 33.475783 | S5: =IF(G5>0,1000*J5/G5,0) -> 17.846968 | T5: =IF(G5>0,1000*K5/G5,0) -> 2.1774522 | U5: =IF(G5>0,1000*L5/G5,0) -> 8.6182336 | V5: =IF(G5>0,1000*M5/G5,0) -> 1.5873016 | W5: =IF(G5>0,1000*N5/G5,0) -> 11.355311 | X5: =IF(G5>0,1000*O5/G5,0) -> 2.7574278 | Y5: =SUMIFS($I$2:$I$5572,$E$2:$E$5572,E5) -> 5842 | Z5: =SUMIFS($J$2:$J$5572,$E$2:$E$5572,E5) -> 3287 | AA5: =SUMIFS($K$2:$K$5572,$E$2:$E$5572,E5) -> 380 | AB5: =SUMIFS($L$2:$L$5572,$E$2:$E$5572,E5) -> 1380 | AC5: =SUMIFS($M$2:$M$5572,$E$2:$E$5572,E5) -> 222 | AD5: =SUMIFS($N$2:$N$5572,$E$2:$E$5572,E5) -> 1947 | AE5: =SUMIFS($O$2:$O$5572,$E$2:$E$5572,E5) -> 442 | AF5: =SUMIFS($P$2:$P$5572,$E$2:$E$5572,E5) -> 14 | AG5: =IF(SUMIFS($G$2:$G$5572,$E$2:$E$5572,E5)>0,1000*Y5/SUMIFS($G$2:$G$5572,$E$2:$E$5572,E5),0) -> 31.456463 | AH5: =12*(J5*'Programas e Observações'!$C$8+K5*'Programas e Observações'!$C$9+L5*('Programas e Observações'!$C$8+'Programas e Observações'!$C$9)+M5*'Programas e Observações'!$C$10) -> 1139287.7 | AI5: =12*(J5*'Programas e Observações'!$D$8+K5*'Programas e Observações'!$D$9+L5*('Programas e Observações'!$D$8+'Programas e Observações'!$D$9)+M5*'Programas e Observações'!$D$10) -> 2099856.6 | AJ5: 2.815 moradores pegam remédio de pressão ou diabetes de graça na Farmácia Popular | AK5: Sem o programa, gastariam pelo menos R$ 1,1 milhões por ano
A6: 1100056 | B6: 110005 | C6: Cerejeiras | D6: RO | E6: 11006 | F6: Cone Sul | G6: 16966 | H6: =G6<'Programas e Observações'!$C$11 -> TRUE | I6: 387 | J6: 148 | K6: 48 | L6: 60 | M6: 1 | N6: 225 | O6: 37 | P6: 0 | R6: =IF(G6>0,1000*I6/G6,0) -> 22.810327 | S6: =IF(G6>0,1000*J6/G6,0) -> 8.723329 | T6: =IF(G6>0,1000*K6/G6,0) -> 2.8291878 | U6: =IF(G6>0,1000*L6/G6,0) -> 3.5364847 | V6: =IF(G6>0,1000*M6/G6,0) -> 0.058941412 | W6: =IF(G6>0,1000*N6/G6,0) -> 13.261818 | X6: =IF(G6>0,1000*O6/G6,0) -> 2.1808323 | Y6: =SUMIFS($I$2:$I$5572,$E$2:$E$5572,E6) -> 6176 | Z6: =SUMIFS($J$2:$J$5572,$E$2:$E$5572,E6) -> 3173 | AA6: =SUMIFS($K$2:$K$5572,$E$2:$E$5572,E6) -> 544 | AB6: =SUMIFS($L$2:$L$5572,$E$2:$E$5572,E6) -> 1434 | AC6: =SUMIFS($M$2:$M$5572,$E$2:$E$5572,E6) -> 238 | AD6: =SUMIFS($N$2:$N$5572,$E$2:$E$5572,E6) -> 1653 | AE6: =SUMIFS($O$2:$O$5572,$E$2:$E$5572,E6) -> 277 | AF6: =SUMIFS($P$2:$P$5572,$E$2:$E$5572,E6) -> 5 | AG6: =IF(SUMIFS($G$2:$G$5572,$E$2:$E$5572,E6)>0,1000*Y6/SUMIFS($G$2:$G$5572,$E$2:$E$5572,E6),0) -> 36.48889 | AH6: =12*(J6*'Programas e Observações'!$C$8+K6*'Programas e Observações'!$C$9+L6*('Programas e Observações'!$C$8+'Programas e Observações'!$C$9)+M6*'Programas e Observações'!$C$10) -> 96851.28 | AI6: =12*(J6*'Programas e Observações'!$D$8+K6*'Programas e Observações'!$D$9+L6*('Programas e Observações'!$D$8+'Programas e Observações'!$D$9)+M6*'Programas e Observações'!$D$10) -> 174003.48 | AJ6: 256 moradores pegam remédio de pressão ou diabetes de graça na Farmácia Popular | AK6: Sem o programa, gastariam pelo menos R$ 97 mil por ano
A7: 1100064 | B7: 110006 | C7: Colorado do Oeste | D7: RO | E7: 11006 | F7: Cone Sul | G7: 16508 | H7: =G7<'Programas e Observações'!$C$11 -> TRUE | I7: 882 | J7: 474 | K7: 79 | L7: 169 | M7: 22 | N7: 308 | O7: 36 | P7: 1 | R7: =IF(G7>0,1000*I7/G7,0) -> 53.428641 | S7: =IF(G7>0,1000*J7/G7,0) -> 28.713351 | T7: =IF(G7>0,1000*K7/G7,0) -> 4.7855585 | U7: =IF(G7>0,1000*L7/G7,0) -> 10.237461 | V7: =IF(G7>0,1000*M7/G7,0) -> 1.3326872 | W7: =IF(G7>0,1000*N7/G7,0) -> 18.657621 | X7: =IF(G7>0,1000*O7/G7,0) -> 2.1807608 | Y7: =SUMIFS($I$2:$I$5572,$E$2:$E$5572,E7) -> 6176 | Z7: =SUMIFS($J$2:$J$5572,$E$2:$E$5572,E7) -> 3173 | AA7: =SUMIFS($K$2:$K$5572,$E$2:$E$5572,E7) -> 544 | AB7: =SUMIFS($L$2:$L$5572,$E$2:$E$5572,E7) -> 1434 | AC7: =SUMIFS($M$2:$M$5572,$E$2:$E$5572,E7) -> 238 | AD7: =SUMIFS($N$2:$N$5572,$E$2:$E$5572,E7) -> 1653 | AE7: =SUMIFS($O$2:$O$5572,$E$2:$E$5572,E7) -> 277 | AF7: =SUMIFS($P$2:$P$5572,$E$2:$E$5572,E7) -> 5 | AG7: =IF(SUMIFS($G$2:$G$5572,$E$2:$E$5572,E7)>0,1000*Y7/SUMIFS($G$2:$G$5572,$E$2:$E$5572,E7),0) -> 36.48889 | AH7: =12*(J7*'Programas e Observações'!$C$8+K7*'Programas e Observações'!$C$9+L7*('Programas e Observações'!$C$8+'Programas e Observações'!$C$9)+M7*'Programas e Observações'!$C$10) -> 265631.16 | AI7: =12*(J7*'Programas e Observações'!$D$8+K7*'Programas e Observações'!$D$9+L7*('Programas e Observações'!$D$8+'Programas e Observações'!$D$9)+M7*'Programas e Observações'!$D$10) -> 502550.64 | AJ7: 722 moradores pegam remédio de pressão ou diabetes de graça na Farmácia Popular | AK7: Sem o programa, gastariam pelo menos R$ 266 mil por ano
A8: 1100072 | B8: 110007 | C8: Corumbiara | D8: RO | E8: 11006 | F8: Cone Sul | G8: 7968 | H8: =G8<'Programas e Observações'!$C$11 -> TRUE | I8: 555 | J8: 332 | K8: 43 | L8: 109 | M8: 3 | N8: 65 | O8: 13 | P8: 1 | R8: =IF(G8>0,1000*I8/G8,0) -> 69.653614 | S8: =IF(G8>0,1000*J8/G8,0) -> 41.666667 | T8: =IF(G8>0,1000*K8/G8,0) -> 5.3965863 | U8: =IF(G8>0,1000*L8/G8,0) -> 13.679719 | V8: =IF(G8>0,1000*M8/G8,0) -> 0.37650602 | W8: =IF(G8>0,1000*N8/G8,0) -> 8.1576305 | X8: =IF(G8>0,1000*O8/G8,0) -> 1.6315261 | Y8: =SUMIFS($I$2:$I$5572,$E$2:$E$5572,E8) -> 6176 | Z8: =SUMIFS($J$2:$J$5572,$E$2:$E$5572,E8) -> 3173 | AA8: =SUMIFS($K$2:$K$5572,$E$2:$E$5572,E8) -> 544 | AB8: =SUMIFS($L$2:$L$5572,$E$2:$E$5572,E8) -> 1434 | AC8: =SUMIFS($M$2:$M$5572,$E$2:$E$5572,E8) -> 238 | AD8: =SUMIFS($N$2:$N$5572,$E$2:$E$5572,E8) -> 1653 | AE8: =SUMIFS($O$2:$O$5572,$E$2:$E$5572,E8) -> 277 | AF8: =SUMIFS($P$2:$P$5572,$E$2:$E$5572,E8) -> 5 | AG8: =IF(SUMIFS($G$2:$G$5572,$E$2:$E$5572,E8)>0,1000*Y8/SUMIFS($G$2:$G$5572,$E$2:$E$5572,E8),0) -> 36.48889 | AH8: =12*(J8*'Programas e Observações'!$C$8+K8*'Programas e Observações'!$C$9+L8*('Programas e Observações'!$C$8+'Programas e Observações'!$C$9)+M8*'Programas e Observações'!$C$10) -> 166593.24 | AI8: =12*(J8*'Programas e Observações'!$D$8+K8*'Programas e Observações'!$D$9+L8*('Programas e Observações'!$D$8+'Programas e Observações'!$D$9)+M8*'Programas e Observações'!$D$10) -> 328520.52 | AJ8: 484 moradores pegam remédio de pressão ou diabetes de graça na Farmácia Popular | AK8: Sem o programa, gastariam pelo menos R$ 167 mil por ano
A9: 1100080 | B9: 110008 | C9: Costa Marques | D9: RO | E9: 11007 | F9: Vale do Guaporé | G9: 13510 | H9: =G9<'Programas e Observações'!$C$11 -> TRUE | I9: 301 | J9: 203 | K9: 25 | L9: 45 | M9: 0 | N9: 57 | O9: 17 | P9: 1 | R9: =IF(G9>0,1000*I9/G9,0) -> 22.279793 | S9: =IF(G9>0,1000*J9/G9,0) -> 15.025907 | T9: =IF(G9>0,1000*K9/G9,0) -> 1.8504811 | U9: =IF(G9>0,1000*L9/G9,0) -> 3.330866 | V9: =IF(G9>0,1000*M9/G9,0) -> 0 | W9: =IF(G9>0,1000*N9/G9,0) -> 4.219097 | X9: =IF(G9>0,1000*O9/G9,0) -> 1.2583272 | Y9: =SUMIFS($I$2:$I$5572,$E$2:$E$5572,E9) -> 554 | Z9: =SUMIFS($J$2:$J$5572,$E$2:$E$5572,E9) -> 380 | AA9: =SUMIFS($K$2:$K$5572,$E$2:$E$5572,E9) -> 42 | AB9: =SUMIFS($L$2:$L$5572,$E$2:$E$5572,E9) -> 103 | AC9: =SUMIFS($M$2:$M$5572,$E$2:$E$5572,E9) -> 0 | AD9: =SUMIFS($N$2:$N$5572,$E$2:$E$5572,E9) -> 284 | AE9: =SUMIFS($O$2:$O$5572,$E$2:$E$5572,E9) -> 56 | AF9: =SUMIFS($P$2:$P$5572,$E$2:$E$5572,E9) -> 2 | AG9: =IF(SUMIFS($G$2:$G$5572,$E$2:$E$5572,E9)>0,1000*Y9/SUMIFS($G$2:$G$5572,$E$2:$E$5572,E9),0) -> 12.581759 | AH9: =12*(J9*'Programas e Observações'!$C$8+K9*'Programas e Observações'!$C$9+L9*('Programas e Observações'!$C$8+'Programas e Observações'!$C$9)+M9*'Programas e Observações'!$C$10) -> 84910.8 | AI9: =12*(J9*'Programas e Observações'!$D$8+K9*'Programas e Observações'!$D$9+L9*('Programas e Observações'!$D$8+'Programas e Observações'!$D$9)+M9*'Programas e Observações'!$D$10) -> 175613.52 | AJ9: 273 moradores pegam remédio de pressão ou diabetes de graça na Farmácia Popular | AK9: Sem o programa, gastariam pelo menos R$ 85 mil por ano
A10: 1100098 | B10: 110009 | C10: Espigão D'Oeste | D10: RO | E10: 11002 | F10: Café | G10: 32842 | H10: =G10<'Programas e Observações'!$C$11 -> FALSE | I10: 347 | J10: 237 | K10: 12 | L10: 45 | M10: 3 | N10: 280 | O10: 59 | P10: 2 | R10: =IF(G10>0,1000*I10/G10,0) -> 10.565739 | S10: =IF(G10>0,1000*J10/G10,0) -> 7.2163693 | T10: =IF(G10>0,1000*K10/G10,0) -> 0.36538579 | U10: =IF(G10>0,1000*L10/G10,0) -> 1.3701967 | V10: =IF(G10>0,1000*M10/G10,0) -> 0.091346447 | W10: =IF(G10>0,1000*N10/G10,0) -> 8.5256684 | X10: =IF(G10>0,1000*O10/G10,0) -> 1.7964801 | Y10: =SUMIFS($I$2:$I$5572,$E$2:$E$5572,E10) -> 5842 | Z10: =SUMIFS($J$2:$J$5572,$E$2:$E$5572,E10) -> 3287 | AA10: =SUMIFS($K$2:$K$5572,$E$2:$E$5572,E10) -> 380 | AB10: =SUMIFS($L$2:$L$5572,$E$2:$E$5572,E10) -> 1380 | AC10: =SUMIFS($M$2:$M$5572,$E$2:$E$5572,E10) -> 222 | AD10: =SUMIFS($N$2:$N$5572,$E$2:$E$5572,E10) -> 1947 | AE10: =SUMIFS($O$2:$O$5572,$E$2:$E$5572,E10) -> 442 | AF10: =SUMIFS($P$2:$P$5572,$E$2:$E$5572,E10) -> 14 | AG10: =IF(SUMIFS($G$2:$G$5572,$E$2:$E$5572,E10)>0,1000*Y10/SUMIFS($G$2:$G$5572,$E$2:$E$5572,E10),0) -> 31.456463 | AH10: =12*(J10*'Programas e Observações'!$C$8+K10*'Programas e Observações'!$C$9+L10*('Programas e Observações'!$C$8+'Programas e Observações'!$C$9)+M10*'Programas e Observações'!$C$10) -> 86622.84 | AI10: =12*(J10*'Programas e Observações'!$D$8+K10*'Programas e Observações'!$D$9+L10*('Programas e Observações'!$D$8+'Programas e Observações'!$D$9)+M10*'Programas e Observações'!$D$10) -> 189315.36 | AJ10: 294 moradores pegam remédio de pressão ou diabetes de graça na Farmácia Popular | AK10: Sem o programa, gastariam pelo menos R$ 87 mil por ano
A11: 1100106 | B11: 110010 | C11: Guajará-Mirim | D11: RO | E11: 11004 | F11: Madeira-Mamoré | G11: 43594 | H11: =G11<'Programas e Observações'!$C$11 -> FALSE | I11: 887 | J11: 421 | K11: 71 | L11: 228 | M11: 7 | N11: 130 | O11: 53 | P11: 2 | R11: =IF(G11>0,1000*I11/G11,0) -> 20.346837 | S11: =IF(G11>0,1000*J11/G11,0) -> 9.6572923 | T11: =IF(G11>0,1000*K11/G11,0) -> 1.6286645 | U11: =IF(G11>0,1000*L11/G11,0) -> 5.2300775 | V11: =IF(G11>0,1000*M11/G11,0) -> 0.16057256 | W11: =IF(G11>0,1000*N11/G11,0) -> 2.9820618 | X11: =IF(G11>0,1000*O11/G11,0) -> 1.2157636 | Y11: =SUMIFS($I$2:$I$5572,$E$2:$E$5572,E11) -> 6894 | Z11: =SUMIFS($J$2:$J$5572,$E$2:$E$5572,E11) -> 1916 | AA11: =SUMIFS($K$2:$K$5572,$E$2:$E$5572,E11) -> 1016 | AB11: =SUMIFS($L$2:$L$5572,$E$2:$E$5572,E11) -> 1376 | AC11: =SUMIFS($M$2:$M$5572,$E$2:$E$5572,E11) -> 263 | AD11: =SUMIFS($N$2:$N$5572,$E$2:$E$5572,E11) -> 5769 | AE11: =SUMIFS($O$2:$O$5572,$E$2:$E$5572,E11) -> 1523 | AF11: =SUMIFS($P$2:$P$5572,$E$2:$E$5572,E11) -> 22 | AG11: =IF(SUMIFS($G$2:$G$5572,$E$2:$E$5572,E11)>0,1000*Y11/SUMIFS($G$2:$G$5572,$E$2:$E$5572,E11),0) -> 11.056139 | AH11: =12*(J11*'Programas e Observações'!$C$8+K11*'Programas e Observações'!$C$9+L11*('Programas e Observações'!$C$8+'Programas e Observações'!$C$9)+M11*'Programas e Observações'!$C$10) -> 284892.96 | AI11: =12*(J11*'Programas e Observações'!$D$8+K11*'Programas e Observações'!$D$9+L11*('Programas e Observações'!$D$8+'Programas e Observações'!$D$9)+M11*'Programas e Observações'!$D$10) -> 524857.68 | AJ11: 720 moradores pegam remédio de pressão ou diabetes de graça na Farmácia Popular | AK11: Sem o programa, gastariam pelo menos R$ 285 mil por ano
A12: 1100114 | B12: 110011 | C12: Jaru | D12: RO | E12: 11003 | F12: Central | G12: 55682 | H12: =G12<'Programas e Observações'!$C$11 -> FALSE | I12: 684 | J12: 251 | K12: 61 | L12: 126 | M12: 4 | N12: 572 | O12: 124 | P12: 4 | Q12: 75 | R12: =IF(G12>0,1000*I12/G12,0) -> 12.284042 | S12: =IF(G12>0,1000*J12/G12,0) -> 4.5077404 | T12: =IF(G12>0,1000*K12/G12,0) -> 1.0955066 | U12: =IF(G12>0,1000*L12/G12,0) -> 2.2628498 | V12: =IF(G12>0,1000*M12/G12,0) -> 0.0718365 | W12: =IF(G12>0,1000*N12/G12,0) -> 10.27262 | X12: =IF(G12>0,1000*O12/G12,0) -> 2.2269315 | Y12: =SUMIFS($I$2:$I$5572,$E$2:$E$5572,E12) -> 5999 | Z12: =SUMIFS($J$2:$J$5572,$E$2:$E$5572,E12) -> 2842 | AA12: =SUMIFS($K$2:$K$5572,$E$2:$E$5572,E12) -> 444 | AB12: =SUMIFS($L$2:$L$5572,$E$2:$E$5572,E12) -> 1118 | AC12: =SUMIFS($M$2:$M$5572,$E$2:$E$5572,E12) -> 101 | AD12: =SUMIFS($N$2:$N$5572,$E$2:$E$5572,E12) -> 3467 | AE12: =SUMIFS($O$2:$O$5572,$E$2:$E$5572,E12) -> 774 | AF12: =SUMIFS($P$2:$P$5572,$E$2:$E$5572,E12) -> 18 | AG12: =IF(SUMIFS($G$2:$G$5572,$E$2:$E$5572,E12)>0,1000*Y12/SUMIFS($G$2:$G$5572,$E$2:$E$5572,E12),0) -> 16.909213 | AH12: =12*(J12*'Programas e Observações'!$C$8+K12*'Programas e Observações'!$C$9+L12*('Programas e Observações'!$C$8+'Programas e Observações'!$C$9)+M12*'Programas e Observações'!$C$10) -> 172239.12 | AI12: =12*(J12*'Programas e Observações'!$D$8+K12*'Programas e Observações'!$D$9+L12*('Programas e Observações'!$D$8+'Programas e Observações'!$D$9)+M12*'Programas e Observações'!$D$10) -> 311919.72 | AJ12: 438 moradores pegam remédio de pressão ou diabetes de graça na Farmácia Popular | AK12: Sem o programa, gastariam pelo menos R$ 172 mil por ano
A13: 1100122 | B13: 110012 | C13: Ji-Paraná | D13: RO | E13: 11003 | F13: Central | G13: 140101 | H13: =G13<'Programas e Observações'!$C$11 -> FALSE | I13: 1907 | J13: 713 | K13: 166 | L13: 276 | M13: 27 | N13: 1369 | O13: 280 | P13: 4 | Q13: 373 | R13: =IF(G13>0,1000*I13/G13,0) -> 13.611609 | S13: =IF(G13>0,1000*J13/G13,0) -> 5.0891857 | T13: =IF(G13>0,1000*K13/G13,0) -> 1.1848595 | U13: =IF(G13>0,1000*L13/G13,0) -> 1.9700074 | V13: =IF(G13>0,1000*M13/G13,0) -> 0.19271811 | W13: =IF(G13>0,1000*N13/G13,0) -> 9.771522 | X13: =IF(G13>0,1000*O13/G13,0) -> 1.9985582 | Y13: =SUMIFS($I$2:$I$5572,$E$2:$E$5572,E13) -> 5999 | Z13: =SUMIFS($J$2:$J$5572,$E$2:$E$5572,E13) -> 2842 | AA13: =SUMIFS($K$2:$K$5572,$E$2:$E$5572,E13) -> 444 | AB13: =SUMIFS($L$2:$L$5572,$E$2:$E$5572,E13) -> 1118 | AC13: =SUMIFS($M$2:$M$5572,$E$2:$E$5572,E13) -> 101 | AD13: =SUMIFS($N$2:$N$5572,$E$2:$E$5572,E13) -> 3467 | AE13: =SUMIFS($O$2:$O$5572,$E$2:$E$5572,E13) -> 774 | AF13: =SUMIFS($P$2:$P$5572,$E$2:$E$5572,E13) -> 18 | AG13: =IF(SUMIFS($G$2:$G$5572,$E$2:$E$5572,E13)>0,1000*Y13/SUMIFS($G$2:$G$5572,$E$2:$E$5572,E13),0) -> 16.909213 | AH13: =12*(J13*'Programas e Observações'!$C$8+K13*'Programas e Observações'!$C$9+L13*('Programas e Observações'!$C$8+'Programas e Observações'!$C$9)+M13*'Programas e Observações'!$C$10) -> 435806.76 | AI13: =12*(J13*'Programas e Observações'!$D$8+K13*'Programas e Observações'!$D$9+L13*('Programas e Observações'!$D$8+'Programas e Observações'!$D$9)+M13*'Programas e Observações'!$D$10) -> 801423.48 | AJ13: 1.155 moradores pegam remédio de pressão ou diabetes de graça na Farmácia Popular | AK13: Sem o programa, gastariam pelo menos R$ 436 mil por ano
A14: 1100130 | B14: 110013 | C14: Machadinho D'Oeste | D14: RO | E14: 11001 | F14: Vale do Jamari | G14: 34149 | H14: =G14<'Programas e Observações'!$C$11 -> FALSE | I14: 333 | J14: 187 | K14: 19 | L14: 30 | M14: 5 | N14: 226 | O14: 51 | P14: 3 | R14: =IF(G14>0,1000*I14/G14,0) -> 9.7513836 | S14: =IF(G14>0,1000*J14/G14,0) -> 5.4760022 | T14: =IF(G14>0,1000*K14/G14,0) -> 0.55638525 | U14: =IF(G14>0,1000*L14/G14,0) -> 0.87850303 | V14: =IF(G14>0,1000*M14/G14,0) -> 0.14641717 | W14: =IF(G14>0,1000*N14/G14,0) -> 6.6180562 | X14: =IF(G14>0,1000*O14/G14,0) -> 1.4934552 | Y14: =SUMIFS($I$2:$I$5572,$E$2:$E$5572,E14) -> 3070 | Z14: =SUMIFS($J$2:$J$5572,$E$2:$E$5572,E14) -> 1523 | AA14: =SUMIFS($K$2:$K$5572,$E$2:$E$5572,E14) -> 232 | AB14: =SUMIFS($L$2:$L$5572,$E$2:$E$5572,E14) -> 477 | AC14: =SUMIFS($M$2:$M$5572,$E$2:$E$5572,E14) -> 83 | AD14: =SUMIFS($N$2:$N$5572,$E$2:$E$5572,E14) -> 2055 | AE14: =SUMIFS($O$2:$O$5572,$E$2:$E$5572,E14) -> 401 | AF14: =SUMIFS($P$2:$P$5572,$E$2:$E$5572,E14) -> 13 | AG14: =IF(SUMIFS($G$2:$G$5572,$E$2:$E$5572,E14)>0,1000*Y14/SUMIFS($G$2:$G$5572,$E$2:$E$5572,E14),0) -> 12.973622 | AH14: =12*(J14*'Programas e Observações'!$C$8+K14*'Programas e Observações'!$C$9+L14*('Programas e Observações'!$C$8+'Programas e Observações'!$C$9)+M14*'Programas e Observações'!$C$10) -> 70693.2 | AI14: =12*(J14*'Programas e Observações'!$D$8+K14*'Programas e Observações'!$D$9+L14*('Programas e Observações'!$D$8+'Programas e Observações'!$D$9)+M14*'Programas e Observações'!$D$10) -> 149864.88 | AJ14: 236 moradores pegam remédio de pressão ou diabetes de graça na Farmácia Popular | AK14: Sem o programa, gastariam pelo menos R$ 71 mil por ano
A15: 1100148 | B15: 110014 | C15: Nova Brasilândia D'Oeste | D15: RO | E15: 11005 | F15: Zona da Mata | G15: 16374 | H15: =G15<'Programas e Observações'!$C$11 -> TRUE | I15: 212 | J15: 96 | K15: 30 | L15: 37 | M15: 4 | N15: 218 | O15: 37 | P15: 1 | R15: =IF(G15>0,1000*I15/G15,0) -> 12.947356 | S15: =IF(G15>0,1000*J15/G15,0) -> 5.8629535 | T15: =IF(G15>0,1000*K15/G15,0) -> 1.832173 | U15: =IF(G15>0,1000*L15/G15,0) -> 2.25968 | V15: =IF(G15>0,1000*M15/G15,0) -> 0.24428973 | W15: =IF(G15>0,1000*N15/G15,0) -> 13.31379 | X15: =IF(G15>0,1000*O15/G15,0) -> 2.25968 | Y15: =SUMIFS($I$2:$I$5572,$E$2:$E$5572,E15) -> 3387 | Z15: =SUMIFS($J$2:$J$5572,$E$2:$E$5572,E15) -> 1912 | AA15: =SUMIFS($K$2:$K$5572,$E$2:$E$5572,E15) -> 196 | AB15: =SUMIFS($L$2:$L$5572,$E$2:$E$5572,E15) -> 835 | AC15: =SUMIFS($M$2:$M$5572,$E$2:$E$5572,E15) -> 38 | AD15: =SUMIFS($N$2:$N$5572,$E$2:$E$5572,E15) -> 1751 | AE15: =SUMIFS($O$2:$O$5572,$E$2:$E$5572,E15) -> 314 | AF15: =SUMIFS($P$2:$P$5572,$E$2:$E$5572,E15) -> 7 | AG15: =IF(SUMIFS($G$2:$G$5572,$E$2:$E$5572,E15)>0,1000*Y15/SUMIFS($G$2:$G$5572,$E$2:$E$5572,E15),0) -> 24.545613 | AH15: =12*(J15*'Programas e Observações'!$C$8+K15*'Programas e Observações'!$C$9+L15*('Programas e Observações'!$C$8+'Programas e Observações'!$C$9)+M15*'Programas e Observações'!$C$10) -> 62652.72 | AI15: =12*(J15*'Programas e Observações'!$D$8+K15*'Programas e Observações'!$D$9+L15*('Programas e Observações'!$D$8+'Programas e Observações'!$D$9)+M15*'Programas e Observações'!$D$10) -> 111989.16 | AJ15: 163 moradores pegam remédio de pressão ou diabetes de graça na Farmácia Popular | AK15: Sem o programa, gastariam pelo menos R$ 63 mil por ano
A16: 1100155 | B16: 110015 | C16: Ouro Preto do Oeste | D16: RO | E16: 11003 | F16: Central | G16: 38684 | H16: =G16<'Programas e Observações'!$C$11 -> FALSE | I16: 983 | J16: 474 | K16: 76 | L16: 235 | M16: 13 | N16: 293 | O16: 112 | P16: 3 | R16: =IF(G16>0,1000*I16/G16,0) -> 25.411023 | S16: =IF(G16>0,1000*J16/G16,0) -> 12.253128 | T16: =IF(G16>0,1000*K16/G16,0) -> 1.9646365 | U16: =IF(G16>0,1000*L16/G16,0) -> 6.074863 | V16: =IF(G16>0,1000*M16/G16,0) -> 0.33605625 | W16: =IF(G16>0,1000*N16/G16,0) -> 7.5741909 | X16: =IF(G16>0,1000*O16/G16,0) -> 2.8952539 | Y16: =SUMIFS($I$2:$I$5572,$E$2:$E$5572,E16) -> 5999 | Z16: =SUMIFS($J$2:$J$5572,$E$2:$E$5572,E16) -> 2842 | AA16: =SUMIFS($K$2:$K$5572,$E$2:$E$5572,E16) -> 444 | AB16: =SUMIFS($L$2:$L$5572,$E$2:$E$5572,E16) -> 1118 | AC16: =SUMIFS($M$2:$M$5572,$E$2:$E$5572,E16) -> 101 | AD16: =SUMIFS($N$2:$N$5572,$E$2:$E$5572,E16) -> 3467 | AE16: =SUMIFS($O$2:$O$5572,$E$2:$E$5572,E16) -> 774 | AF16: =SUMIFS($P$2:$P$5572,$E$2:$E$5572,E16) -> 18 | AG16: =IF(SUMIFS($G$2:$G$5572,$E$2:$E$5572,E16)>0,1000*Y16/SUMIFS($G$2:$G$5572,$E$2:$E$5572,E16),0) -> 16.909213 | AH16: =12*(J16*'Programas e Observações'!$C$8+K16*'Programas e Observações'!$C$9+L16*('Programas e Observações'!$C$8+'Programas e Observações'!$C$9)+M16*'Programas e Observações'!$C$10) -> 306085.44 | AI16: =12*(J16*'Programas e Observações'!$D$8+K16*'Programas e Observações'!$D$9+L16*('Programas e Observações'!$D$8+'Programas e Observações'!$D$9)+M16*'Programas e Observações'!$D$10) -> 567973.44 | AJ16: 785 moradores pegam remédio de pressão ou diabetes de graça na Farmácia Popular | AK16: Sem o programa, gastariam pelo menos R$ 306 mil por ano
A17: 1100189 | B17: 110018 | C17: Pimenta Bueno | D17: RO | E17: 11002 | F17: Café | G17: 39220 | H17: =G17<'Programas e Observações'!$C$11 -> FALSE | I17: 1823 | J17: 982 | K17: 147 | L17: 453 | M17: 55 | N17: 371 | O17: 65 | P17: 2 | R17: =IF(G17>0,1000*I17/G17,0) -> 46.481387 | S17: =IF(G17>0,1000*J17/G17,0) -> 25.038246 | T17: =IF(G17>0,1000*K17/G17,0) -> 3.7480877 | U17: =IF(G17>0,1000*L17/G17,0) -> 11.550229 | V17: =IF(G17>0,1000*M17/G17,0) -> 1.4023457 | W17: =IF(G17>0,1000*N17/G17,0) -> 9.4594595 | X17: =IF(G17>0,1000*O17/G17,0) -> 1.6573177 | Y17: =SUMIFS($I$2:$I$5572,$E$2:$E$5572,E17) -> 5842 | Z17: =SUMIFS($J$2:$J$5572,$E$2:$E$5572,E17) -> 3287 | AA17: =SUMIFS($K$2:$K$5572,$E$2:$E$5572,E17) -> 380 | AB17: =SUMIFS($L$2:$L$5572,$E$2:$E$5572,E17) -> 1380 | AC17: =SUMIFS($M$2:$M$5572,$E$2:$E$5572,E17) -> 222 | AD17: =SUMIFS($N$2:$N$5572,$E$2:$E$5572,E17) -> 1947 | AE17: =SUMIFS($O$2:$O$5572,$E$2:$E$5572,E17) -> 442 | AF17: =SUMIFS($P$2:$P$5572,$E$2:$E$5572,E17) -> 14 | AG17: =IF(SUMIFS($G$2:$G$5572,$E$2:$E$5572,E17)>0,1000*Y17/SUMIFS($G$2:$G$5572,$E$2:$E$5572,E17),0) -> 31.456463 | AH17: =12*(J17*'Programas e Observações'!$C$8+K17*'Programas e Observações'!$C$9+L17*('Programas e Observações'!$C$8+'Programas e Observações'!$C$9)+M17*'Programas e Observações'!$C$10) -> 619631.4 | AI17: =12*(J17*'Programas e Observações'!$D$8+K17*'Programas e Observações'!$D$9+L17*('Programas e Observações'!$D$8+'Programas e Observações'!$D$9)+M17*'Programas e Observações'!$D$10) -> 1149460.2 | AJ17: 1.582 moradores pegam remédio de pressão ou diabetes de graça na Farmácia Popular | AK17: Sem o programa, gastariam pelo menos R$ 620 mil por ano
A18: 1100205 | B18: 110020 | C18: Porto Velho | D18: RO | E18: 11004 | F18: Madeira-Mamoré | G18: 517709 | H18: =G18<'Programas e Observações'!$C$11 -> FALSE | I18: 5535 | J18: 1289 | K18: 893 | L18: 1061 | M18: 234 | N18: 5304 | O18: 1367 | P18: 19 | Q18: 2756 | R18: =IF(G18>0,1000*I18/G18,0) -> 10.691334 | S18: =IF(G18>0,1000*J18/G18,0) -> 2.4898157 | T18: =IF(G18>0,1000*K18/G18,0) -> 1.7249072 | U18: =IF(G18>0,1000*L18/G18,0) -> 2.0494139 | V18: =IF(G18>0,1000*M18/G18,0) -> 0.45199137 | W18: =IF(G18>0,1000*N18/G18,0) -> 10.245138 | X18: =IF(G18>0,1000*O18/G18,0) -> 2.6404795 | Y18: =SUMIFS($I$2:$I$5572,$E$2:$E$5572,E18) -> 6894 | Z18: =SUMIFS($J$2:$J$5572,$E$2:$E$5572,E18) -> 1916 | AA18: =SUMIFS($K$2:$K$5572,$E$2:$E$5572,E18) -> 1016 | AB18: =SUMIFS($L$2:$L$5572,$E$2:$E$5572,E18) -> 1376 | AC18: =SUMIFS($M$2:$M$5572,$E$2:$E$5572,E18) -> 263 | AD18: =SUMIFS($N$2:$N$5572,$E$2:$E$5572,E18) -> 5769 | AE18: =SUMIFS($O$2:$O$5572,$E$2:$E$5572,E18) -> 1523 | AF18: =SUMIFS($P$2:$P$5572,$E$2:$E$5572,E18) -> 22 | AG18: =IF(SUMIFS($G$2:$G$5572,$E$2:$E$5572,E18)>0,1000*Y18/SUMIFS($G$2:$G$5572,$E$2:$E$5572,E18),0) -> 11.056139 | AH18: =12*(J18*'Programas e Observações'!$C$8+K18*'Programas e Observações'!$C$9+L18*('Programas e Observações'!$C$8+'Programas e Observações'!$C$9)+M18*'Programas e Observações'!$C$10) -> 1585461.1 | AI18: =12*(J18*'Programas e Observações'!$D$8+K18*'Programas e Observações'!$D$9+L18*('Programas e Observações'!$D$8+'Programas e Observações'!$D$9)+M18*'Programas e Observações'!$D$10) -> 2476163 | AJ18: 3.243 moradores pegam remédio de pressão ou diabetes de graça na Farmácia Popular | AK18: Sem o programa, gastariam pelo menos R$ 1,6 milhões por ano
A19: 1100254 | B19: 110025 | C19: Presidente Médici | D19: RO | E19: 11003 | F19: Central | G19: 20443 | H19: =G19<'Programas e Observações'!$C$11 -> FALSE | I19: 506 | J19: 250 | K19: 31 | L19: 89 | M19: 17 | N19: 284 | O19: 49 | P19: 3 | R19: =IF(G19>0,1000*I19/G19,0) -> 24.751749 | S19: =IF(G19>0,1000*J19/G19,0) -> 12.229125 | T19: =IF(G19>0,1000*K19/G19,0) -> 1.5164115 | U19: =IF(G19>0,1000*L19/G19,0) -> 4.3535685 | V19: =IF(G19>0,1000*M19/G19,0) -> 0.83158049 | W19: =IF(G19>0,1000*N19/G19,0) -> 13.892286 | X19: =IF(G19>0,1000*O19/G19,0) -> 2.3969085 | Y19: =SUMIFS($I$2:$I$5572,$E$2:$E$5572,E19) -> 5999 | Z19: =SUMIFS($J$2:$J$5572,$E$2:$E$5572,E19) -> 2842 | AA19: =SUMIFS($K$2:$K$5572,$E$2:$E$5572,E19) -> 444 | AB19: =SUMIFS($L$2:$L$5572,$E$2:$E$5572,E19) -> 1118 | AC19: =SUMIFS($M$2:$M$5572,$E$2:$E$5572,E19) -> 101 | AD19: =SUMIFS($N$2:$N$5572,$E$2:$E$5572,E19) -> 3467 | AE19: =SUMIFS($O$2:$O$5572,$E$2:$E$5572,E19) -> 774 | AF19: =SUMIFS($P$2:$P$5572,$E$2:$E$5572,E19) -> 18 | AG19: =IF(SUMIFS($G$2:$G$5572,$E$2:$E$5572,E19)>0,1000*Y19/SUMIFS($G$2:$G$5572,$E$2:$E$5572,E19),0) -> 16.909213 | AH19: =12*(J19*'Programas e Observações'!$C$8+K19*'Programas e Observações'!$C$9+L19*('Programas e Observações'!$C$8+'Programas e Observações'!$C$9)+M19*'Programas e Observações'!$C$10) -> 137417.16 | AI19: =12*(J19*'Programas e Observações'!$D$8+K19*'Programas e Observações'!$D$9+L19*('Programas e Observações'!$D$8+'Programas e Observações'!$D$9)+M19*'Programas e Observações'!$D$10) -> 262169.88 | AJ19: 370 moradores pegam remédio de pressão ou diabetes de graça na Farmácia Popular | AK19: Sem o programa, gastariam pelo menos R$ 137 mil por ano
A20: 1100262 | B20: 110026 | C20: Rio Crespo | D20: RO | E20: 11001 | F20: Vale do Jamari | G20: 3767 | H20: =G20<'Programas e Observações'!$C$11 -> TRUE | I20: 12 | J20: 7 | K20: 0 | L20: 0 | M20: 0 | N20: 36 | O20: 5 | P20: 0 | R20: =IF(G20>0,1000*I20/G20,0) -> 3.1855588 | S20: =IF(G20>0,1000*J20/G20,0) -> 1.8582426 | T20: =IF(G20>0,1000*K20/G20,0) -> 0 | U20: =IF(G20>0,1000*L20/G20,0) -> 0 | V20: =IF(G20>0,1000*M20/G20,0) -> 0 | W20: =IF(G20>0,1000*N20/G20,0) -> 9.5566764 | X20: =IF(G20>0,1000*O20/G20,0) -> 1.3273162 | Y20: =SUMIFS($I$2:$I$5572,$E$2:$E$5572,E20) -> 3070 | Z20: =SUMIFS($J$2:$J$5572,$E$2:$E$5572,E20) -> 1523 | AA20: =SUMIFS($K$2:$K$5572,$E$2:$E$5572,E20) -> 232 | AB20: =SUMIFS($L$2:$L$5572,$E$2:$E$5572,E20) -> 477 | AC20: =SUMIFS($M$2:$M$5572,$E$2:$E$5572,E20) -> 83 | AD20: =SUMIFS($N$2:$N$5572,$E$2:$E$5572,E20) -> 2055 | AE20: =SUMIFS($O$2:$O$5572,$E$2:$E$5572,E20) -> 401 | AF20: =SUMIFS($P$2:$P$5572,$E$2:$E$5572,E20) -> 13 | AG20: =IF(SUMIFS($G$2:$G$5572,$E$2:$E$5572,E20)>0,1000*Y20/SUMIFS($G$2:$G$5572,$E$2:$E$5572,E20),0) -> 12.973622 | AH20: =12*(J20*'Programas e Observações'!$C$8+K20*'Programas e Observações'!$C$9+L20*('Programas e Observações'!$C$8+'Programas e Observações'!$C$9)+M20*'Programas e Observações'!$C$10) -> 1390.2 | AI20: =12*(J20*'Programas e Observações'!$D$8+K20*'Programas e Observações'!$D$9+L20*('Programas e Observações'!$D$8+'Programas e Observações'!$D$9)+M20*'Programas e Observações'!$D$10) -> 3907.68 | AJ20: 7 moradores pegam remédio de pressão ou diabetes de graça na Farmácia Popular | AK20: Sem o programa, gastariam pelo menos R$ 1 mil por ano
A21: 1100288 | B21: 110028 | C21: Rolim de Moura | D21: RO | E21: 11005 | F21: Zona da Mata | G21: 62959 | H21: =G21<'Programas e Observações'!$C$11 -> FALSE | I21: 1635 | J21: 874 | K21: 66 | L21: 509 | M21: 7 | N21: 697 | O21: 128 | P21: 3 | Q21: 126 | R21: =IF(G21>0,1000*I21/G21,0) -> 25.969282 | S21: =IF(G21>0,1000*J21/G21,0) -> 13.88205 | T21: =IF(G21>0,1000*K21/G21,0) -> 1.0483013 | U21: =IF(G21>0,1000*L21/G21,0) -> 8.0846265 | V21: =IF(G21>0,1000*M21/G21,0) -> 0.11118347 | W21: =IF(G21>0,1000*N21/G21,0) -> 11.070697 | X21: =IF(G21>0,1000*O21/G21,0) -> 2.0330691 | Y21: =SUMIFS($I$2:$I$5572,$E$2:$E$5572,E21) -> 3387 | Z21: =SUMIFS($J$2:$J$5572,$E$2:$E$5572,E21) -> 1912 | AA21: =SUMIFS($K$2:$K$5572,$E$2:$E$5572,E21) -> 196 | AB21: =SUMIFS($L$2:$L$5572,$E$2:$E$5572,E21) -> 835 | AC21: =SUMIFS($M$2:$M$5572,$E$2:$E$5572,E21) -> 38 | AD21: =SUMIFS($N$2:$N$5572,$E$2:$E$5572,E21) -> 1751 | AE21: =SUMIFS($O$2:$O$5572,$E$2:$E$5572,E21) -> 314 | AF21: =SUMIFS($P$2:$P$5572,$E$2:$E$5572,E21) -> 7 | AG21: =IF(SUMIFS($G$2:$G$5572,$E$2:$E$5572,E21)>0,1000*Y21/SUMIFS($G$2:$G$5572,$E$2:$E$5572,E21),0) -> 24.545613 | AH21: =12*(J21*'Programas e Observações'!$C$8+K21*'Programas e Observações'!$C$9+L21*('Programas e Observações'!$C$8+'Programas e Observações'!$C$9)+M21*'Programas e Observações'!$C$10) -> 571259.76 | AI21: =12*(J21*'Programas e Observações'!$D$8+K21*'Programas e Observações'!$D$9+L21*('Programas e Observações'!$D$8+'Programas e Observações'!$D$9)+M21*'Programas e Observações'!$D$10) -> 1081161.8 | AJ21: 1.449 moradores pegam remédio de pressão ou diabetes de graça na Farmácia Popular | AK21: Sem o programa, gastariam pelo menos R$ 571 mil por ano
A22: 1100296 | B22: 110029 | C22: Santa Luzia D'Oeste | D22: RO | E22: 11005 | F22: Zona da Mata | G22: 7837 | H22: =G22<'Programas e Observações'!$C$11 -> TRUE | I22: 271 | J22: 153 | K22: 16 | L22: 49 | M22: 3 | N22: 131 | O22: 22 | P22: 0 | R22: =IF(G22>0,1000*I22/G22,0) -> 34.579558 | S22: =IF(G22>0,1000*J22/G22,0) -> 19.522777 | T22: =IF(G22>0,1000*K22/G22,0) -> 2.0415976 | U22: =IF(G22>0,1000*L22/G22,0) -> 6.2523925 | V22: =IF(G22>0,1000*M22/G22,0) -> 0.38279954 | W22: =IF(G22>0,1000*N22/G22,0) -> 16.71558 | X22: =IF(G22>0,1000*O22/G22,0) -> 2.8071966 | Y22: =SUMIFS($I$2:$I$5572,$E$2:$E$5572,E22) -> 3387 | Z22: =SUMIFS($J$2:$J$5572,$E$2:$E$5572,E22) -> 1912 | AA22: =SUMIFS($K$2:$K$5572,$E$2:$E$5572,E22) -> 196 | AB22: =SUMIFS($L$2:$L$5572,$E$2:$E$5572,E22) -> 835 | AC22: =SUMIFS($M$2:$M$5572,$E$2:$E$5572,E22) -> 38 | AD22: =SUMIFS($N$2:$N$5572,$E$2:$E$5572,E22) -> 1751 | AE22: =SUMIFS($O$2:$O$5572,$E$2:$E$5572,E22) -> 314 | AF22: =SUMIFS($P$2:$P$5572,$E$2:$E$5572,E22) -> 7 | AG22: =IF(SUMIFS($G$2:$G$5572,$E$2:$E$5572,E22)>0,1000*Y22/SUMIFS($G$2:$G$5572,$E$2:$E$5572,E22),0) -> 24.545613 | AH22: =12*(J22*'Programas e Observações'!$C$8+K22*'Programas e Observações'!$C$9+L22*('Programas e Observações'!$C$8+'Programas e Observações'!$C$9)+M22*'Programas e Observações'!$C$10) -> 74810.04 | AI22: =12*(J22*'Programas e Observações'!$D$8+K22*'Programas e Observações'!$D$9+L22*('Programas e Observações'!$D$8+'Programas e Observações'!$D$9)+M22*'Programas e Observações'!$D$10) -> 148904.16 | AJ22: 218 moradores pegam remédio de pressão ou diabetes de graça na Farmácia Popular | AK22: Sem o programa, gastariam pelo menos R$ 75 mil por ano
A23: 1100304 | B23: 110030 | C23: Vilhena | D23: RO | E23: 11006 | F23: Cone Sul | G23: 109651 | H23: =G23<'Programas e Observações'!$C$11 -> FALSE | I23: 3793 | J23: 1954 | K23: 342 | L23: 900 | M23: 61 | N23: 957 | O23: 163 | P23: 3 | Q23: 323 | R23: =IF(G23>0,1000*I23/G23,0) -> 34.591568 | S23: =IF(G23>0,1000*J23/G23,0) -> 17.820175 | T23: =IF(G23>0,1000*K23/G23,0) -> 3.1189866 | U23: =IF(G23>0,1000*L23/G23,0) -> 8.2078595 | V23: =IF(G23>0,1000*M23/G23,0) -> 0.55631048 | W23: =IF(G23>0,1000*N23/G23,0) -> 8.7276906 | X23: =IF(G23>0,1000*O23/G23,0) -> 1.4865346 | Y23: =SUMIFS($I$2:$I$5572,$E$2:$E$5572,E23) -> 6176 | Z23: =SUMIFS($J$2:$J$5572,$E$2:$E$5572,E23) -> 3173 | AA23: =SUMIFS($K$2:$K$5572,$E$2:$E$5572,E23) -> 544 | AB23: =SUMIFS($L$2:$L$5572,$E$2:$E$5572,E23) -> 1434 | AC23: =SUMIFS($M$2:$M$5572,$E$2:$E$5572,E23) -> 238 | AD23: =SUMIFS($N$2:$N$5572,$E$2:$E$5572,E23) -> 1653 | AE23: =SUMIFS($O$2:$O$5572,$E$2:$E$5572,E23) -> 277 | AF23: =SUMIFS($P$2:$P$5572,$E$2:$E$5572,E23) -> 5 | AG23: =IF(SUMIFS($G$2:$G$5572,$E$2:$E$5572,E23)>0,1000*Y23/SUMIFS($G$2:$G$5572,$E$2:$E$5572,E23),0) -> 36.48889 | AH23: =12*(J23*'Programas e Observações'!$C$8+K23*'Programas e Observações'!$C$9+L23*('Programas e Observações'!$C$8+'Programas e Observações'!$C$9)+M23*'Programas e Observações'!$C$10) -> 1231643.3 | AI23: =12*(J23*'Programas e Observações'!$D$8+K23*'Programas e Observações'!$D$9+L23*('Programas e Observações'!$D$8+'Programas e Observações'!$D$9)+M23*'Programas e Observações'!$D$10) -> 2285754.1 | AJ23: 3.196 moradores pegam remédio de pressão ou diabetes de graça na Farmácia Popular | AK23: Sem o programa, gastariam pelo menos R$ 1,2 milhões por ano
A24: 1100320 | B24: 110032 | C24: São Miguel do Guaporé | D24: RO | E24: 11003 | F24: Central | G24: 22305 | H24: =G24<'Programas e Observações'!$C$11 -> FALSE | I24: 0 | J24: 0 | K24: 0 | L24: 0 | M24: 0 | N24: 164 | O24: 46 | P24: 1 | R24: =IF(G24>0,1000*I24/G24,0) -> 0 | S24: =IF(G24>0,1000*J24/G24,0) -> 0 | T24: =IF(G24>0,1000*K24/G24,0) -> 0 | U24: =IF(G24>0,1000*L24/G24,0) -> 0 | V24: =IF(G24>0,1000*M24/G24,0) -> 0 | W24: =IF(G24>0,1000*N24/G24,0) -> 7.3526115 | X24: =IF(G24>0,1000*O24/G24,0) -> 2.0623179 | Y24: =SUMIFS($I$2:$I$5572,$E$2:$E$5572,E24) -> 5999 | Z24: =SUMIFS($J$2:$J$5572,$E$2:$E$5572,E24) -> 2842 | AA24: =SUMIFS($K$2:$K$5572,$E$2:$E$5572,E24) -> 444 | AB24: =SUMIFS($L$2:$L$5572,$E$2:$E$5572,E24) -> 1118 | AC24: =SUMIFS($M$2:$M$5572,$E$2:$E$5572,E24) -> 101 | AD24: =SUMIFS($N$2:$N$5572,$E$2:$E$5572,E24) -> 3467 | AE24: =SUMIFS($O$2:$O$5572,$E$2:$E$5572,E24) -> 774 | AF24: =SUMIFS($P$2:$P$5572,$E$2:$E$5572,E24) -> 18 | AG24: =IF(SUMIFS($G$2:$G$5572,$E$2:$E$5572,E24)>0,1000*Y24/SUMIFS($G$2:$G$5572,$E$2:$E$5572,E24),0) -> 16.909213 | AH24: =12*(J24*'Programas e Observações'!$C$8+K24*'Programas e Observações'!$C$9+L24*('Programas e Observações'!$C$8+'Programas e Observações'!$C$9)+M24*'Programas e Observações'!$C$10) -> 0 | AI24: =12*(J24*'Programas e Observações'!$D$8+K24*'Programas e Observações'!$D$9+L24*('Programas e Observações'!$D$8+'Programas e Observações'!$D$9)+M24*'Programas e Observações'!$D$10) -> 0 | AJ24: 0 moradores pegam remédio de pressão ou diabetes de graça na Farmácia Popular | AK24: Sem o programa, gastariam pelo menos R$ 0 mil por ano
A25: 1100338 | B25: 110033 | C25: Nova Mamoré | D25: RO | E25: 11004 | F25: Madeira-Mamoré | G25: 28701 | H25: =G25<'Programas e Observações'!$C$11 -> FALSE | I25: 128 | J25: 28 | K25: 19 | L25: 20 | M25: 5 | N25: 132 | O25: 33 | P25: 0 | R25: =IF(G25>0,1000*I25/G25,0) -> 4.4597749 | S25: =IF(G25>0,1000*J25/G25,0) -> 0.97557576 | T25: =IF(G25>0,1000*K25/G25,0) -> 0.66199784 | U25: =IF(G25>0,1000*L25/G25,0) -> 0.69683983 | V25: =IF(G25>0,1000*M25/G25,0) -> 0.17420996 | W25: =IF(G25>0,1000*N25/G25,0) -> 4.5991429 | X25: =IF(G25>0,1000*O25/G25,0) -> 1.1497857 | Y25: =SUMIFS($I$2:$I$5572,$E$2:$E$5572,E25) -> 6894 | Z25: =SUMIFS($J$2:$J$5572,$E$2:$E$5572,E25) -> 1916 | AA25: =SUMIFS($K$2:$K$5572,$E$2:$E$5572,E25) -> 1016 | AB25: =SUMIFS($L$2:$L$5572,$E$2:$E$5572,E25) -> 1376 | AC25: =SUMIFS($M$2:$M$5572,$E$2:$E$5572,E25) -> 263 | AD25: =SUMIFS($N$2:$N$5572,$E$2:$E$5572,E25) -> 5769 | AE25: =SUMIFS($O$2:$O$5572,$E$2:$E$5572,E25) -> 1523 | AF25: =SUMIFS($P$2:$P$5572,$E$2:$E$5572,E25) -> 22 | AG25: =IF(SUMIFS($G$2:$G$5572,$E$2:$E$5572,E25)>0,1000*Y25/SUMIFS($G$2:$G$5572,$E$2:$E$5572,E25),0) -> 11.056139 | AH25: =12*(J25*'Programas e Observações'!$C$8+K25*'Programas e Observações'!$C$9+L25*('Programas e Observações'!$C$8+'Programas e Observações'!$C$9)+M25*'Programas e Observações'!$C$10) -> 32035.8 | AI25: =12*(J25*'Programas e Observações'!$D$8+K25*'Programas e Observações'!$D$9+L25*('Programas e Observações'!$D$8+'Programas e Observações'!$D$9)+M25*'Programas e Observações'!$D$10) -> 50212.32 | AJ25: 67 moradores pegam remédio de pressão ou diabetes de graça na Farmácia Popular | AK25: Sem o programa, gastariam pelo menos R$ 32 mil por ano
A26: 1100346 | B26: 110034 | C26: Alvorada D'Oeste | D26: RO | E26: 11003 | F26: Central | G26: 13720 | H26: =G26<'Programas e Observações'!$C$11 -> TRUE | I26: 451 | J26: 257 | K26: 31 | L26: 91 | M26: 28 | N26: 123 | O26: 36 | P26: 0 | R26: =IF(G26>0,1000*I26/G26,0) -> 32.87172 | S26: =IF(G26>0,1000*J26/G26,0) -> 18.731778 | T26: =IF(G26>0,1000*K26/G26,0) -> 2.2594752 | U26: =IF(G26>0,1000*L26/G26,0) -> 6.6326531 | V26: =IF(G26>0,1000*M26/G26,0) -> 2.0408163 | W26: =IF(G26>0,1000*N26/G26,0) -> 8.9650146 | X26: =IF(G26>0,1000*O26/G26,0) -> 2.6239067 | Y26: =SUMIFS($I$2:$I$5572,$E$2:$E$5572,E26) -> 5999 | Z26: =SUMIFS($J$2:$J$5572,$E$2:$E$5572,E26) -> 2842 | AA26: =SUMIFS($K$2:$K$5572,$E$2:$E$5572,E26) -> 444 | AB26: =SUMIFS($L$2:$L$5572,$E$2:$E$5572,E26) -> 1118 | AC26: =SUMIFS($M$2:$M$5572,$E$2:$E$5572,E26) -> 101 | AD26: =SUMIFS($N$2:$N$5572,$E$2:$E$5572,E26) -> 3467 | AE26: =SUMIFS($O$2:$O$5572,$E$2:$E$5572,E26) -> 774 | AF26: =SUMIFS($P$2:$P$5572,$E$2:$E$5572,E26) -> 18 | AG26: =IF(SUMIFS($G$2:$G$5572,$E$2:$E$5572,E26)>0,1000*Y26/SUMIFS($G$2:$G$5572,$E$2:$E$5572,E26),0) -> 16.909213 | AH26: =12*(J26*'Programas e Observações'!$C$8+K26*'Programas e Observações'!$C$9+L26*('Programas e Observações'!$C$8+'Programas e Observações'!$C$9)+M26*'Programas e Observações'!$C$10) -> 146023.44 | AI26: =12*(J26*'Programas e Observações'!$D$8+K26*'Programas e Observações'!$D$9+L26*('Programas e Observações'!$D$8+'Programas e Observações'!$D$9)+M26*'Programas e Observações'!$D$10) -> 274213.2 | AJ26: 379 moradores pegam remédio de pressão ou diabetes de graça na Farmácia Popular | AK26: Sem o programa, gastariam pelo menos R$ 146 mil por ano
A27: 1100379 | B27: 110037 | C27: Alto Alegre dos Parecis | D27: RO | E27: 11005 | F27: Zona da Mata | G27: 12237 | H27: =G27<'Programas e Observações'!$C$11 -> TRUE | I27: 522 | J27: 313 | K27: 27 | L27: 87 | M27: 22 | N27: 182 | O27: 31 | P27: 1 | R27: =IF(G27>0,1000*I27/G27,0) -> 42.657514 | S27: =IF(G27>0,1000*J27/G27,0) -> 25.578165 | T27: =IF(G27>0,1000*K27/G27,0) -> 2.2064231 | U27: =IF(G27>0,1000*L27/G27,0) -> 7.1095857 | V27: =IF(G27>0,1000*M27/G27,0) -> 1.7978263 | W27: =IF(G27>0,1000*N27/G27,0) -> 14.872926 | X27: =IF(G27>0,1000*O27/G27,0) -> 2.5333006 | Y27: =SUMIFS($I$2:$I$5572,$E$2:$E$5572,E27) -> 3387 | Z27: =SUMIFS($J$2:$J$5572,$E$2:$E$5572,E27) -> 1912 | AA27: =SUMIFS($K$2:$K$5572,$E$2:$E$5572,E27) -> 196 | AB27: =SUMIFS($L$2:$L$5572,$E$2:$E$5572,E27) -> 835 | AC27: =SUMIFS($M$2:$M$5572,$E$2:$E$5572,E27) -> 38 | AD27: =SUMIFS($N$2:$N$5572,$E$2:$E$5572,E27) -> 1751 | AE27: =SUMIFS($O$2:$O$5572,$E$2:$E$5572,E27) -> 314 | AF27: =SUMIFS($P$2:$P$5572,$E$2:$E$5572,E27) -> 7 | AG27: =IF(SUMIFS($G$2:$G$5572,$E$2:$E$5572,E27)>0,1000*Y27/SUMIFS($G$2:$G$5572,$E$2:$E$5572,E27),0) -> 24.545613 | AH27: =12*(J27*'Programas e Observações'!$C$8+K27*'Programas e Observações'!$C$9+L27*('Programas e Observações'!$C$8+'Programas e Observações'!$C$9)+M27*'Programas e Observações'!$C$10) -> 149111.76 | AI27: =12*(J27*'Programas e Observações'!$D$8+K27*'Programas e Observações'!$D$9+L27*('Programas e Observações'!$D$8+'Programas e Observações'!$D$9)+M27*'Programas e Observações'!$D$10) -> 295744.32 | AJ27: 427 moradores pegam remédio de pressão ou diabetes de graça na Farmácia Popular | AK27: Sem o programa, gastariam pelo menos R$ 149 mil por ano
A28: 1100403 | B28: 110040 | C28: Alto Paraíso | D28: RO | E28: 11001 | F28: Vale do Jamari | G28: 17467 | H28: =G28<'Programas e Observações'!$C$11 -> TRUE | I28: 188 | J28: 112 | K28: 19 | L28: 43 | M28: 0 | N28: 175 | O28: 37 | P28: 1 | R28: =IF(G28>0,1000*I28/G28,0) -> 10.763153 | S28: =IF(G28>0,1000*J28/G28,0) -> 6.4120914 | T28: =IF(G28>0,1000*K28/G28,0) -> 1.0877655 | U28: =IF(G28>0,1000*L28/G28,0) -> 2.4617851 | V28: =IF(G28>0,1000*M28/G28,0) -> 0 | W28: =IF(G28>0,1000*N28/G28,0) -> 10.018893 | X28: =IF(G28>0,1000*O28/G28,0) -> 2.1182802 | Y28: =SUMIFS($I$2:$I$5572,$E$2:$E$5572,E28) -> 3070 | Z28: =SUMIFS($J$2:$J$5572,$E$2:$E$5572,E28) -> 1523 | AA28: =SUMIFS($K$2:$K$5572,$E$2:$E$5572,E28) -> 232 | AB28: =SUMIFS($L$2:$L$5572,$E$2:$E$5572,E28) -> 477 | AC28: =SUMIFS($M$2:$M$5572,$E$2:$E$5572,E28) -> 83 | AD28: =SUMIFS($N$2:$N$5572,$E$2:$E$5572,E28) -> 2055 | AE28: =SUMIFS($O$2:$O$5572,$E$2:$E$5572,E28) -> 401 | AF28: =SUMIFS($P$2:$P$5572,$E$2:$E$5572,E28) -> 13 | AG28: =IF(SUMIFS($G$2:$G$5572,$E$2:$E$5572,E28)>0,1000*Y28/SUMIFS($G$2:$G$5572,$E$2:$E$5572,E28),0) -> 12.973622 | AH28: =12*(J28*'Programas e Observações'!$C$8+K28*'Programas e Observações'!$C$9+L28*('Programas e Observações'!$C$8+'Programas e Observações'!$C$9)+M28*'Programas e Observações'!$C$10) -> 62365.8 | AI28: =12*(J28*'Programas e Observações'!$D$8+K28*'Programas e Observações'!$D$9+L28*('Programas e Observações'!$D$8+'Programas e Observações'!$D$9)+M28*'Programas e Observações'!$D$10) -> 119449.2 | AJ28: 174 moradores pegam remédio de pressão ou diabetes de graça na Farmácia Popular | AK28: Sem o programa, gastariam pelo menos R$ 62 mil por ano
A29: 1100452 | B29: 110045 | C29: Buritis | D29: RO | E29: 11001 | F29: Vale do Jamari | G29: 30649 | H29: =G29<'Programas e Observações'!$C$11 -> FALSE | I29: 456 | J29: 209 | K29: 50 | L29: 95 | M29: 14 | N29: 287 | O29: 46 | P29: 0 | R29: =IF(G29>0,1000*I29/G29,0) -> 14.878136 | S29: =IF(G29>0,1000*J29/G29,0) -> 6.8191458 | T29: =IF(G29>0,1000*K29/G29,0) -> 1.6313746 | U29: =IF(G29>0,1000*L29/G29,0) -> 3.0996117 | V29: =IF(G29>0,1000*M29/G29,0) -> 0.45678489 | W29: =IF(G29>0,1000*N29/G29,0) -> 9.3640902 | X29: =IF(G29>0,1000*O29/G29,0) -> 1.5008646 | Y29: =SUMIFS($I$2:$I$5572,$E$2:$E$5572,E29) -> 3070 | Z29: =SUMIFS($J$2:$J$5572,$E$2:$E$5572,E29) -> 1523 | AA29: =SUMIFS($K$2:$K$5572,$E$2:$E$5572,E29) -> 232 | AB29: =SUMIFS($L$2:$L$5572,$E$2:$E$5572,E29) -> 477 | AC29: =SUMIFS($M$2:$M$5572,$E$2:$E$5572,E29) -> 83 | AD29: =SUMIFS($N$2:$N$5572,$E$2:$E$5572,E29) -> 2055 | AE29: =SUMIFS($O$2:$O$5572,$E$2:$E$5572,E29) -> 401 | AF29: =SUMIFS($P$2:$P$5572,$E$2:$E$5572,E29) -> 13 | AG29: =IF(SUMIFS($G$2:$G$5572,$E$2:$E$5572,E29)>0,1000*Y29/SUMIFS($G$2:$G$5572,$E$2:$E$5572,E29),0) -> 12.973622 | AH29: =12*(J29*'Programas e Observações'!$C$8+K29*'Programas e Observações'!$C$9+L29*('Programas e Observações'!$C$8+'Programas e Observações'!$C$9)+M29*'Programas e Observações'!$C$10) -> 141619.32 | AI29: =12*(J29*'Programas e Observações'!$D$8+K29*'Programas e Observações'!$D$9+L29*('Programas e Observações'!$D$8+'Programas e Observações'!$D$9)+M29*'Programas e Observações'!$D$10) -> 254281.8 | AJ29: 354 moradores pegam remédio de pressão ou diabetes de graça na Farmácia Popular | AK29: Sem o programa, gastariam pelo menos R$ 142 mil por ano
A30: 1100502 | B30: 110050 | C30: Novo Horizonte do Oeste | D30: RO | E30: 11005 | F30: Zona da Mata | G30: 7972 | H30: =G30<'Programas e Observações'!$C$11 -> TRUE | I30: 269 | J30: 185 | K30: 27 | L30: 50 | M30: 0 | N30: 105 | O30: 18 | P30: 0 | R30: =IF(G30>0,1000*I30/G30,0) -> 33.743101 | S30: =IF(G30>0,1000*J30/G30,0) -> 23.206222 | T30: =IF(G30>0,1000*K30/G30,0) -> 3.386854 | U30: =IF(G30>0,1000*L30/G30,0) -> 6.2719518 | V30: =IF(G30>0,1000*M30/G30,0) -> 0 | W30: =IF(G30>0,1000*N30/G30,0) -> 13.171099 | X30: =IF(G30>0,1000*O30/G30,0) -> 2.2579027 | Y30: =SUMIFS($I$2:$I$5572,$E$2:$E$5572,E30) -> 3387 | Z30: =SUMIFS($J$2:$J$5572,$E$2:$E$5572,E30) -> 1912 | AA30: =SUMIFS($K$2:$K$5572,$E$2:$E$5572,E30) -> 196 | AB30: =SUMIFS($L$2:$L$5572,$E$2:$E$5572,E30) -> 835 | AC30: =SUMIFS($M$2:$M$5572,$E$2:$E$5572,E30) -> 38 | AD30: =SUMIFS($N$2:$N$5572,$E$2:$E$5572,E30) -> 1751 | AE30: =SUMIFS($O$2:$O$5572,$E$2:$E$5572,E30) -> 314 | AF30: =SUMIFS($P$2:$P$5572,$E$2:$E$5572,E30) -> 7 | AG30: =IF(SUMIFS($G$2:$G$5572,$E$2:$E$5572,E30)>0,1000*Y30/SUMIFS($G$2:$G$5572,$E$2:$E$5572,E30),0) -> 24.545613 | AH30: =12*(J30*'Programas e Observações'!$C$8+K30*'Programas e Observações'!$C$9+L30*('Programas e Observações'!$C$8+'Programas e Observações'!$C$9)+M30*'Programas e Observações'!$C$10) -> 85894.8 | AI30: =12*(J30*'Programas e Observações'!$D$8+K30*'Programas e Observações'!$D$9+L30*('Programas e Observações'!$D$8+'Programas e Observações'!$D$9)+M30*'Programas e Observações'!$D$10) -> 172073.4 | AJ30: 262 moradores pegam remédio de pressão ou diabetes de graça na Farmácia Popular | AK30: Sem o programa, gastariam pelo menos R$ 86 mil por ano
A31: 1100601 | B31: 110060 | C31: Cacaulândia | D31: RO | E31: 11001 | F31: Vale do Jamari | G31: 4292 | H31: =G31<'Programas e Observações'!$C$11 -> TRUE | I31: 174 | J31: 100 | K31: 13 | L31: 20 | M31: 20 | N31: 77 | O31: 9 | P31: 0 | R31: =IF(G31>0,1000*I31/G31,0) -> 40.540541 | S31: =IF(G31>0,1000*J31/G31,0) -> 23.299161 | T31: =IF(G31>0,1000*K31/G31,0) -> 3.028891 | U31: =IF(G31>0,1000*L31/G31,0) -> 4.6598322 | V31: =IF(G31>0,1000*M31/G31,0) -> 4.6598322 | W31: =IF(G31>0,1000*N31/G31,0) -> 17.940354 | X31: =IF(G31>0,1000*O31/G31,0) -> 2.0969245 | Y31: =SUMIFS($I$2:$I$5572,$E$2:$E$5572,E31) -> 3070 | Z31: =SUMIFS($J$2:$J$5572,$E$2:$E$5572,E31) -> 1523 | AA31: =SUMIFS($K$2:$K$5572,$E$2:$E$5572,E31) -> 232 | AB31: =SUMIFS($L$2:$L$5572,$E$2:$E$5572,E31) -> 477 | AC31: =SUMIFS($M$2:$M$5572,$E$2:$E$5572,E31) -> 83 | AD31: =SUMIFS($N$2:$N$5572,$E$2:$E$5572,E31) -> 2055 | AE31: =SUMIFS($O$2:$O$5572,$E$2:$E$5572,E31) -> 401 | AF31: =SUMIFS($P$2:$P$5572,$E$2:$E$5572,E31) -> 13 | AG31: =IF(SUMIFS($G$2:$G$5572,$E$2:$E$5572,E31)>0,1000*Y31/SUMIFS($G$2:$G$5572,$E$2:$E$5572,E31),0) -> 12.973622 | AH31: =12*(J31*'Programas e Observações'!$C$8+K31*'Programas e Observações'!$C$9+L31*('Programas e Observações'!$C$8+'Programas e Observações'!$C$9)+M31*'Programas e Observações'!$C$10) -> 51187.8 | AI31: =12*(J31*'Programas e Observações'!$D$8+K31*'Programas e Observações'!$D$9+L31*('Programas e Observações'!$D$8+'Programas e Observações'!$D$9)+M31*'Programas e Observações'!$D$10) -> 95343 | AJ31: 133 moradores pegam remédio de pressão ou diabetes de graça na Farmácia Popular | AK31: Sem o programa, gastariam pelo menos R$ 51 mil por ano
A32: 1100700 | B32: 110070 | C32: Campo Novo de Rondônia | D32: RO | E32: 11001 | F32: Vale do Jamari | G32: 9095 | H32: =G32<'Programas e Observações'!$C$11 -> TRUE | I32: 125 | J32: 81 | K32: 11 | L32: 23 | M32: 0 | N32: 76 | O32: 14 | P32: 1 | R32: =IF(G32>0,1000*I32/G32,0) -> 13.743815 | S32: =IF(G32>0,1000*J32/G32,0) -> 8.9059923 | T32: =IF(G32>0,1000*K32/G32,0) -> 1.2094557 | U32: =IF(G32>0,1000*L32/G32,0) -> 2.528862 | V32: =IF(G32>0,1000*M32/G32,0) -> 0 | W32: =IF(G32>0,1000*N32/G32,0) -> 8.3562397 | X32: =IF(G32>0,1000*O32/G32,0) -> 1.5393073 | Y32: =SUMIFS($I$2:$I$5572,$E$2:$E$5572,E32) -> 3070 | Z32: =SUMIFS($J$2:$J$5572,$E$2:$E$5572,E32) -> 1523 | AA32: =SUMIFS($K$2:$K$5572,$E$2:$E$5572,E32) -> 232 | AB32: =SUMIFS($L$2:$L$5572,$E$2:$E$5572,E32) -> 477 | AC32: =SUMIFS($M$2:$M$5572,$E$2:$E$5572,E32) -> 83 | AD32: =SUMIFS($N$2:$N$5572,$E$2:$E$5572,E32) -> 2055 | AE32: =SUMIFS($O$2:$O$5572,$E$2:$E$5572,E32) -> 401 | AF32: =SUMIFS($P$2:$P$5572,$E$2:$E$5572,E32) -> 13 | AG32: =IF(SUMIFS($G$2:$G$5572,$E$2:$E$5572,E32)>0,1000*Y32/SUMIFS($G$2:$G$5572,$E$2:$E$5572,E32),0) -> 12.973622 | AH32: =12*(J32*'Programas e Observações'!$C$8+K32*'Programas e Observações'!$C$9+L32*('Programas e Observações'!$C$8+'Programas e Observações'!$C$9)+M32*'Programas e Observações'!$C$10) -> 37974 | AI32: =12*(J32*'Programas e Observações'!$D$8+K32*'Programas e Observações'!$D$9+L32*('Programas e Observações'!$D$8+'Programas e Observações'!$D$9)+M32*'Programas e Observações'!$D$10) -> 76110.96 | AJ32: 115 moradores pegam remédio de pressão ou diabetes de graça na Farmácia Popular | AK32: Sem o programa, gastariam pelo menos R$ 38 mil por ano
A33: 1100809 | B33: 110080 | C33: Candeias do Jamari | D33: RO | E33: 11004 | F33: Madeira-Mamoré | G33: 24313 | H33: =G33<'Programas e Observações'!$C$11 -> FALSE | I33: 330 | J33: 164 | K33: 33 | L33: 67 | M33: 17 | N33: 163 | O33: 50 | P33: 0 | R33: =IF(G33>0,1000*I33/G33,0) -> 13.572986 | S33: =IF(G33>0,1000*J33/G33,0) -> 6.7453626 | T33: =IF(G33>0,1000*K33/G33,0) -> 1.3572986 | U33: =IF(G33>0,1000*L33/G33,0) -> 2.7557274 | V33: =IF(G33>0,1000*M33/G33,0) -> 0.69921441 | W33: =IF(G33>0,1000*N33/G33,0) -> 6.7042323 | X33: =IF(G33>0,1000*O33/G33,0) -> 2.056513 | Y33: =SUMIFS($I$2:$I$5572,$E$2:$E$5572,E33) -> 6894 | Z33: =SUMIFS($J$2:$J$5572,$E$2:$E$5572,E33) -> 1916 | AA33: =SUMIFS($K$2:$K$5572,$E$2:$E$5572,E33) -> 1016 | AB33: =SUMIFS($L$2:$L$5572,$E$2:$E$5572,E33) -> 1376 | AC33: =SUMIFS($M$2:$M$5572,$E$2:$E$5572,E33) -> 263 | AD33: =SUMIFS($N$2:$N$5572,$E$2:$E$5572,E33) -> 5769 | AE33: =SUMIFS($O$2:$O$5572,$E$2:$E$5572,E33) -> 1523 | AF33: =SUMIFS($P$2:$P$5572,$E$2:$E$5572,E33) -> 22 | AG33: =IF(SUMIFS($G$2:$G$5572,$E$2:$E$5572,E33)>0,1000*Y33/SUMIFS($G$2:$G$5572,$E$2:$E$5572,E33),0) -> 11.056139 | AH33: =12*(J33*'Programas e Observações'!$C$8+K33*'Programas e Observações'!$C$9+L33*('Programas e Observações'!$C$8+'Programas e Observações'!$C$9)+M33*'Programas e Observações'!$C$10) -> 105780.36 | AI33: =12*(J33*'Programas e Observações'!$D$8+K33*'Programas e Observações'!$D$9+L33*('Programas e Observações'!$D$8+'Programas e Observações'!$D$9)+M33*'Programas e Observações'!$D$10) -> 191259.96 | AJ33: 264 moradores pegam remédio de pressão ou diabetes de graça na Farmácia Popular | AK33: Sem o programa, gastariam pelo menos R$ 106 mil por ano
A34: 1100908 | B34: 110090 | C34: Castanheiras | D34: RO | E34: 11005 | F34: Zona da Mata | G34: 3450 | H34: =G34<'Programas e Observações'!$C$11 -> TRUE | I34: 0 | J34: 0 | K34: 0 | L34: 0 | M34: 0 | N34: 34 | O34: 11 | P34: 1 | R34: =IF(G34>0,1000*I34/G34,0) -> 0 | S34: =IF(G34>0,1000*J34/G34,0) -> 0 | T34: =IF(G34>0,1000*K34/G34,0) -> 0 | U34: =IF(G34>0,1000*L34/G34,0) -> 0 | V34: =IF(G34>0,1000*M34/G34,0) -> 0 | W34: =IF(G34>0,1000*N34/G34,0) -> 9.8550725 | X34: =IF(G34>0,1000*O34/G34,0) -> 3.1884058 | Y34: =SUMIFS($I$2:$I$5572,$E$2:$E$5572,E34) -> 3387 | Z34: =SUMIFS($J$2:$J$5572,$E$2:$E$5572,E34) -> 1912 | AA34: =SUMIFS($K$2:$K$5572,$E$2:$E$5572,E34) -> 196 | AB34: =SUMIFS($L$2:$L$5572,$E$2:$E$5572,E34) -> 835 | AC34: =SUMIFS($M$2:$M$5572,$E$2:$E$5572,E34) -> 38 | AD34: =SUMIFS($N$2:$N$5572,$E$2:$E$5572,E34) -> 1751 | AE34: =SUMIFS($O$2:$O$5572,$E$2:$E$5572,E34) -> 314 | AF34: =SUMIFS($P$2:$P$5572,$E$2:$E$5572,E34) -> 7 | AG34: =IF(SUMIFS($G$2:$G$5572,$E$2:$E$5572,E34)>0,1000*Y34/SUMIFS($G$2:$G$5572,$E$2:$E$5572,E34),0) -> 24.545613 | AH34: =12*(J34*'Programas e Observações'!$C$8+K34*'Programas e Observações'!$C$9+L34*('Programas e Observações'!$C$8+'Programas e Observações'!$C$9)+M34*'Programas e Observações'!$C$10) -> 0 | AI34: =12*(J34*'Programas e Observações'!$D$8+K34*'Programas e Observações'!$D$9+L34*('Programas e Observações'!$D$8+'Programas e Observações'!$D$9)+M34*'Programas e Observações'!$D$10) -> 0 | AJ34: 0 moradores pegam remédio de pressão ou diabetes de graça na Farmácia Popular | AK34: Sem o programa, gastariam pelo menos R$ 0 mil por ano
A35: 1100924 | B35: 110092 | C35: Chupinguaia | D35: RO | E35: 11006 | F35: Cone Sul | G35: 10191 | H35: =G35<'Programas e Observações'!$C$11 -> TRUE | I35: 94 | J35: 45 | K35: 10 | L35: 17 | M35: 4 | N35: 59 | O35: 17 | P35: 0 | R35: =IF(G35>0,1000*I35/G35,0) -> 9.2238249 | S35: =IF(G35>0,1000*J35/G35,0) -> 4.4156609 | T35: =IF(G35>0,1000*K35/G35,0) -> 0.98125797 | U35: =IF(G35>0,1000*L35/G35,0) -> 1.6681386 | V35: =IF(G35>0,1000*M35/G35,0) -> 0.39250319 | W35: =IF(G35>0,1000*N35/G35,0) -> 5.789422 | X35: =IF(G35>0,1000*O35/G35,0) -> 1.6681386 | Y35: =SUMIFS($I$2:$I$5572,$E$2:$E$5572,E35) -> 6176 | Z35: =SUMIFS($J$2:$J$5572,$E$2:$E$5572,E35) -> 3173 | AA35: =SUMIFS($K$2:$K$5572,$E$2:$E$5572,E35) -> 544 | AB35: =SUMIFS($L$2:$L$5572,$E$2:$E$5572,E35) -> 1434 | AC35: =SUMIFS($M$2:$M$5572,$E$2:$E$5572,E35) -> 238 | AD35: =SUMIFS($N$2:$N$5572,$E$2:$E$5572,E35) -> 1653 | AE35: =SUMIFS($O$2:$O$5572,$E$2:$E$5572,E35) -> 277 | AF35: =SUMIFS($P$2:$P$5572,$E$2:$E$5572,E35) -> 5 | AG35: =IF(SUMIFS($G$2:$G$5572,$E$2:$E$5572,E35)>0,1000*Y35/SUMIFS($G$2:$G$5572,$E$2:$E$5572,E35),0) -> 36.48889 | AH35: =12*(J35*'Programas e Observações'!$C$8+K35*'Programas e Observações'!$C$9+L35*('Programas e Observações'!$C$8+'Programas e Observações'!$C$9)+M35*'Programas e Observações'!$C$10) -> 28176.12 | AI35: =12*(J35*'Programas e Observações'!$D$8+K35*'Programas e Observações'!$D$9+L35*('Programas e Observações'!$D$8+'Programas e Observações'!$D$9)+M35*'Programas e Observações'!$D$10) -> 51114.12 | AJ35: 72 moradores pegam remédio de pressão ou diabetes de graça na Farmácia Popular | AK35: Sem o programa, gastariam pelo menos R$ 28 mil por ano
... A58: 1200179 | B58: 120017 | C58: Capixaba | D58: AC | E58: 12002 | F58: Baixo Acre e Purus | G58: 10981 | H58: =G58<'Programas e Observações'!$C$11 -> TRUE | I58: 0 | J58: 0 | K58: 0 | L58: 0 | M58: 0 | N58: 31 | O58: 6 | P58: 0 | R58: =IF(G58>0,1000*I58/G58,0) -> 0 | S58: =IF(G58>0,1000*J58/G58,0) -> 0 | T58: =IF(G58>0,1000*K58/G58,0) -> 0 | U58: =IF(G58>0,1000*L58/G58,0) -> 0 | V58: =IF(G58>0,1000*M58/G58,0) -> 0 | W58: =IF(G58>0,1000*N58/G58,0) -> 2.823058 | X58: =IF(G58>0,1000*O58/G58,0) -> 0.54639832 | Y58: =SUMIFS($I$2:$I$5572,$E$2:$E$5572,E58) -> 4168 | Z58: =SUMIFS($J$2:$J$5572,$E$2:$E$5572,E58) -> 877 | AA58: =SUMIFS($K$2:$K$5572,$E$2:$E$5572,E58) -> 267 | AB58: =SUMIFS($L$2:$L$5572,$E$2:$E$5572,E58) -> 346 | AC58: =SUMIFS($M$2:$M$5572,$E$2:$E$5572,E58) -> 37 | AD58: =SUMIFS($N$2:$N$5572,$E$2:$E$5572,E58) -> 3474 | AE58: =SUMIFS($O$2:$O$5572,$E$2:$E$5572,E58) -> 518 | AF58: =SUMIFS($P$2:$P$5572,$E$2:$E$5572,E58) -> 20 | AG58: =IF(SUMIFS($G$2:$G$5572,$E$2:$E$5572,E58)>0,1000*Y58/SUMIFS($G$2:$G$5572,$E$2:$E$5572,E58),0) -> 7.4464873 | AH58: =12*(J58*'Programas e Observações'!$C$8+K58*'Programas e Observações'!$C$9+L58*('Programas e Observações'!$C$8+'Programas e Observações'!$C$9)+M58*'Programas e Observações'!$C$10) -> 0 | AI58: =12*(J58*'Programas e Observações'!$D$8+K58*'Programas e Observações'!$D$9+L58*('Programas e Observações'!$D$8+'Programas e Observações'!$D$9)+M58*'Programas e Observações'!$D$10) -> 0 | AJ58: 0 moradores pegam remédio de pressão ou diabetes de graça na Farmácia Popular | AK58: Sem o programa, gastariam pelo menos R$ 0 mil por ano
A59: 1200203 | B59: 120020 | C59: Cruzeiro do Sul | D59: AC | E59: 12003 | F59: Juruá e Tarauacá/Envira | G59: 98916 | H59: =G59<'Programas e Observações'!$C$11 -> FALSE | I59: 1856 | J59: 234 | K59: 118 | L59: 128 | M59: 17 | N59: 455 | O59: 42 | P59: 3 | Q59: 54 | R59: =IF(G59>0,1000*I59/G59,0) -> 18.763395 | S59: =IF(G59>0,1000*J59/G59,0) -> 2.3656436 | T59: =IF(G59>0,1000*K59/G59,0) -> 1.1929314 | U59: =IF(G59>0,1000*L59/G59,0) -> 1.2940273 | V59: =IF(G59>0,1000*M59/G59,0) -> 0.17186299 | W59: =IF(G59>0,1000*N59/G59,0) -> 4.5998625 | X59: =IF(G59>0,1000*O59/G59,0) -> 0.42460269 | Y59: =SUMIFS($I$2:$I$5572,$E$2:$E$5572,E59) -> 2019 | Z59: =SUMIFS($J$2:$J$5572,$E$2:$E$5572,E59) -> 237 | AA59: =SUMIFS($K$2:$K$5572,$E$2:$E$5572,E59) -> 122 | AB59: =SUMIFS($L$2:$L$5572,$E$2:$E$5572,E59) -> 129 | AC59: =SUMIFS($M$2:$M$5572,$E$2:$E$5572,E59) -> 18 | AD59: =SUMIFS($N$2:$N$5572,$E$2:$E$5572,E59) -> 656 | AE59: =SUMIFS($O$2:$O$5572,$E$2:$E$5572,E59) -> 79 | AF59: =SUMIFS($P$2:$P$5572,$E$2:$E$5572,E59) -> 6 | AG59: =IF(SUMIFS($G$2:$G$5572,$E$2:$E$5572,E59)>0,1000*Y59/SUMIFS($G$2:$G$5572,$E$2:$E$5572,E59),0) -> 8.1108768 | AH59: =12*(J59*'Programas e Observações'!$C$8+K59*'Programas e Observações'!$C$9+L59*('Programas e Observações'!$C$8+'Programas e Observações'!$C$9)+M59*'Programas e Observações'!$C$10) -> 206169.36 | AI59: =12*(J59*'Programas e Observações'!$D$8+K59*'Programas e Observações'!$D$9+L59*('Programas e Observações'!$D$8+'Programas e Observações'!$D$9)+M59*'Programas e Observações'!$D$10) -> 341915.4 | AJ59: 480 moradores pegam remédio de pressão ou diabetes de graça na Farmácia Popular | AK59: Sem o programa, gastariam pelo menos R$ 206 mil por ano
A60: 1200252 | B60: 120025 | C60: Epitaciolândia | D60: AC | E60: 12001 | F60: Alto Acre | G60: 19874 | H60: =G60<'Programas e Observações'!$C$11 -> TRUE | I60: 41 | J60: 0 | K60: 1 | L60: 1 | M60: 1 | N60: 65 | O60: 13 | P60: 1 | R60: =IF(G60>0,1000*I60/G60,0) -> 2.0629969 | S60: =IF(G60>0,1000*J60/G60,0) -> 0 | T60: =IF(G60>0,1000*K60/G60,0) -> 0.050316997 | U60: =IF(G60>0,1000*L60/G60,0) -> 0.050316997 | V60: =IF(G60>0,1000*M60/G60,0) -> 0.050316997 | W60: =IF(G60>0,1000*N60/G60,0) -> 3.2706048 | X60: =IF(G60>0,1000*O60/G60,0) -> 0.65412096 | Y60: =SUMIFS($I$2:$I$5572,$E$2:$E$5572,E60) -> 349 | Z60: =SUMIFS($J$2:$J$5572,$E$2:$E$5572,E60) -> 23 | AA60: =SUMIFS($K$2:$K$5572,$E$2:$E$5572,E60) -> 16 | AB60: =SUMIFS($L$2:$L$5572,$E$2:$E$5572,E60) -> 10 | AC60: =SUMIFS($M$2:$M$5572,$E$2:$E$5572,E60) -> 3 | AD60: =SUMIFS($N$2:$N$5572,$E$2:$E$5572,E60) -> 218 | AE60: =SUMIFS($O$2:$O$5572,$E$2:$E$5572,E60) -> 42 | AF60: =SUMIFS($P$2:$P$5572,$E$2:$E$5572,E60) -> 2 | AG60: =IF(SUMIFS($G$2:$G$5572,$E$2:$E$5572,E60)>0,1000*Y60/SUMIFS($G$2:$G$5572,$E$2:$E$5572,E60),0) -> 4.6090861 | AH60: =12*(J60*'Programas e Observações'!$C$8+K60*'Programas e Observações'!$C$9+L60*('Programas e Observações'!$C$8+'Programas e Observações'!$C$9)+M60*'Programas e Observações'!$C$10) -> 1744.68 | AI60: =12*(J60*'Programas e Observações'!$D$8+K60*'Programas e Observações'!$D$9+L60*('Programas e Observações'!$D$8+'Programas e Observações'!$D$9)+M60*'Programas e Observações'!$D$10) -> 2161.8 | AJ60: 2 moradores pegam remédio de pressão ou diabetes de graça na Farmácia Popular | AK60: Sem o programa, gastariam pelo menos R$ 2 mil por ano
A61: 1200302 | B61: 120030 | C61: Feijó | D61: AC | E61: 12003 | F61: Juruá e Tarauacá/Envira | G61: 37764 | H61: =G61<'Programas e Observações'!$C$11 -> FALSE | I61: 0 | J61: 0 | K61: 0 | L61: 0 | M61: 0 | N61: 56 | O61: 10 | P61: 1 | R61: =IF(G61>0,1000*I61/G61,0) -> 0 | S61: =IF(G61>0,1000*J61/G61,0) -> 0 | T61: =IF(G61>0,1000*K61/G61,0) -> 0 | U61: =IF(G61>0,1000*L61/G61,0) -> 0 | V61: =IF(G61>0,1000*M61/G61,0) -> 0 | W61: =IF(G61>0,1000*N61/G61,0) -> 1.4828938 | X61: =IF(G61>0,1000*O61/G61,0) -> 0.26480246 | Y61: =SUMIFS($I$2:$I$5572,$E$2:$E$5572,E61) -> 2019 | Z61: =SUMIFS($J$2:$J$5572,$E$2:$E$5572,E61) -> 237 | AA61: =SUMIFS($K$2:$K$5572,$E$2:$E$5572,E61) -> 122 | AB61: =SUMIFS($L$2:$L$5572,$E$2:$E$5572,E61) -> 129 | AC61: =SUMIFS($M$2:$M$5572,$E$2:$E$5572,E61) -> 18 | AD61: =SUMIFS($N$2:$N$5572,$E$2:$E$5572,E61) -> 656 | AE61: =SUMIFS($O$2:$O$5572,$E$2:$E$5572,E61) -> 79 | AF61: =SUMIFS($P$2:$P$5572,$E$2:$E$5572,E61) -> 6 | AG61: =IF(SUMIFS($G$2:$G$5572,$E$2:$E$5572,E61)>0,1000*Y61/SUMIFS($G$2:$G$5572,$E$2:$E$5572,E61),0) -> 8.1108768 | AH61: =12*(J61*'Programas e Observações'!$C$8+K61*'Programas e Observações'!$C$9+L61*('Programas e Observações'!$C$8+'Programas e Observações'!$C$9)+M61*'Programas e Observações'!$C$10) -> 0 | AI61: =12*(J61*'Programas e Observações'!$D$8+K61*'Programas e Observações'!$D$9+L61*('Programas e Observações'!$D$8+'Programas e Observações'!$D$9)+M61*'Programas e Observações'!$D$10) -> 0 | AJ61: 0 moradores pegam remédio de pressão ou diabetes de graça na Farmácia Popular | AK61: Sem o programa, gastariam pelo menos R$ 0 mil por ano
A62: 1200328 | B62: 120032 | C62: Jordão | D62: AC | E62: 12002 | F62: Baixo Acre e Purus | G62: 9884 | H62: =G62<'Programas e Observações'!$C$11 -> TRUE | I62: 0 | J62: 0 | K62: 0 | L62: 0 | M62: 0 | N62: 1 | O62: 3 | P62: 0 | R62: =IF(G62>0,1000*I62/G62,0) -> 0 | S62: =IF(G62>0,1000*J62/G62,0) -> 0 | T62: =IF(G62>0,1000*K62/G62,0) -> 0 | U62: =IF(G62>0,1000*L62/G62,0) -> 0 | V62: =IF(G62>0,1000*M62/G62,0) -> 0 | W62: =IF(G62>0,1000*N62/G62,0) -> 0.10117361 | X62: =IF(G62>0,1000*O62/G62,0) -> 0.30352084 | Y62: =SUMIFS($I$2:$I$5572,$E$2:$E$5572,E62) -> 4168 | Z62: =SUMIFS($J$2:$J$5572,$E$2:$E$5572,E62) -> 877 | AA62: =SUMIFS($K$2:$K$5572,$E$2:$E$5572,E62) -> 267 | AB62: =SUMIFS($L$2:$L$5572,$E$2:$E$5572,E62) -> 346 | AC62: =SUMIFS($M$2:$M$5572,$E$2:$E$5572,E62) -> 37 | AD62: =SUMIFS($N$2:$N$5572,$E$2:$E$5572,E62) -> 3474 | AE62: =SUMIFS($O$2:$O$5572,$E$2:$E$5572,E62) -> 518 | AF62: =SUMIFS($P$2:$P$5572,$E$2:$E$5572,E62) -> 20 | AG62: =IF(SUMIFS($G$2:$G$5572,$E$2:$E$5572,E62)>0,1000*Y62/SUMIFS($G$2:$G$5572,$E$2:$E$5572,E62),0) -> 7.4464873 | AH62: =12*(J62*'Programas e Observações'!$C$8+K62*'Programas e Observações'!$C$9+L62*('Programas e Observações'!$C$8+'Programas e Observações'!$C$9)+M62*'Programas e Observações'!$C$10) -> 0 | AI62: =12*(J62*'Programas e Observações'!$D$8+K62*'Programas e Observações'!$D$9+L62*('Programas e Observações'!$D$8+'Programas e Observações'!$D$9)+M62*'Programas e Observações'!$D$10) -> 0 | AJ62: 0 moradores pegam remédio de pressão ou diabetes de graça na Farmácia Popular | AK62: Sem o programa, gastariam pelo menos R$ 0 mil por ano
A63: 1200336 | B63: 120033 | C63: Mâncio Lima | D63: AC | E63: 12003 | F63: Juruá e Tarauacá/Envira | G63: 20479 | H63: =G63<'Programas e Observações'!$C$11 -> FALSE | I63: 0 | J63: 0 | K63: 0 | L63: 0 | M63: 0 | N63: 39 | O63: 9 | P63: 1 | R63: =IF(G63>0,1000*I63/G63,0) -> 0 | S63: =IF(G63>0,1000*J63/G63,0) -> 0 | T63: =IF(G63>0,1000*K63/G63,0) -> 0 | U63: =IF(G63>0,1000*L63/G63,0) -> 0 | V63: =IF(G63>0,1000*M63/G63,0) -> 0 | W63: =IF(G63>0,1000*N63/G63,0) -> 1.9043899 | X63: =IF(G63>0,1000*O63/G63,0) -> 0.43947458 | Y63: =SUMIFS($I$2:$I$5572,$E$2:$E$5572,E63) -> 2019 | Z63: =SUMIFS($J$2:$J$5572,$E$2:$E$5572,E63) -> 237 | AA63: =SUMIFS($K$2:$K$5572,$E$2:$E$5572,E63) -> 122 | AB63: =SUMIFS($L$2:$L$5572,$E$2:$E$5572,E63) -> 129 | AC63: =SUMIFS($M$2:$M$5572,$E$2:$E$5572,E63) -> 18 | AD63: =SUMIFS($N$2:$N$5572,$E$2:$E$5572,E63) -> 656 | AE63: =SUMIFS($O$2:$O$5572,$E$2:$E$5572,E63) -> 79 | AF63: =SUMIFS($P$2:$P$5572,$E$2:$E$5572,E63) -> 6 | AG63: =IF(SUMIFS($G$2:$G$5572,$E$2:$E$5572,E63)>0,1000*Y63/SUMIFS($G$2:$G$5572,$E$2:$E$5572,E63),0) -> 8.1108768 | AH63: =12*(J63*'Programas e Observações'!$C$8+K63*'Programas e Observações'!$C$9+L63*('Programas e Observações'!$C$8+'Programas e Observações'!$C$9)+M63*'Programas e Observações'!$C$10) -> 0 | AI63: =12*(J63*'Programas e Observações'!$D$8+K63*'Programas e Observações'!$D$9+L63*('Programas e Observações'!$D$8+'Programas e Observações'!$D$9)+M63*'Programas e Observações'!$D$10) -> 0 | AJ63: 0 moradores pegam remédio de pressão ou diabetes de graça na Farmácia Popular | AK63: Sem o programa, gastariam pelo menos R$ 0 mil por ano
A64: 1200344 | B64: 120034 | C64: Manoel Urbano | D64: AC | E64: 12002 | F64: Baixo Acre e Purus | G64: 12923 | H64: =G64<'Programas e Observações'!$C$11 -> TRUE | I64: 0 | J64: 0 | K64: 0 | L64: 0 | M64: 0 | N64: 19 | O64: 4 | P64: 0 | R64: =IF(G64>0,1000*I64/G64,0) -> 0 | S64: =IF(G64>0,1000*J64/G64,0) -> 0 | T64: =IF(G64>0,1000*K64/G64,0) -> 0 | U64: =IF(G64>0,1000*L64/G64,0) -> 0 | V64: =IF(G64>0,1000*M64/G64,0) -> 0 | W64: =IF(G64>0,1000*N64/G64,0) -> 1.4702468 | X64: =IF(G64>0,1000*O64/G64,0) -> 0.30952565 | Y64: =SUMIFS($I$2:$I$5572,$E$2:$E$5572,E64) -> 4168 | Z64: =SUMIFS($J$2:$J$5572,$E$2:$E$5572,E64) -> 877 | AA64: =SUMIFS($K$2:$K$5572,$E$2:$E$5572,E64) -> 267 | AB64: =SUMIFS($L$2:$L$5572,$E$2:$E$5572,E64) -> 346 | AC64: =SUMIFS($M$2:$M$5572,$E$2:$E$5572,E64) -> 37 | AD64: =SUMIFS($N$2:$N$5572,$E$2:$E$5572,E64) -> 3474 | AE64: =SUMIFS($O$2:$O$5572,$E$2:$E$5572,E64) -> 518 | AF64: =SUMIFS($P$2:$P$5572,$E$2:$E$5572,E64) -> 20 | AG64: =IF(SUMIFS($G$2:$G$5572,$E$2:$E$5572,E64)>0,1000*Y64/SUMIFS($G$2:$G$5572,$E$2:$E$5572,E64),0) -> 7.4464873 | AH64: =12*(J64*'Programas e Observações'!$C$8+K64*'Programas e Observações'!$C$9+L64*('Programas e Observações'!$C$8+'Programas e Observações'!$C$9)+M64*'Programas e Observações'!$C$10) -> 0 | AI64: =12*(J64*'Programas e Observações'!$D$8+K64*'Programas e Observações'!$D$9+L64*('Programas e Observações'!$D$8+'Programas e Observações'!$D$9)+M64*'Programas e Observações'!$D$10) -> 0 | AJ64: 0 moradores pegam remédio de pressão ou diabetes de graça na Farmácia Popular | AK64: Sem o programa, gastariam pelo menos R$ 0 mil por ano
A65: 1200351 | B65: 120035 | C65: Marechal Thaumaturgo | D65: AC | E65: 12003 | F65: Juruá e Tarauacá/Envira | G65: 18057 | H65: =G65<'Programas e Observações'!$C$11 -> TRUE | I65: 0 | J65: 0 | K65: 0 | L65: 0 | M65: 0 | N65: 9 | O65: 2 | P65: 0 | R65: =IF(G65>0,1000*I65/G65,0) -> 0 | S65: =IF(G65>0,1000*J65/G65,0) -> 0 | T65: =IF(G65>0,1000*K65/G65,0) -> 0 | U65: =IF(G65>0,1000*L65/G65,0) -> 0 | V65: =IF(G65>0,1000*M65/G65,0) -> 0 | W65: =IF(G65>0,1000*N65/G65,0) -> 0.49842166 | X65: =IF(G65>0,1000*O65/G65,0) -> 0.11076037 | Y65: =SUMIFS($I$2:$I$5572,$E$2:$E$5572,E65) -> 2019 | Z65: =SUMIFS($J$2:$J$5572,$E$2:$E$5572,E65) -> 237 | AA65: =SUMIFS($K$2:$K$5572,$E$2:$E$5572,E65) -> 122 | AB65: =SUMIFS($L$2:$L$5572,$E$2:$E$5572,E65) -> 129 | AC65: =SUMIFS($M$2:$M$5572,$E$2:$E$5572,E65) -> 18 | AD65: =SUMIFS($N$2:$N$5572,$E$2:$E$5572,E65) -> 656 | AE65: =SUMIFS($O$2:$O$5572,$E$2:$E$5572,E65) -> 79 | AF65: =SUMIFS($P$2:$P$5572,$E$2:$E$5572,E65) -> 6 | AG65: =IF(SUMIFS($G$2:$G$5572,$E$2:$E$5572,E65)>0,1000*Y65/SUMIFS($G$2:$G$5572,$E$2:$E$5572,E65),0) -> 8.1108768 | AH65: =12*(J65*'Programas e Observações'!$C$8+K65*'Programas e Observações'!$C$9+L65*('Programas e Observações'!$C$8+'Programas e Observações'!$C$9)+M65*'Programas e Observações'!$C$10) -> 0 | AI65: =12*(J65*'Programas e Observações'!$D$8+K65*'Programas e Observações'!$D$9+L65*('Programas e Observações'!$D$8+'Programas e Observações'!$D$9)+M65*'Programas e Observações'!$D$10) -> 0 | AJ65: 0 moradores pegam remédio de pressão ou diabetes de graça na Farmácia Popular | AK65: Sem o programa, gastariam pelo menos R$ 0 mil por ano
A66: 1200385 | B66: 120038 | C66: Plácido de Castro | D66: AC | E66: 12002 | F66: Baixo Acre e Purus | G66: 17107 | H66: =G66<'Programas e Observações'!$C$11 -> TRUE | I66: 220 | J66: 139 | K66: 9 | L66: 37 | M66: 1 | N66: 56 | O66: 9 | P66: 0 | R66: =IF(G66>0,1000*I66/G66,0) -> 12.860233 | S66: =IF(G66>0,1000*J66/G66,0) -> 8.1253288 | T66: =IF(G66>0,1000*K66/G66,0) -> 0.52610043 | U66: =IF(G66>0,1000*L66/G66,0) -> 2.1628573 | V66: =IF(G66>0,1000*M66/G66,0) -> 0.058455603 | W66: =IF(G66>0,1000*N66/G66,0) -> 3.2735138 | X66: =IF(G66>0,1000*O66/G66,0) -> 0.52610043 | Y66: =SUMIFS($I$2:$I$5572,$E$2:$E$5572,E66) -> 4168 | Z66: =SUMIFS($J$2:$J$5572,$E$2:$E$5572,E66) -> 877 | AA66: =SUMIFS($K$2:$K$5572,$E$2:$E$5572,E66) -> 267 | AB66: =SUMIFS($L$2:$L$5572,$E$2:$E$5572,E66) -> 346 | AC66: =SUMIFS($M$2:$M$5572,$E$2:$E$5572,E66) -> 37 | AD66: =SUMIFS($N$2:$N$5572,$E$2:$E$5572,E66) -> 3474 | AE66: =SUMIFS($O$2:$O$5572,$E$2:$E$5572,E66) -> 518 | AF66: =SUMIFS($P$2:$P$5572,$E$2:$E$5572,E66) -> 20 | AG66: =IF(SUMIFS($G$2:$G$5572,$E$2:$E$5572,E66)>0,1000*Y66/SUMIFS($G$2:$G$5572,$E$2:$E$5572,E66),0) -> 7.4464873 | AH66: =12*(J66*'Programas e Observações'!$C$8+K66*'Programas e Observações'!$C$9+L66*('Programas e Observações'!$C$8+'Programas e Observações'!$C$9)+M66*'Programas e Observações'!$C$10) -> 58913.28 | AI66: =12*(J66*'Programas e Observações'!$D$8+K66*'Programas e Observações'!$D$9+L66*('Programas e Observações'!$D$8+'Programas e Observações'!$D$9)+M66*'Programas e Observações'!$D$10) -> 123217.8 | AJ66: 185 moradores pegam remédio de pressão ou diabetes de graça na Farmácia Popular | AK66: Sem o programa, gastariam pelo menos R$ 59 mil por ano
A67: 1200393 | B67: 120039 | C67: Porto Walter | D67: AC | E67: 12003 | F67: Juruá e Tarauacá/Envira | G67: 11333 | H67: =G67<'Programas e Observações'!$C$11 -> TRUE | I67: 0 | J67: 0 | K67: 0 | L67: 0 | M67: 0 | N67: 6 | O67: 1 | P67: 0 | R67: =IF(G67>0,1000*I67/G67,0) -> 0 | S67: =IF(G67>0,1000*J67/G67,0) -> 0 | T67: =IF(G67>0,1000*K67/G67,0) -> 0 | U67: =IF(G67>0,1000*L67/G67,0) -> 0 | V67: =IF(G67>0,1000*M67/G67,0) -> 0 | W67: =IF(G67>0,1000*N67/G67,0) -> 0.52942734 | X67: =IF(G67>0,1000*O67/G67,0) -> 0.088237889 | Y67: =SUMIFS($I$2:$I$5572,$E$2:$E$5572,E67) -> 2019 | Z67: =SUMIFS($J$2:$J$5572,$E$2:$E$5572,E67) -> 237 | AA67: =SUMIFS($K$2:$K$5572,$E$2:$E$5572,E67) -> 122 | AB67: =SUMIFS($L$2:$L$5572,$E$2:$E$5572,E67) -> 129 | AC67: =SUMIFS($M$2:$M$5572,$E$2:$E$5572,E67) -> 18 | AD67: =SUMIFS($N$2:$N$5572,$E$2:$E$5572,E67) -> 656 | AE67: =SUMIFS($O$2:$O$5572,$E$2:$E$5572,E67) -> 79 | AF67: =SUMIFS($P$2:$P$5572,$E$2:$E$5572,E67) -> 6 | AG67: =IF(SUMIFS($G$2:$G$5572,$E$2:$E$5572,E67)>0,1000*Y67/SUMIFS($G$2:$G$5572,$E$2:$E$5572,E67),0) -> 8.1108768 | AH67: =12*(J67*'Programas e Observações'!$C$8+K67*'Programas e Observações'!$C$9+L67*('Programas e Observações'!$C$8+'Programas e Observações'!$C$9)+M67*'Programas e Observações'!$C$10) -> 0 | AI67: =12*(J67*'Programas e Observações'!$D$8+K67*'Programas e Observações'!$D$9+L67*('Programas e Observações'!$D$8+'Programas e Observações'!$D$9)+M67*'Programas e Observações'!$D$10) -> 0 | AJ67: 0 moradores pegam remédio de pressão ou diabetes de graça na Farmácia Popular | AK67: Sem o programa, gastariam pelo menos R$ 0 mil por ano
A68: 1200401 | B68: 120040 | C68: Rio Branco | D68: AC | E68: 12002 | F68: Baixo Acre e Purus | G68: 389001 | H68: =G68<'Programas e Observações'!$C$11 -> FALSE | I68: 3602 | J68: 706 | K68: 242 | L68: 297 | M68: 32 | N68: 3036 | O68: 438 | P68: 17 | Q68: 903 | R68: =IF(G68>0,1000*I68/G68,0) -> 9.2596163 | S68: =IF(G68>0,1000*J68/G68,0) -> 1.8149054 | T68: =IF(G68>0,1000*K68/G68,0) -> 0.62210637 | U68: =IF(G68>0,1000*L68/G68,0) -> 0.76349418 | V68: =IF(G68>0,1000*M68/G68,0) -> 0.082261999 | W68: =IF(G68>0,1000*N68/G68,0) -> 7.8046072 | X68: =IF(G68>0,1000*O68/G68,0) -> 1.1259611 | Y68: =SUMIFS($I$2:$I$5572,$E$2:$E$5572,E68) -> 4168 | Z68: =SUMIFS($J$2:$J$5572,$E$2:$E$5572,E68) -> 877 | AA68: =SUMIFS($K$2:$K$5572,$E$2:$E$5572,E68) -> 267 | AB68: =SUMIFS($L$2:$L$5572,$E$2:$E$5572,E68) -> 346 | AC68: =SUMIFS($M$2:$M$5572,$E$2:$E$5572,E68) -> 37 | AD68: =SUMIFS($N$2:$N$5572,$E$2:$E$5572,E68) -> 3474 | AE68: =SUMIFS($O$2:$O$5572,$E$2:$E$5572,E68) -> 518 | AF68: =SUMIFS($P$2:$P$5572,$E$2:$E$5572,E68) -> 20 | AG68: =IF(SUMIFS($G$2:$G$5572,$E$2:$E$5572,E68)>0,1000*Y68/SUMIFS($G$2:$G$5572,$E$2:$E$5572,E68),0) -> 7.4464873 | AH68: =12*(J68*'Programas e Observações'!$C$8+K68*'Programas e Observações'!$C$9+L68*('Programas e Observações'!$C$8+'Programas e Observações'!$C$9)+M68*'Programas e Observações'!$C$10) -> 490635.36 | AI68: =12*(J68*'Programas e Observações'!$D$8+K68*'Programas e Observações'!$D$9+L68*('Programas e Observações'!$D$8+'Programas e Observações'!$D$9)+M68*'Programas e Observações'!$D$10) -> 863453.64 | AJ68: 1.245 moradores pegam remédio de pressão ou diabetes de graça na Farmácia Popular | AK68: Sem o programa, gastariam pelo menos R$ 491 mil por ano
A69: 1200427 | B69: 120042 | C69: Rodrigues Alves | D69: AC | E69: 12003 | F69: Juruá e Tarauacá/Envira | G69: 15560 | H69: =G69<'Programas e Observações'!$C$11 -> TRUE | I69: 0 | J69: 0 | K69: 0 | L69: 0 | M69: 0 | N69: 25 | O69: 2 | P69: 0 | R69: =IF(G69>0,1000*I69/G69,0) -> 0 | S69: =IF(G69>0,1000*J69/G69,0) -> 0 | T69: =IF(G69>0,1000*K69/G69,0) -> 0 | U69: =IF(G69>0,1000*L69/G69,0) -> 0 | V69: =IF(G69>0,1000*M69/G69,0) -> 0 | W69: =IF(G69>0,1000*N69/G69,0) -> 1.6066838 | X69: =IF(G69>0,1000*O69/G69,0) -> 0.1285347 | Y69: =SUMIFS($I$2:$I$5572,$E$2:$E$5572,E69) -> 2019 | Z69: =SUMIFS($J$2:$J$5572,$E$2:$E$5572,E69) -> 237 | AA69: =SUMIFS($K$2:$K$5572,$E$2:$E$5572,E69) -> 122 | AB69: =SUMIFS($L$2:$L$5572,$E$2:$E$5572,E69) -> 129 | AC69: =SUMIFS($M$2:$M$5572,$E$2:$E$5572,E69) -> 18 | AD69: =SUMIFS($N$2:$N$5572,$E$2:$E$5572,E69) -> 656 | AE69: =SUMIFS($O$2:$O$5572,$E$2:$E$5572,E69) -> 79 | AF69: =SUMIFS($P$2:$P$5572,$E$2:$E$5572,E69) -> 6 | AG69: =IF(SUMIFS($G$2:$G$5572,$E$2:$E$5572,E69)>0,1000*Y69/SUMIFS($G$2:$G$5572,$E$2:$E$5572,E69),0) -> 8.1108768 | AH69: =12*(J69*'Programas e Observações'!$C$8+K69*'Programas e Observações'!$C$9+L69*('Programas e Observações'!$C$8+'Programas e Observações'!$C$9)+M69*'Programas e Observações'!$C$10) -> 0 | AI69: =12*(J69*'Programas e Observações'!$D$8+K69*'Programas e Observações'!$D$9+L69*('Programas e Observações'!$D$8+'Programas e Observações'!$D$9)+M69*'Programas e Observações'!$D$10) -> 0 | AJ69: 0 moradores pegam remédio de pressão ou diabetes de graça na Farmácia Popular | AK69: Sem o programa, gastariam pelo menos R$ 0 mil por ano
A70: 1200435 | B70: 120043 | C70: Santa Rosa do Purus | D70: AC | E70: 12002 | F70: Baixo Acre e Purus | G70: 7217 | H70: =G70<'Programas e Observações'!$C$11 -> TRUE | I70: 0 | J70: 0 | K70: 0 | L70: 0 | M70: 0 | N70: 1 | O70: 0 | P70: 0 | R70: =IF(G70>0,1000*I70/G70,0) -> 0 | S70: =IF(G70>0,1000*J70/G70,0) -> 0 | T70: =IF(G70>0,1000*K70/G70,0) -> 0 | U70: =IF(G70>0,1000*L70/G70,0) -> 0 | V70: =IF(G70>0,1000*M70/G70,0) -> 0 | W70: =IF(G70>0,1000*N70/G70,0) -> 0.13856173 | X70: =IF(G70>0,1000*O70/G70,0) -> 0 | Y70: =SUMIFS($I$2:$I$5572,$E$2:$E$5572,E70) -> 4168 | Z70: =SUMIFS($J$2:$J$5572,$E$2:$E$5572,E70) -> 877 | AA70: =SUMIFS($K$2:$K$5572,$E$2:$E$5572,E70) -> 267 | AB70: =SUMIFS($L$2:$L$5572,$E$2:$E$5572,E70) -> 346 | AC70: =SUMIFS($M$2:$M$5572,$E$2:$E$5572,E70) -> 37 | AD70: =SUMIFS($N$2:$N$5572,$E$2:$E$5572,E70) -> 3474 | AE70: =SUMIFS($O$2:$O$5572,$E$2:$E$5572,E70) -> 518 | AF70: =SUMIFS($P$2:$P$5572,$E$2:$E$5572,E70) -> 20 | AG70: =IF(SUMIFS($G$2:$G$5572,$E$2:$E$5572,E70)>0,1000*Y70/SUMIFS($G$2:$G$5572,$E$2:$E$5572,E70),0) -> 7.4464873 | AH70: =12*(J70*'Programas e Observações'!$C$8+K70*'Programas e Observações'!$C$9+L70*('Programas e Observações'!$C$8+'Programas e Observações'!$C$9)+M70*'Programas e Observações'!$C$10) -> 0 | AI70: =12*(J70*'Programas e Observações'!$D$8+K70*'Programas e Observações'!$D$9+L70*('Programas e Observações'!$D$8+'Programas e Observações'!$D$9)+M70*'Programas e Observações'!$D$10) -> 0 | AJ70: 0 moradores pegam remédio de pressão ou diabetes de graça na Farmácia Popular | AK70: Sem o programa, gastariam pelo menos R$ 0 mil por ano
A71: 1200450 | B71: 120045 | C71: Senador Guiomard | D71: AC | E71: 12002 | F71: Baixo Acre e Purus | G71: 22402 | H71: =G71<'Programas e Observações'!$C$11 -> FALSE | I71: 0 | J71: 0 | K71: 0 | L71: 0 | M71: 0 | N71: 76 | O71: 11 | P71: 0 | R71: =IF(G71>0,1000*I71/G71,0) -> 0 | S71: =IF(G71>0,1000*J71/G71,0) -> 0 | T71: =IF(G71>0,1000*K71/G71,0) -> 0 | U71: =IF(G71>0,1000*L71/G71,0) -> 0 | V71: =IF(G71>0,1000*M71/G71,0) -> 0 | W71: =IF(G71>0,1000*N71/G71,0) -> 3.3925542 | X71: =IF(G71>0,1000*O71/G71,0) -> 0.49102759 | Y71: =SUMIFS($I$2:$I$5572,$E$2:$E$5572,E71) -> 4168 | Z71: =SUMIFS($J$2:$J$5572,$E$2:$E$5572,E71) -> 877 | AA71: =SUMIFS($K$2:$K$5572,$E$2:$E$5572,E71) -> 267 | AB71: =SUMIFS($L$2:$L$5572,$E$2:$E$5572,E71) -> 346 | AC71: =SUMIFS($M$2:$M$5572,$E$2:$E$5572,E71) -> 37 | AD71: =SUMIFS($N$2:$N$5572,$E$2:$E$5572,E71) -> 3474 | AE71: =SUMIFS($O$2:$O$5572,$E$2:$E$5572,E71) -> 518 | AF71: =SUMIFS($P$2:$P$5572,$E$2:$E$5572,E71) -> 20 | AG71: =IF(SUMIFS($G$2:$G$5572,$E$2:$E$5572,E71)>0,1000*Y71/SUMIFS($G$2:$G$5572,$E$2:$E$5572,E71),0) -> 7.4464873 | AH71: =12*(J71*'Programas e Observações'!$C$8+K71*'Programas e Observações'!$C$9+L71*('Programas e Observações'!$C$8+'Programas e Observações'!$C$9)+M71*'Programas e Observações'!$C$10) -> 0 | AI71: =12*(J71*'Programas e Observações'!$D$8+K71*'Programas e Observações'!$D$9+L71*('Programas e Observações'!$D$8+'Programas e Observações'!$D$9)+M71*'Programas e Observações'!$D$10) -> 0 | AJ71: 0 moradores pegam remédio de pressão ou diabetes de graça na Farmácia Popular | AK71: Sem o programa, gastariam pelo menos R$ 0 mil por ano
A72: 1200500 | B72: 120050 | C72: Sena Madureira | D72: AC | E72: 12002 | F72: Baixo Acre e Purus | G72: 44049 | H72: =G72<'Programas e Observações'!$C$11 -> FALSE | I72: 292 | J72: 22 | K72: 16 | L72: 11 | M72: 4 | N72: 123 | O72: 12 | P72: 2 | R72: =IF(G72>0,1000*I72/G72,0) -> 6.6289814 | S72: =IF(G72>0,1000*J72/G72,0) -> 0.4994438 | T72: =IF(G72>0,1000*K72/G72,0) -> 0.36323186 | U72: =IF(G72>0,1000*L72/G72,0) -> 0.2497219 | V72: =IF(G72>0,1000*M72/G72,0) -> 0.090807964 | W72: =IF(G72>0,1000*N72/G72,0) -> 2.7923449 | X72: =IF(G72>0,1000*O72/G72,0) -> 0.27242389 | Y72: =SUMIFS($I$2:$I$5572,$E$2:$E$5572,E72) -> 4168 | Z72: =SUMIFS($J$2:$J$5572,$E$2:$E$5572,E72) -> 877 | AA72: =SUMIFS($K$2:$K$5572,$E$2:$E$5572,E72) -> 267 | AB72: =SUMIFS($L$2:$L$5572,$E$2:$E$5572,E72) -> 346 | AC72: =SUMIFS($M$2:$M$5572,$E$2:$E$5572,E72) -> 37 | AD72: =SUMIFS($N$2:$N$5572,$E$2:$E$5572,E72) -> 3474 | AE72: =SUMIFS($O$2:$O$5572,$E$2:$E$5572,E72) -> 518 | AF72: =SUMIFS($P$2:$P$5572,$E$2:$E$5572,E72) -> 20 | AG72: =IF(SUMIFS($G$2:$G$5572,$E$2:$E$5572,E72)>0,1000*Y72/SUMIFS($G$2:$G$5572,$E$2:$E$5572,E72),0) -> 7.4464873 | AH72: =12*(J72*'Programas e Observações'!$C$8+K72*'Programas e Observações'!$C$9+L72*('Programas e Observações'!$C$8+'Programas e Observações'!$C$9)+M72*'Programas e Observações'!$C$10) -> 22416.72 | AI72: =12*(J72*'Programas e Observações'!$D$8+K72*'Programas e Observações'!$D$9+L72*('Programas e Observações'!$D$8+'Programas e Observações'!$D$9)+M72*'Programas e Observações'!$D$10) -> 34925.16 | AJ72: 49 moradores pegam remédio de pressão ou diabetes de graça na Farmácia Popular | AK72: Sem o programa, gastariam pelo menos R$ 22 mil por ano
A73: 1200609 | B73: 120060 | C73: Tarauacá | D73: AC | E73: 12003 | F73: Juruá e Tarauacá/Envira | G73: 46816 | H73: =G73<'Programas e Observações'!$C$11 -> FALSE | I73: 163 | J73: 3 | K73: 4 | L73: 1 | M73: 1 | N73: 66 | O73: 13 | P73: 1 | R73: =IF(G73>0,1000*I73/G73,0) -> 3.4817157 | S73: =IF(G73>0,1000*J73/G73,0) -> 0.064080656 | T73: =IF(G73>0,1000*K73/G73,0) -> 0.085440875 | U73: =IF(G73>0,1000*L73/G73,0) -> 0.021360219 | V73: =IF(G73>0,1000*M73/G73,0) -> 0.021360219 | W73: =IF(G73>0,1000*N73/G73,0) -> 1.4097744 | X73: =IF(G73>0,1000*O73/G73,0) -> 0.27768284 | Y73: =SUMIFS($I$2:$I$5572,$E$2:$E$5572,E73) -> 2019 | Z73: =SUMIFS($J$2:$J$5572,$E$2:$E$5572,E73) -> 237 | AA73: =SUMIFS($K$2:$K$5572,$E$2:$E$5572,E73) -> 122 | AB73: =SUMIFS($L$2:$L$5572,$E$2:$E$5572,E73) -> 129 | AC73: =SUMIFS($M$2:$M$5572,$E$2:$E$5572,E73) -> 18 | AD73: =SUMIFS($N$2:$N$5572,$E$2:$E$5572,E73) -> 656 | AE73: =SUMIFS($O$2:$O$5572,$E$2:$E$5572,E73) -> 79 | AF73: =SUMIFS($P$2:$P$5572,$E$2:$E$5572,E73) -> 6 | AG73: =IF(SUMIFS($G$2:$G$5572,$E$2:$E$5572,E73)>0,1000*Y73/SUMIFS($G$2:$G$5572,$E$2:$E$5572,E73),0) -> 8.1108768 | AH73: =12*(J73*'Programas e Observações'!$C$8+K73*'Programas e Observações'!$C$9+L73*('Programas e Observações'!$C$8+'Programas e Observações'!$C$9)+M73*'Programas e Observações'!$C$10) -> 3868.68 | AI73: =12*(J73*'Programas e Observações'!$D$8+K73*'Programas e Observações'!$D$9+L73*('Programas e Observações'!$D$8+'Programas e Observações'!$D$9)+M73*'Programas e Observações'!$D$10) -> 5429.52 | AJ73: 8 moradores pegam remédio de pressão ou diabetes de graça na Farmácia Popular | AK73: Sem o programa, gastariam pelo menos R$ 4 mil por ano
A74: 1200708 | B74: 120070 | C74: Xapuri | D74: AC | E74: 12001 | F74: Alto Acre | G74: 19170 | H74: =G74<'Programas e Observações'!$C$11 -> TRUE | I74: 0 | J74: 0 | K74: 0 | L74: 0 | M74: 0 | N74: 49 | O74: 10 | P74: 1 | R74: =IF(G74>0,1000*I74/G74,0) -> 0 | S74: =IF(G74>0,1000*J74/G74,0) -> 0 | T74: =IF(G74>0,1000*K74/G74,0) -> 0 | U74: =IF(G74>0,1000*L74/G74,0) -> 0 | V74: =IF(G74>0,1000*M74/G74,0) -> 0 | W74: =IF(G74>0,1000*N74/G74,0) -> 2.5560772 | X74: =IF(G74>0,1000*O74/G74,0) -> 0.52164841 | Y74: =SUMIFS($I$2:$I$5572,$E$2:$E$5572,E74) -> 349 | Z74: =SUMIFS($J$2:$J$5572,$E$2:$E$5572,E74) -> 23 | AA74: =SUMIFS($K$2:$K$5572,$E$2:$E$5572,E74) -> 16 | AB74: =SUMIFS($L$2:$L$5572,$E$2:$E$5572,E74) -> 10 | AC74: =SUMIFS($M$2:$M$5572,$E$2:$E$5572,E74) -> 3 | AD74: =SUMIFS($N$2:$N$5572,$E$2:$E$5572,E74) -> 218 | AE74: =SUMIFS($O$2:$O$5572,$E$2:$E$5572,E74) -> 42 | AF74: =SUMIFS($P$2:$P$5572,$E$2:$E$5572,E74) -> 2 | AG74: =IF(SUMIFS($G$2:$G$5572,$E$2:$E$5572,E74)>0,1000*Y74/SUMIFS($G$2:$G$5572,$E$2:$E$5572,E74),0) -> 4.6090861 | AH74: =12*(J74*'Programas e Observações'!$C$8+K74*'Programas e Observações'!$C$9+L74*('Programas e Observações'!$C$8+'Programas e Observações'!$C$9)+M74*'Programas e Observações'!$C$10) -> 0 | AI74: =12*(J74*'Programas e Observações'!$D$8+K74*'Programas e Observações'!$D$9+L74*('Programas e Observações'!$D$8+'Programas e Observações'!$D$9)+M74*'Programas e Observações'!$D$10) -> 0 | AJ74: 0 moradores pegam remédio de pressão ou diabetes de graça na Farmácia Popular | AK74: Sem o programa, gastariam pelo menos R$ 0 mil por ano
A75: 1200807 | B75: 120080 | C75: Porto Acre | D75: AC | E75: 12002 | F75: Baixo Acre e Purus | G75: 17523 | H75: =G75<'Programas e Observações'!$C$11 -> TRUE | I75: 54 | J75: 10 | K75: 0 | L75: 1 | M75: 0 | N75: 58 | O75: 14 | P75: 0 | R75: =IF(G75>0,1000*I75/G75,0) -> 3.0816641 | S75: =IF(G75>0,1000*J75/G75,0) -> 0.57067854 | T75: =IF(G75>0,1000*K75/G75,0) -> 0 | U75: =IF(G75>0,1000*L75/G75,0) -> 0.057067854 | V75: =IF(G75>0,1000*M75/G75,0) -> 0 | W75: =IF(G75>0,1000*N75/G75,0) -> 3.3099355 | X75: =IF(G75>0,1000*O75/G75,0) -> 0.79894995 | Y75: =SUMIFS($I$2:$I$5572,$E$2:$E$5572,E75) -> 4168 | Z75: =SUMIFS($J$2:$J$5572,$E$2:$E$5572,E75) -> 877 | AA75: =SUMIFS($K$2:$K$5572,$E$2:$E$5572,E75) -> 267 | AB75: =SUMIFS($L$2:$L$5572,$E$2:$E$5572,E75) -> 346 | AC75: =SUMIFS($M$2:$M$5572,$E$2:$E$5572,E75) -> 37 | AD75: =SUMIFS($N$2:$N$5572,$E$2:$E$5572,E75) -> 3474 | AE75: =SUMIFS($O$2:$O$5572,$E$2:$E$5572,E75) -> 518 | AF75: =SUMIFS($P$2:$P$5572,$E$2:$E$5572,E75) -> 20 | AG75: =IF(SUMIFS($G$2:$G$5572,$E$2:$E$5572,E75)>0,1000*Y75/SUMIFS($G$2:$G$5572,$E$2:$E$5572,E75),0) -> 7.4464873 | AH75: =12*(J75*'Programas e Observações'!$C$8+K75*'Programas e Observações'!$C$9+L75*('Programas e Observações'!$C$8+'Programas e Observações'!$C$9)+M75*'Programas e Observações'!$C$10) -> 2694 | AI75: =12*(J75*'Programas e Observações'!$D$8+K75*'Programas e Observações'!$D$9+L75*('Programas e Observações'!$D$8+'Programas e Observações'!$D$9)+M75*'Programas e Observações'!$D$10) -> 6671.64 | AJ75: 11 moradores pegam remédio de pressão ou diabetes de graça na Farmácia Popular | AK75: Sem o programa, gastariam pelo menos R$ 3 mil por ano
A76: 1300029 | B76: 130002 | C76: Alvarães | D76: AM | E76: 13008 | F76: Triângulo | G76: 16806 | H76: =G76<'Programas e Observações'!$C$11 -> TRUE | I76: 0 | J76: 0 | K76: 0 | L76: 0 | M76: 0 | N76: 9 | O76: 1 | P76: 0 | R76: =IF(G76>0,1000*I76/G76,0) -> 0 | S76: =IF(G76>0,1000*J76/G76,0) -> 0 | T76: =IF(G76>0,1000*K76/G76,0) -> 0 | U76: =IF(G76>0,1000*L76/G76,0) -> 0 | V76: =IF(G76>0,1000*M76/G76,0) -> 0 | W76: =IF(G76>0,1000*N76/G76,0) -> 0.53552303 | X76: =IF(G76>0,1000*O76/G76,0) -> 0.059502559 | Y76: =SUMIFS($I$2:$I$5572,$E$2:$E$5572,E76) -> 0 | Z76: =SUMIFS($J$2:$J$5572,$E$2:$E$5572,E76) -> 0 | AA76: =SUMIFS($K$2:$K$5572,$E$2:$E$5572,E76) -> 0 | AB76: =SUMIFS($L$2:$L$5572,$E$2:$E$5572,E76) -> 0 | AC76: =SUMIFS($M$2:$M$5572,$E$2:$E$5572,E76) -> 0 | AD76: =SUMIFS($N$2:$N$5572,$E$2:$E$5572,E76) -> 64 | AE76: =SUMIFS($O$2:$O$5572,$E$2:$E$5572,E76) -> 5 | AF76: =SUMIFS($P$2:$P$5572,$E$2:$E$5572,E76) -> 3 | AG76: =IF(SUMIFS($G$2:$G$5572,$E$2:$E$5572,E76)>0,1000*Y76/SUMIFS($G$2:$G$5572,$E$2:$E$5572,E76),0) -> 0 | AH76: =12*(J76*'Programas e Observações'!$C$8+K76*'Programas e Observações'!$C$9+L76*('Programas e Observações'!$C$8+'Programas e Observações'!$C$9)+M76*'Programas e Observações'!$C$10) -> 0 | AI76: =12*(J76*'Programas e Observações'!$D$8+K76*'Programas e Observações'!$D$9+L76*('Programas e Observações'!$D$8+'Programas e Observações'!$D$9)+M76*'Programas e Observações'!$D$10) -> 0 | AJ76: 0 moradores pegam remédio de pressão ou diabetes de graça na Farmácia Popular | AK76: Sem o programa, gastariam pelo menos R$ 0 mil por ano
A77: 1300060 | B77: 130006 | C77: Amaturá | D77: AM | E77: 13009 | F77: Alto Solimões | G77: 11533 | H77: =G77<'Programas e Observações'!$C$11 -> TRUE | I77: 0 | J77: 0 | K77: 0 | L77: 0 | M77: 0 | N77: 1 | O77: 2 | P77: 0 | R77: =IF(G77>0,1000*I77/G77,0) -> 0 | S77: =IF(G77>0,1000*J77/G77,0) -> 0 | T77: =IF(G77>0,1000*K77/G77,0) -> 0 | U77: =IF(G77>0,1000*L77/G77,0) -> 0 | V77: =IF(G77>0,1000*M77/G77,0) -> 0 | W77: =IF(G77>0,1000*N77/G77,0) -> 0.086707708 | X77: =IF(G77>0,1000*O77/G77,0) -> 0.17341542 | Y77: =SUMIFS($I$2:$I$5572,$E$2:$E$5572,E77) -> 632 | Z77: =SUMIFS($J$2:$J$5572,$E$2:$E$5572,E77) -> 303 | AA77: =SUMIFS($K$2:$K$5572,$E$2:$E$5572,E77) -> 91 | AB77: =SUMIFS($L$2:$L$5572,$E$2:$E$5572,E77) -> 31 | AC77: =SUMIFS($M$2:$M$5572,$E$2:$E$5572,E77) -> 17 | AD77: =SUMIFS($N$2:$N$5572,$E$2:$E$5572,E77) -> 77 | AE77: =SUMIFS($O$2:$O$5572,$E$2:$E$5572,E77) -> 11 | AF77: =SUMIFS($P$2:$P$5572,$E$2:$E$5572,E77) -> 2 | AG77: =IF(SUMIFS($G$2:$G$5572,$E$2:$E$5572,E77)>0,1000*Y77/SUMIFS($G$2:$G$5572,$E$2:$E$5572,E77),0) -> 2.2215583 | AH77: =12*(J77*'Programas e Observações'!$C$8+K77*'Programas e Observações'!$C$9+L77*('Programas e Observações'!$C$8+'Programas e Observações'!$C$9)+M77*'Programas e Observações'!$C$10) -> 0 | AI77: =12*(J77*'Programas e Observações'!$D$8+K77*'Programas e Observações'!$D$9+L77*('Programas e Observações'!$D$8+'Programas e Observações'!$D$9)+M77*'Programas e Observações'!$D$10) -> 0 | AJ77: 0 moradores pegam remédio de pressão ou diabetes de graça na Farmácia Popular | AK77: Sem o programa, gastariam pelo menos R$ 0 mil por ano
A78: 1300086 | B78: 130008 | C78: Anamã | D78: AM | E78: 13002 | F78: Rio Negro e Solimões | G78: 9981 | H78: =G78<'Programas e Observações'!$C$11 -> TRUE | I78: 0 | J78: 0 | K78: 0 | L78: 0 | M78: 0 | N78: 8 | O78: 2 | P78: 0 | R78: =IF(G78>0,1000*I78/G78,0) -> 0 | S78: =IF(G78>0,1000*J78/G78,0) -> 0 | T78: =IF(G78>0,1000*K78/G78,0) -> 0 | U78: =IF(G78>0,1000*L78/G78,0) -> 0 | V78: =IF(G78>0,1000*M78/G78,0) -> 0 | W78: =IF(G78>0,1000*N78/G78,0) -> 0.80152289 | X78: =IF(G78>0,1000*O78/G78,0) -> 0.20038072 | Y78: =SUMIFS($I$2:$I$5572,$E$2:$E$5572,E78) -> 1330 | Z78: =SUMIFS($J$2:$J$5572,$E$2:$E$5572,E78) -> 163 | AA78: =SUMIFS($K$2:$K$5572,$E$2:$E$5572,E78) -> 73 | AB78: =SUMIFS($L$2:$L$5572,$E$2:$E$5572,E78) -> 86 | AC78: =SUMIFS($M$2:$M$5572,$E$2:$E$5572,E78) -> 157 | AD78: =SUMIFS($N$2:$N$5572,$E$2:$E$5572,E78) -> 322 | AE78: =SUMIFS($O$2:$O$5572,$E$2:$E$5572,E78) -> 15 | AF78: =SUMIFS($P$2:$P$5572,$E$2:$E$5572,E78) -> 3 | AG78: =IF(SUMIFS($G$2:$G$5572,$E$2:$E$5572,E78)>0,1000*Y78/SUMIFS($G$2:$G$5572,$E$2:$E$5572,E78),0) -> 4.557932 | AH78: =12*(J78*'Programas e Observações'!$C$8+K78*'Programas e Observações'!$C$9+L78*('Programas e Observações'!$C$8+'Programas e Observações'!$C$9)+M78*'Programas e Observações'!$C$10) -> 0 | AI78: =12*(J78*'Programas e Observações'!$D$8+K78*'Programas e Observações'!$D$9+L78*('Programas e Observações'!$D$8+'Programas e Observações'!$D$9)+M78*'Programas e Observações'!$D$10) -> 0 | AJ78: 0 moradores pegam remédio de pressão ou diabetes de graça na Farmácia Popular | AK78: Sem o programa, gastariam pelo menos R$ 0 mil por ano
A79: 1300102 | B79: 130010 | C79: Anori | D79: AM | E79: 13002 | F79: Rio Negro e Solimões | G79: 18056 | H79: =G79<'Programas e Observações'!$C$11 -> TRUE | I79: 0 | J79: 0 | K79: 0 | L79: 0 | M79: 0 | N79: 19 | O79: 1 | P79: 0 | R79: =IF(G79>0,1000*I79/G79,0) -> 0 | S79: =IF(G79>0,1000*J79/G79,0) -> 0 | T79: =IF(G79>0,1000*K79/G79,0) -> 0 | U79: =IF(G79>0,1000*L79/G79,0) -> 0 | V79: =IF(G79>0,1000*M79/G79,0) -> 0 | W79: =IF(G79>0,1000*N79/G79,0) -> 1.0522818 | X79: =IF(G79>0,1000*O79/G79,0) -> 0.055383252 | Y79: =SUMIFS($I$2:$I$5572,$E$2:$E$5572,E79) -> 1330 | Z79: =SUMIFS($J$2:$J$5572,$E$2:$E$5572,E79) -> 163 | AA79: =SUMIFS($K$2:$K$5572,$E$2:$E$5572,E79) -> 73 | AB79: =SUMIFS($L$2:$L$5572,$E$2:$E$5572,E79) -> 86 | AC79: =SUMIFS($M$2:$M$5572,$E$2:$E$5572,E79) -> 157 | AD79: =SUMIFS($N$2:$N$5572,$E$2:$E$5572,E79) -> 322 | AE79: =SUMIFS($O$2:$O$5572,$E$2:$E$5572,E79) -> 15 | AF79: =SUMIFS($P$2:$P$5572,$E$2:$E$5572,E79) -> 3 | AG79: =IF(SUMIFS($G$2:$G$5572,$E$2:$E$5572,E79)>0,1000*Y79/SUMIFS($G$2:$G$5572,$E$2:$E$5572,E79),0) -> 4.557932 | AH79: =12*(J79*'Programas e Observações'!$C$8+K79*'Programas e Observações'!$C$9+L79*('Programas e Observações'!$C$8+'Programas e Observações'!$C$9)+M79*'Programas e Observações'!$C$10) -> 0 | AI79: =12*(J79*'Programas e Observações'!$D$8+K79*'Programas e Observações'!$D$9+L79*('Programas e Observações'!$D$8+'Programas e Observações'!$D$9)+M79*'Programas e Observações'!$D$10) -> 0 | AJ79: 0 moradores pegam remédio de pressão ou diabetes de graça na Farmácia Popular | AK79: Sem o programa, gastariam pelo menos R$ 0 mil por ano
A80: 1300144 | B80: 130014 | C80: Apuí | D80: AM | E80: 13003 | F80: Rio Madeira | G80: 21781 | H80: =G80<'Programas e Observações'!$C$11 -> FALSE | I80: 0 | J80: 0 | K80: 0 | L80: 0 | M80: 0 | N80: 5 | O80: 16 | P80: 0 | R80: =IF(G80>0,1000*I80/G80,0) -> 0 | S80: =IF(G80>0,1000*J80/G80,0) -> 0 | T80: =IF(G80>0,1000*K80/G80,0) -> 0 | U80: =IF(G80>0,1000*L80/G80,0) -> 0 | V80: =IF(G80>0,1000*M80/G80,0) -> 0 | W80: =IF(G80>0,1000*N80/G80,0) -> 0.22955787 | X80: =IF(G80>0,1000*O80/G80,0) -> 0.73458519 | Y80: =SUMIFS($I$2:$I$5572,$E$2:$E$5572,E80) -> 971 | Z80: =SUMIFS($J$2:$J$5572,$E$2:$E$5572,E80) -> 454 | AA80: =SUMIFS($K$2:$K$5572,$E$2:$E$5572,E80) -> 12 | AB80: =SUMIFS($L$2:$L$5572,$E$2:$E$5572,E80) -> 289 | AC80: =SUMIFS($M$2:$M$5572,$E$2:$E$5572,E80) -> 0 | AD80: =SUMIFS($N$2:$N$5572,$E$2:$E$5572,E80) -> 185 | AE80: =SUMIFS($O$2:$O$5572,$E$2:$E$5572,E80) -> 86 | AF80: =SUMIFS($P$2:$P$5572,$E$2:$E$5572,E80) -> 2 | AG80: =IF(SUMIFS($G$2:$G$5572,$E$2:$E$5572,E80)>0,1000*Y80/SUMIFS($G$2:$G$5572,$E$2:$E$5572,E80),0) -> 4.7727418 | AH80: =12*(J80*'Programas e Observações'!$C$8+K80*'Programas e Observações'!$C$9+L80*('Programas e Observações'!$C$8+'Programas e Observações'!$C$9)+M80*'Programas e Observações'!$C$10) -> 0 | AI80: =12*(J80*'Programas e Observações'!$D$8+K80*'Programas e Observações'!$D$9+L80*('Programas e Observações'!$D$8+'Programas e Observações'!$D$9)+M80*'Programas e Observações'!$D$10) -> 0 | AJ80: 0 moradores pegam remédio de pressão ou diabetes de graça na Farmácia Popular | AK80: Sem o programa, gastariam pelo menos R$ 0 mil por ano
... A94: 1301159 | B94: 130115 | C94: Careiro da Várzea | D94: AM | E94: 13001 | F94: Manaus, Entorno e Alto Rio Negro | G94: 20324 | H94: =G94<'Programas e Observações'!$C$11 -> FALSE | I94: 0 | J94: 0 | K94: 0 | L94: 0 | M94: 0 | N94: 36 | O94: 1 | P94: 0 | R94: =IF(G94>0,1000*I94/G94,0) -> 0 | S94: =IF(G94>0,1000*J94/G94,0) -> 0 | T94: =IF(G94>0,1000*K94/G94,0) -> 0 | U94: =IF(G94>0,1000*L94/G94,0) -> 0 | V94: =IF(G94>0,1000*M94/G94,0) -> 0 | W94: =IF(G94>0,1000*N94/G94,0) -> 1.7713049 | X94: =IF(G94>0,1000*O94/G94,0) -> 0.049202913 | Y94: =SUMIFS($I$2:$I$5572,$E$2:$E$5572,E94) -> 13707 | Z94: =SUMIFS($J$2:$J$5572,$E$2:$E$5572,E94) -> 2662 | AA94: =SUMIFS($K$2:$K$5572,$E$2:$E$5572,E94) -> 1816 | AB94: =SUMIFS($L$2:$L$5572,$E$2:$E$5572,E94) -> 1620 | AC94: =SUMIFS($M$2:$M$5572,$E$2:$E$5572,E94) -> 687 | AD94: =SUMIFS($N$2:$N$5572,$E$2:$E$5572,E94) -> 11419 | AE94: =SUMIFS($O$2:$O$5572,$E$2:$E$5572,E94) -> 592 | AF94: =SUMIFS($P$2:$P$5572,$E$2:$E$5572,E94) -> 8 | AG94: =IF(SUMIFS($G$2:$G$5572,$E$2:$E$5572,E94)>0,1000*Y94/SUMIFS($G$2:$G$5572,$E$2:$E$5572,E94),0) -> 5.1457416 | AH94: =12*(J94*'Programas e Observações'!$C$8+K94*'Programas e Observações'!$C$9+L94*('Programas e Observações'!$C$8+'Programas e Observações'!$C$9)+M94*'Programas e Observações'!$C$10) -> 0 | AI94: =12*(J94*'Programas e Observações'!$D$8+K94*'Programas e Observações'!$D$9+L94*('Programas e Observações'!$D$8+'Programas e Observações'!$D$9)+M94*'Programas e Observações'!$D$10) -> 0 | AJ94: 0 moradores pegam remédio de pressão ou diabetes de graça na Farmácia Popular | AK94: Sem o programa, gastariam pelo menos R$ 0 mil por ano
A95: 1301209 | B95: 130120 | C95: Coari | D95: AM | E95: 13002 | F95: Rio Negro e Solimões | G95: 73576 | H95: =G95<'Programas e Observações'!$C$11 -> FALSE | I95: 0 | J95: 0 | K95: 0 | L95: 0 | M95: 0 | N95: 86 | O95: 2 | P95: 0 | Q95: 18 | R95: =IF(G95>0,1000*I95/G95,0) -> 0 | S95: =IF(G95>0,1000*J95/G95,0) -> 0 | T95: =IF(G95>0,1000*K95/G95,0) -> 0 | U95: =IF(G95>0,1000*L95/G95,0) -> 0 | V95: =IF(G95>0,1000*M95/G95,0) -> 0 | W95: =IF(G95>0,1000*N95/G95,0) -> 1.1688594 | X95: =IF(G95>0,1000*O95/G95,0) -> 0.027182777 | Y95: =SUMIFS($I$2:$I$5572,$E$2:$E$5572,E95) -> 1330 | Z95: =SUMIFS($J$2:$J$5572,$E$2:$E$5572,E95) -> 163 | AA95: =SUMIFS($K$2:$K$5572,$E$2:$E$5572,E95) -> 73 | AB95: =SUMIFS($L$2:$L$5572,$E$2:$E$5572,E95) -> 86 | AC95: =SUMIFS($M$2:$M$5572,$E$2:$E$5572,E95) -> 157 | AD95: =SUMIFS($N$2:$N$5572,$E$2:$E$5572,E95) -> 322 | AE95: =SUMIFS($O$2:$O$5572,$E$2:$E$5572,E95) -> 15 | AF95: =SUMIFS($P$2:$P$5572,$E$2:$E$5572,E95) -> 3 | AG95: =IF(SUMIFS($G$2:$G$5572,$E$2:$E$5572,E95)>0,1000*Y95/SUMIFS($G$2:$G$5572,$E$2:$E$5572,E95),0) -> 4.557932 | AH95: =12*(J95*'Programas e Observações'!$C$8+K95*'Programas e Observações'!$C$9+L95*('Programas e Observações'!$C$8+'Programas e Observações'!$C$9)+M95*'Programas e Observações'!$C$10) -> 0 | AI95: =12*(J95*'Programas e Observações'!$D$8+K95*'Programas e Observações'!$D$9+L95*('Programas e Observações'!$D$8+'Programas e Observações'!$D$9)+M95*'Programas e Observações'!$D$10) -> 0 | AJ95: 0 moradores pegam remédio de pressão ou diabetes de graça na Farmácia Popular | AK95: Sem o programa, gastariam pelo menos R$ 0 mil por ano
A96: 1301308 | B96: 130130 | C96: Codajás | D96: AM | E96: 13002 | F96: Rio Negro e Solimões | G96: 24572 | H96: =G96<'Programas e Observações'!$C$11 -> FALSE | I96: 0 | J96: 0 | K96: 0 | L96: 0 | M96: 0 | N96: 18 | O96: 2 | P96: 0 | R96: =IF(G96>0,1000*I96/G96,0) -> 0 | S96: =IF(G96>0,1000*J96/G96,0) -> 0 | T96: =IF(G96>0,1000*K96/G96,0) -> 0 | U96: =IF(G96>0,1000*L96/G96,0) -> 0 | V96: =IF(G96>0,1000*M96/G96,0) -> 0 | W96: =IF(G96>0,1000*N96/G96,0) -> 0.7325411 | X96: =IF(G96>0,1000*O96/G96,0) -> 0.081393456 | Y96: =SUMIFS($I$2:$I$5572,$E$2:$E$5572,E96) -> 1330 | Z96: =SUMIFS($J$2:$J$5572,$E$2:$E$5572,E96) -> 163 | AA96: =SUMIFS($K$2:$K$5572,$E$2:$E$5572,E96) -> 73 | AB96: =SUMIFS($L$2:$L$5572,$E$2:$E$5572,E96) -> 86 | AC96: =SUMIFS($M$2:$M$5572,$E$2:$E$5572,E96) -> 157 | AD96: =SUMIFS($N$2:$N$5572,$E$2:$E$5572,E96) -> 322 | AE96: =SUMIFS($O$2:$O$5572,$E$2:$E$5572,E96) -> 15 | AF96: =SUMIFS($P$2:$P$5572,$E$2:$E$5572,E96) -> 3 | AG96: =IF(SUMIFS($G$2:$G$5572,$E$2:$E$5572,E96)>0,1000*Y96/SUMIFS($G$2:$G$5572,$E$2:$E$5572,E96),0) -> 4.557932 | AH96: =12*(J96*'Programas e Observações'!$C$8+K96*'Programas e Observações'!$C$9+L96*('Programas e Observações'!$C$8+'Programas e Observações'!$C$9)+M96*'Programas e Observações'!$C$10) -> 0 | AI96: =12*(J96*'Programas e Observações'!$D$8+K96*'Programas e Observações'!$D$9+L96*('Programas e Observações'!$D$8+'Programas e Observações'!$D$9)+M96*'Programas e Observações'!$D$10) -> 0 | AJ96: 0 moradores pegam remédio de pressão ou diabetes de graça na Farmácia Popular | AK96: Sem o programa, gastariam pelo menos R$ 0 mil por ano
A97: 1301407 | B97: 130140 | C97: Eirunepé | D97: AM | E97: 13007 | F97: Regional Juruá | G97: 35793 | H97: =G97<'Programas e Observações'!$C$11 -> FALSE | I97: 103 | J97: 3 | K97: 1 | L97: 0 | M97: 0 | N97: 32 | O97: 3 | P97: 0 | R97: =IF(G97>0,1000*I97/G97,0) -> 2.8776576 | S97: =IF(G97>0,1000*J97/G97,0) -> 0.083815271 | T97: =IF(G97>0,1000*K97/G97,0) -> 0.027938424 | U97: =IF(G97>0,1000*L97/G97,0) -> 0 | V97: =IF(G97>0,1000*M97/G97,0) -> 0 | W97: =IF(G97>0,1000*N97/G97,0) -> 0.89402956 | X97: =IF(G97>0,1000*O97/G97,0) -> 0.083815271 | Y97: =SUMIFS($I$2:$I$5572,$E$2:$E$5572,E97) -> 242 | Z97: =SUMIFS($J$2:$J$5572,$E$2:$E$5572,E97) -> 9 | AA97: =SUMIFS($K$2:$K$5572,$E$2:$E$5572,E97) -> 2 | AB97: =SUMIFS($L$2:$L$5572,$E$2:$E$5572,E97) -> 1 | AC97: =SUMIFS($M$2:$M$5572,$E$2:$E$5572,E97) -> 0 | AD97: =SUMIFS($N$2:$N$5572,$E$2:$E$5572,E97) -> 83 | AE97: =SUMIFS($O$2:$O$5572,$E$2:$E$5572,E97) -> 15 | AF97: =SUMIFS($P$2:$P$5572,$E$2:$E$5572,E97) -> 1 | AG97: =IF(SUMIFS($G$2:$G$5572,$E$2:$E$5572,E97)>0,1000*Y97/SUMIFS($G$2:$G$5572,$E$2:$E$5572,E97),0) -> 1.7685275 | AH97: =12*(J97*'Programas e Observações'!$C$8+K97*'Programas e Observações'!$C$9+L97*('Programas e Observações'!$C$8+'Programas e Observações'!$C$9)+M97*'Programas e Observações'!$C$10) -> 1105.2 | AI97: =12*(J97*'Programas e Observações'!$D$8+K97*'Programas e Observações'!$D$9+L97*('Programas e Observações'!$D$8+'Programas e Observações'!$D$9)+M97*'Programas e Observações'!$D$10) -> 2205.72 | AJ97: 4 moradores pegam remédio de pressão ou diabetes de graça na Farmácia Popular | AK97: Sem o programa, gastariam pelo menos R$ 1 mil por ano
A98: 1301506 | B98: 130150 | C98: Envira | D98: AM | E98: 13007 | F98: Regional Juruá | G98: 17985 | H98: =G98<'Programas e Observações'!$C$11 -> TRUE | I98: 139 | J98: 6 | K98: 1 | L98: 1 | M98: 0 | N98: 14 | O98: 5 | P98: 0 | R98: =IF(G98>0,1000*I98/G98,0) -> 7.7286628 | S98: =IF(G98>0,1000*J98/G98,0) -> 0.33361134 | T98: =IF(G98>0,1000*K98/G98,0) -> 0.05560189 | U98: =IF(G98>0,1000*L98/G98,0) -> 0.05560189 | V98: =IF(G98>0,1000*M98/G98,0) -> 0 | W98: =IF(G98>0,1000*N98/G98,0) -> 0.77842647 | X98: =IF(G98>0,1000*O98/G98,0) -> 0.27800945 | Y98: =SUMIFS($I$2:$I$5572,$E$2:$E$5572,E98) -> 242 | Z98: =SUMIFS($J$2:$J$5572,$E$2:$E$5572,E98) -> 9 | AA98: =SUMIFS($K$2:$K$5572,$E$2:$E$5572,E98) -> 2 | AB98: =SUMIFS($L$2:$L$5572,$E$2:$E$5572,E98) -> 1 | AC98: =SUMIFS($M$2:$M$5572,$E$2:$E$5572,E98) -> 0 | AD98: =SUMIFS($N$2:$N$5572,$E$2:$E$5572,E98) -> 83 | AE98: =SUMIFS($O$2:$O$5572,$E$2:$E$5572,E98) -> 15 | AF98: =SUMIFS($P$2:$P$5572,$E$2:$E$5572,E98) -> 1 | AG98: =IF(SUMIFS($G$2:$G$5572,$E$2:$E$5572,E98)>0,1000*Y98/SUMIFS($G$2:$G$5572,$E$2:$E$5572,E98),0) -> 1.7685275 | AH98: =12*(J98*'Programas e Observações'!$C$8+K98*'Programas e Observações'!$C$9+L98*('Programas e Observações'!$C$8+'Programas e Observações'!$C$9)+M98*'Programas e Observações'!$C$10) -> 2409 | AI98: =12*(J98*'Programas e Observações'!$D$8+K98*'Programas e Observações'!$D$9+L98*('Programas e Observações'!$D$8+'Programas e Observações'!$D$9)+M98*'Programas e Observações'!$D$10) -> 4969.68 | AJ98: 8 moradores pegam remédio de pressão ou diabetes de graça na Farmácia Popular | AK98: Sem o programa, gastariam pelo menos R$ 2 mil por ano
A99: 1301605 | B99: 130160 | C99: Fonte Boa | D99: AM | E99: 13009 | F99: Alto Solimões | G99: 28227 | H99: =G99<'Programas e Observações'!$C$11 -> FALSE | I99: 0 | J99: 0 | K99: 0 | L99: 0 | M99: 0 | N99: 10 | O99: 1 | P99: 0 | R99: =IF(G99>0,1000*I99/G99,0) -> 0 | S99: =IF(G99>0,1000*J99/G99,0) -> 0 | T99: =IF(G99>0,1000*K99/G99,0) -> 0 | U99: =IF(G99>0,1000*L99/G99,0) -> 0 | V99: =IF(G99>0,1000*M99/G99,0) -> 0 | W99: =IF(G99>0,1000*N99/G99,0) -> 0.35427073 | X99: =IF(G99>0,1000*O99/G99,0) -> 0.035427073 | Y99: =SUMIFS($I$2:$I$5572,$E$2:$E$5572,E99) -> 632 | Z99: =SUMIFS($J$2:$J$5572,$E$2:$E$5572,E99) -> 303 | AA99: =SUMIFS($K$2:$K$5572,$E$2:$E$5572,E99) -> 91 | AB99: =SUMIFS($L$2:$L$5572,$E$2:$E$5572,E99) -> 31 | AC99: =SUMIFS($M$2:$M$5572,$E$2:$E$5572,E99) -> 17 | AD99: =SUMIFS($N$2:$N$5572,$E$2:$E$5572,E99) -> 77 | AE99: =SUMIFS($O$2:$O$5572,$E$2:$E$5572,E99) -> 11 | AF99: =SUMIFS($P$2:$P$5572,$E$2:$E$5572,E99) -> 2 | AG99: =IF(SUMIFS($G$2:$G$5572,$E$2:$E$5572,E99)>0,1000*Y99/SUMIFS($G$2:$G$5572,$E$2:$E$5572,E99),0) -> 2.2215583 | AH99: =12*(J99*'Programas e Observações'!$C$8+K99*'Programas e Observações'!$C$9+L99*('Programas e Observações'!$C$8+'Programas e Observações'!$C$9)+M99*'Programas e Observações'!$C$10) -> 0 | AI99: =12*(J99*'Programas e Observações'!$D$8+K99*'Programas e Observações'!$D$9+L99*('Programas e Observações'!$D$8+'Programas e Observações'!$D$9)+M99*'Programas e Observações'!$D$10) -> 0 | AJ99: 0 moradores pegam remédio de pressão ou diabetes de graça na Farmácia Popular | AK99: Sem o programa, gastariam pelo menos R$ 0 mil por ano
A100: 1301654 | B100: 130165 | C100: Guajará | D100: AM | E100: 13007 | F100: Regional Juruá | G100: 14344 | H100: =G100<'Programas e Observações'!$C$11 -> TRUE | I100: 0 | J100: 0 | K100: 0 | L100: 0 | M100: 0 | N100: 5 | O100: 1 | P100: 0 | R100: =IF(G100>0,1000*I100/G100,0) -> 0 | S100: =IF(G100>0,1000*J100/G100,0) -> 0 | T100: =IF(G100>0,1000*K100/G100,0) -> 0 | U100: =IF(G100>0,1000*L100/G100,0) -> 0 | V100: =IF(G100>0,1000*M100/G100,0) -> 0 | W100: =IF(G100>0,1000*N100/G100,0) -> 0.3485778 | X100: =IF(G100>0,1000*O100/G100,0) -> 0.069715561 | Y100: =SUMIFS($I$2:$I$5572,$E$2:$E$5572,E100) -> 242 | Z100: =SUMIFS($J$2:$J$5572,$E$2:$E$5572,E100) -> 9 | AA100: =SUMIFS($K$2:$K$5572,$E$2:$E$5572,E100) -> 2 | AB100: =SUMIFS($L$2:$L$5572,$E$2:$E$5572,E100) -> 1 | AC100: =SUMIFS($M$2:$M$5572,$E$2:$E$5572,E100) -> 0 | AD100: =SUMIFS($N$2:$N$5572,$E$2:$E$5572,E100) -> 83 | AE100: =SUMIFS($O$2:$O$5572,$E$2:$E$5572,E100) -> 15 | AF100: =SUMIFS($P$2:$P$5572,$E$2:$E$5572,E100) -> 1 | AG100: =IF(SUMIFS($G$2:$G$5572,$E$2:$E$5572,E100)>0,1000*Y100/SUMIFS($G$2:$G$5572,$E$2:$E$5572,E100),0) -> 1.7685275 | AH100: =12*(J100*'Programas e Observações'!$C$8+K100*'Programas e Observações'!$C$9+L100*('Programas e Observações'!$C$8+'Programas e Observações'!$C$9)+M100*'Programas e Observações'!$C$10) -> 0 | AI100: =12*(J100*'Programas e Observações'!$D$8+K100*'Programas e Observações'!$D$9+L100*('Programas e Observações'!$D$8+'Programas e Observações'!$D$9)+M100*'Programas e Observações'!$D$10) -> 0 | AJ100: 0 moradores pegam remédio de pressão ou diabetes de graça na Farmácia Popular | AK100: Sem o programa, gastariam pelo menos R$ 0 mil por ano
A101: 1301704 | B101: 130170 | C101: Humaitá | D101: AM | E101: 13003 | F101: Rio Madeira | G101: 63454 | H101: =G101<'Programas e Observações'!$C$11 -> FALSE | I101: 971 | J101: 454 | K101: 12 | L101: 289 | M101: 0 | N101: 126 | O101: 60 | P101: 1 | Q101: 78 | R101: =IF(G101>0,1000*I101/G101,0) -> 15.302424 | S101: =IF(G101>0,1000*J101/G101,0) -> 7.1547893 | T101: =IF(G101>0,1000*K101/G101,0) -> 0.18911337 | U101: =IF(G101>0,1000*L101/G101,0) -> 4.5544804 | V101: =IF(G101>0,1000*M101/G101,0) -> 0 | W101: =IF(G101>0,1000*N101/G101,0) -> 1.9856904 | X101: =IF(G101>0,1000*O101/G101,0) -> 0.94556687 | Y101: =SUMIFS($I$2:$I$5572,$E$2:$E$5572,E101) -> 971 | Z101: =SUMIFS($J$2:$J$5572,$E$2:$E$5572,E101) -> 454 | AA101: =SUMIFS($K$2:$K$5572,$E$2:$E$5572,E101) -> 12 | AB101: =SUMIFS($L$2:$L$5572,$E$2:$E$5572,E101) -> 289 | AC101: =SUMIFS($M$2:$M$5572,$E$2:$E$5572,E101) -> 0 | AD101: =SUMIFS($N$2:$N$5572,$E$2:$E$5572,E101) -> 185 | AE101: =SUMIFS($O$2:$O$5572,$E$2:$E$5572,E101) -> 86 | AF101: =SUMIFS($P$2:$P$5572,$E$2:$E$5572,E101) -> 2 | AG101: =IF(SUMIFS($G$2:$G$5572,$E$2:$E$5572,E101)>0,1000*Y101/SUMIFS($G$2:$G$5572,$E$2:$E$5572,E101),0) -> 4.7727418 | AH101: =12*(J101*'Programas e Observações'!$C$8+K101*'Programas e Observações'!$C$9+L101*('Programas e Observações'!$C$8+'Programas e Observações'!$C$9)+M101*'Programas e Observações'!$C$10) -> 300889.2 | AI101: =12*(J101*'Programas e Observações'!$D$8+K101*'Programas e Observações'!$D$9+L101*('Programas e Observações'!$D$8+'Programas e Observações'!$D$9)+M101*'Programas e Observações'!$D$10) -> 574603.32 | AJ101: 755 moradores pegam remédio de pressão ou diabetes de graça na Farmácia Popular | AK101: Sem o programa, gastariam pelo menos R$ 301 mil por ano
A102: 1301803 | B102: 130180 | C102: Ipixuna | D102: AM | E102: 13007 | F102: Regional Juruá | G102: 25629 | H102: =G102<'Programas e Observações'!$C$11 -> FALSE | I102: 0 | J102: 0 | K102: 0 | L102: 0 | M102: 0 | N102: 8 | O102: 4 | P102: 1 | R102: =IF(G102>0,1000*I102/G102,0) -> 0 | S102: =IF(G102>0,1000*J102/G102,0) -> 0 | T102: =IF(G102>0,1000*K102/G102,0) -> 0 | U102: =IF(G102>0,1000*L102/G102,0) -> 0 | V102: =IF(G102>0,1000*M102/G102,0) -> 0 | W102: =IF(G102>0,1000*N102/G102,0) -> 0.3121464 | X102: =IF(G102>0,1000*O102/G102,0) -> 0.1560732 | Y102: =SUMIFS($I$2:$I$5572,$E$2:$E$5572,E102) -> 242 | Z102: =SUMIFS($J$2:$J$5572,$E$2:$E$5572,E102) -> 9 | AA102: =SUMIFS($K$2:$K$5572,$E$2:$E$5572,E102) -> 2 | AB102: =SUMIFS($L$2:$L$5572,$E$2:$E$5572,E102) -> 1 | AC102: =SUMIFS($M$2:$M$5572,$E$2:$E$5572,E102) -> 0 | AD102: =SUMIFS($N$2:$N$5572,$E$2:$E$5572,E102) -> 83 | AE102: =SUMIFS($O$2:$O$5572,$E$2:$E$5572,E102) -> 15 | AF102: =SUMIFS($P$2:$P$5572,$E$2:$E$5572,E102) -> 1 | AG102: =IF(SUMIFS($G$2:$G$5572,$E$2:$E$5572,E102)>0,1000*Y102/SUMIFS($G$2:$G$5572,$E$2:$E$5572,E102),0) -> 1.7685275 | AH102: =12*(J102*'Programas e Observações'!$C$8+K102*'Programas e Observações'!$C$9+L102*('Programas e Observações'!$C$8+'Programas e Observações'!$C$9)+M102*'Programas e Observações'!$C$10) -> 0 | AI102: =12*(J102*'Programas e Observações'!$D$8+K102*'Programas e Observações'!$D$9+L102*('Programas e Observações'!$D$8+'Programas e Observações'!$D$9)+M102*'Programas e Observações'!$D$10) -> 0 | AJ102: 0 moradores pegam remédio de pressão ou diabetes de graça na Farmácia Popular | AK102: Sem o programa, gastariam pelo menos R$ 0 mil por ano
A103: 1301852 | B103: 130185 | C103: Iranduba | D103: AM | E103: 13001 | F103: Manaus, Entorno e Alto Rio Negro | G103: 68862 | H103: =G103<'Programas e Observações'!$C$11 -> FALSE | I103: 0 | J103: 0 | K103: 0 | L103: 0 | M103: 0 | N103: 140 | O103: 1 | P103: 1 | R103: =IF(G103>0,1000*I103/G103,0) -> 0 | S103: =IF(G103>0,1000*J103/G103,0) -> 0 | T103: =IF(G103>0,1000*K103/G103,0) -> 0 | U103: =IF(G103>0,1000*L103/G103,0) -> 0 | V103: =IF(G103>0,1000*M103/G103,0) -> 0 | W103: =IF(G103>0,1000*N103/G103,0) -> 2.0330516 | X103: =IF(G103>0,1000*O103/G103,0) -> 0.014521797 | Y103: =SUMIFS($I$2:$I$5572,$E$2:$E$5572,E103) -> 13707 | Z103: =SUMIFS($J$2:$J$5572,$E$2:$E$5572,E103) -> 2662 | AA103: =SUMIFS($K$2:$K$5572,$E$2:$E$5572,E103) -> 1816 | AB103: =SUMIFS($L$2:$L$5572,$E$2:$E$5572,E103) -> 1620 | AC103: =SUMIFS($M$2:$M$5572,$E$2:$E$5572,E103) -> 687 | AD103: =SUMIFS($N$2:$N$5572,$E$2:$E$5572,E103) -> 11419 | AE103: =SUMIFS($O$2:$O$5572,$E$2:$E$5572,E103) -> 592 | AF103: =SUMIFS($P$2:$P$5572,$E$2:$E$5572,E103) -> 8 | AG103: =IF(SUMIFS($G$2:$G$5572,$E$2:$E$5572,E103)>0,1000*Y103/SUMIFS($G$2:$G$5572,$E$2:$E$5572,E103),0) -> 5.1457416 | AH103: =12*(J103*'Programas e Observações'!$C$8+K103*'Programas e Observações'!$C$9+L103*('Programas e Observações'!$C$8+'Programas e Observações'!$C$9)+M103*'Programas e Observações'!$C$10) -> 0 | AI103: =12*(J103*'Programas e Observações'!$D$8+K103*'Programas e Observações'!$D$9+L103*('Programas e Observações'!$D$8+'Programas e Observações'!$D$9)+M103*'Programas e Observações'!$D$10) -> 0 | AJ103: 0 moradores pegam remédio de pressão ou diabetes de graça na Farmácia Popular | AK103: Sem o programa, gastariam pelo menos R$ 0 mil por ano
A104: 1301902 | B104: 130190 | C104: Itacoatiara | D104: AM | E104: 13004 | F104: Médio Amazonas | G104: 113917 | H104: =G104<'Programas e Observações'!$C$11 -> FALSE | I104: 0 | J104: 0 | K104: 0 | L104: 0 | M104: 0 | N104: 219 | O104: 4 | P104: 1 | Q104: 295 | R104: =IF(G104>0,1000*I104/G104,0) -> 0 | S104: =IF(G104>0,1000*J104/G104,0) -> 0 | T104: =IF(G104>0,1000*K104/G104,0) -> 0 | U104: =IF(G104>0,1000*L104/G104,0) -> 0 | V104: =IF(G104>0,1000*M104/G104,0) -> 0 | W104: =IF(G104>0,1000*N104/G104,0) -> 1.9224523 | X104: =IF(G104>0,1000*O104/G104,0) -> 0.035113284 | Y104: =SUMIFS($I$2:$I$5572,$E$2:$E$5572,E104) -> 0 | Z104: =SUMIFS($J$2:$J$5572,$E$2:$E$5572,E104) -> 0 | AA104: =SUMIFS($K$2:$K$5572,$E$2:$E$5572,E104) -> 0 | AB104: =SUMIFS($L$2:$L$5572,$E$2:$E$5572,E104) -> 0 | AC104: =SUMIFS($M$2:$M$5572,$E$2:$E$5572,E104) -> 0 | AD104: =SUMIFS($N$2:$N$5572,$E$2:$E$5572,E104) -> 265 | AE104: =SUMIFS($O$2:$O$5572,$E$2:$E$5572,E104) -> 10 | AF104: =SUMIFS($P$2:$P$5572,$E$2:$E$5572,E104) -> 2 | AG104: =IF(SUMIFS($G$2:$G$5572,$E$2:$E$5572,E104)>0,1000*Y104/SUMIFS($G$2:$G$5572,$E$2:$E$5572,E104),0) -> 0 | AH104: =12*(J104*'Programas e Observações'!$C$8+K104*'Programas e Observações'!$C$9+L104*('Programas e Observações'!$C$8+'Programas e Observações'!$C$9)+M104*'Programas e Observações'!$C$10) -> 0 | AI104: =12*(J104*'Programas e Observações'!$D$8+K104*'Programas e Observações'!$D$9+L104*('Programas e Observações'!$D$8+'Programas e Observações'!$D$9)+M104*'Programas e Observações'!$D$10) -> 0 | AJ104: 0 moradores pegam remédio de pressão ou diabetes de graça na Farmácia Popular | AK104: Sem o programa, gastariam pelo menos R$ 0 mil por ano
A105: 1301951 | B105: 130195 | C105: Itamarati | D105: AM | E105: 13007 | F105: Regional Juruá | G105: 11956 | H105: =G105<'Programas e Observações'!$C$11 -> TRUE | I105: 0 | J105: 0 | K105: 0 | L105: 0 | M105: 0 | N105: 3 | O105: 0 | P105: 0 | R105: =IF(G105>0,1000*I105/G105,0) -> 0 | S105: =IF(G105>0,1000*J105/G105,0) -> 0 | T105: =IF(G105>0,1000*K105/G105,0) -> 0 | U105: =IF(G105>0,1000*L105/G105,0) -> 0 | V105: =IF(G105>0,1000*M105/G105,0) -> 0 | W105: =IF(G105>0,1000*N105/G105,0) -> 0.25092004 | X105: =IF(G105>0,1000*O105/G105,0) -> 0 | Y105: =SUMIFS($I$2:$I$5572,$E$2:$E$5572,E105) -> 242 | Z105: =SUMIFS($J$2:$J$5572,$E$2:$E$5572,E105) -> 9 | AA105: =SUMIFS($K$2:$K$5572,$E$2:$E$5572,E105) -> 2 | AB105: =SUMIFS($L$2:$L$5572,$E$2:$E$5572,E105) -> 1 | AC105: =SUMIFS($M$2:$M$5572,$E$2:$E$5572,E105) -> 0 | AD105: =SUMIFS($N$2:$N$5572,$E$2:$E$5572,E105) -> 83 | AE105: =SUMIFS($O$2:$O$5572,$E$2:$E$5572,E105) -> 15 | AF105: =SUMIFS($P$2:$P$5572,$E$2:$E$5572,E105) -> 1 | AG105: =IF(SUMIFS($G$2:$G$5572,$E$2:$E$5572,E105)>0,1000*Y105/SUMIFS($G$2:$G$5572,$E$2:$E$5572,E105),0) -> 1.7685275 | AH105: =12*(J105*'Programas e Observações'!$C$8+K105*'Programas e Observações'!$C$9+L105*('Programas e Observações'!$C$8+'Programas e Observações'!$C$9)+M105*'Programas e Observações'!$C$10) -> 0 | AI105: =12*(J105*'Programas e Observações'!$D$8+K105*'Programas e Observações'!$D$9+L105*('Programas e Observações'!$D$8+'Programas e Observações'!$D$9)+M105*'Programas e Observações'!$D$10) -> 0 | AJ105: 0 moradores pegam remédio de pressão ou diabetes de graça na Farmácia Popular | AK105: Sem o programa, gastariam pelo menos R$ 0 mil por ano
A106: 1302009 | B106: 130200 | C106: Itapiranga | D106: AM | E106: 13004 | F106: Médio Amazonas | G106: 10955 | H106: =G106<'Programas e Observações'!$C$11 -> TRUE | I106: 0 | J106: 0 | K106: 0 | L106: 0 | M106: 0 | N106: 11 | O106: 2 | P106: 1 | R106: =IF(G106>0,1000*I106/G106,0) -> 0 | S106: =IF(G106>0,1000*J106/G106,0) -> 0 | T106: =IF(G106>0,1000*K106/G106,0) -> 0 | U106: =IF(G106>0,1000*L106/G106,0) -> 0 | V106: =IF(G106>0,1000*M106/G106,0) -> 0 | W106: =IF(G106>0,1000*N106/G106,0) -> 1.0041077 | X106: =IF(G106>0,1000*O106/G106,0) -> 0.18256504 | Y106: =SUMIFS($I$2:$I$5572,$E$2:$E$5572,E106) -> 0 | Z106: =SUMIFS($J$2:$J$5572,$E$2:$E$5572,E106) -> 0 | AA106: =SUMIFS($K$2:$K$5572,$E$2:$E$5572,E106) -> 0 | AB106: =SUMIFS($L$2:$L$5572,$E$2:$E$5572,E106) -> 0 | AC106: =SUMIFS($M$2:$M$5572,$E$2:$E$5572,E106) -> 0 | AD106: =SUMIFS($N$2:$N$5572,$E$2:$E$5572,E106) -> 265 | AE106: =SUMIFS($O$2:$O$5572,$E$2:$E$5572,E106) -> 10 | AF106: =SUMIFS($P$2:$P$5572,$E$2:$E$5572,E106) -> 2 | AG106: =IF(SUMIFS($G$2:$G$5572,$E$2:$E$5572,E106)>0,1000*Y106/SUMIFS($G$2:$G$5572,$E$2:$E$5572,E106),0) -> 0 | AH106: =12*(J106*'Programas e Observações'!$C$8+K106*'Programas e Observações'!$C$9+L106*('Programas e Observações'!$C$8+'Programas e Observações'!$C$9)+M106*'Programas e Observações'!$C$10) -> 0 | AI106: =12*(J106*'Programas e Observações'!$D$8+K106*'Programas e Observações'!$D$9+L106*('Programas e Observações'!$D$8+'Programas e Observações'!$D$9)+M106*'Programas e Observações'!$D$10) -> 0 | AJ106: 0 moradores pegam remédio de pressão ou diabetes de graça na Farmácia Popular | AK106: Sem o programa, gastariam pelo menos R$ 0 mil por ano
A107: 1302108 | B107: 130210 | C107: Japurá | D107: AM | E107: 13008 | F107: Triângulo | G107: 9420 | H107: =G107<'Programas e Observações'!$C$11 -> TRUE | I107: 0 | J107: 0 | K107: 0 | L107: 0 | M107: 0 | N107: 5 | O107: 1 | P107: 1 | R107: =IF(G107>0,1000*I107/G107,0) -> 0 | S107: =IF(G107>0,1000*J107/G107,0) -> 0 | T107: =IF(G107>0,1000*K107/G107,0) -> 0 | U107: =IF(G107>0,1000*L107/G107,0) -> 0 | V107: =IF(G107>0,1000*M107/G107,0) -> 0 | W107: =IF(G107>0,1000*N107/G107,0) -> 0.53078556 | X107: =IF(G107>0,1000*O107/G107,0) -> 0.10615711 | Y107: =SUMIFS($I$2:$I$5572,$E$2:$E$5572,E107) -> 0 | Z107: =SUMIFS($J$2:$J$5572,$E$2:$E$5572,E107) -> 0 | AA107: =SUMIFS($K$2:$K$5572,$E$2:$E$5572,E107) -> 0 | AB107: =SUMIFS($L$2:$L$5572,$E$2:$E$5572,E107) -> 0 | AC107: =SUMIFS($M$2:$M$5572,$E$2:$E$5572,E107) -> 0 | AD107: =SUMIFS($N$2:$N$5572,$E$2:$E$5572,E107) -> 64 | AE107: =SUMIFS($O$2:$O$5572,$E$2:$E$5572,E107) -> 5 | AF107: =SUMIFS($P$2:$P$5572,$E$2:$E$5572,E107) -> 3 | AG107: =IF(SUMIFS($G$2:$G$5572,$E$2:$E$5572,E107)>0,1000*Y107/SUMIFS($G$2:$G$5572,$E$2:$E$5572,E107),0) -> 0 | AH107: =12*(J107*'Programas e Observações'!$C$8+K107*'Programas e Observações'!$C$9+L107*('Programas e Observações'!$C$8+'Programas e Observações'!$C$9)+M107*'Programas e Observações'!$C$10) -> 0 | AI107: =12*(J107*'Programas e Observações'!$D$8+K107*'Programas e Observações'!$D$9+L107*('Programas e Observações'!$D$8+'Programas e Observações'!$D$9)+M107*'Programas e Observações'!$D$10) -> 0 | AJ107: 0 moradores pegam remédio de pressão ou diabetes de graça na Farmácia Popular | AK107: Sem o programa, gastariam pelo menos R$ 0 mil por ano
A108: 1302207 | B108: 130220 | C108: Juruá | D108: AM | E108: 13008 | F108: Triângulo | G108: 11093 | H108: =G108<'Programas e Observações'!$C$11 -> TRUE | I108: 0 | J108: 0 | K108: 0 | L108: 0 | M108: 0 | N108: 10 | O108: 0 | P108: 0 | R108: =IF(G108>0,1000*I108/G108,0) -> 0 | S108: =IF(G108>0,1000*J108/G108,0) -> 0 | T108: =IF(G108>0,1000*K108/G108,0) -> 0 | U108: =IF(G108>0,1000*L108/G108,0) -> 0 | V108: =IF(G108>0,1000*M108/G108,0) -> 0 | W108: =IF(G108>0,1000*N108/G108,0) -> 0.9014694 | X108: =IF(G108>0,1000*O108/G108,0) -> 0 | Y108: =SUMIFS($I$2:$I$5572,$E$2:$E$5572,E108) -> 0 | Z108: =SUMIFS($J$2:$J$5572,$E$2:$E$5572,E108) -> 0 | AA108: =SUMIFS($K$2:$K$5572,$E$2:$E$5572,E108) -> 0 | AB108: =SUMIFS($L$2:$L$5572,$E$2:$E$5572,E108) -> 0 | AC108: =SUMIFS($M$2:$M$5572,$E$2:$E$5572,E108) -> 0 | AD108: =SUMIFS($N$2:$N$5572,$E$2:$E$5572,E108) -> 64 | AE108: =SUMIFS($O$2:$O$5572,$E$2:$E$5572,E108) -> 5 | AF108: =SUMIFS($P$2:$P$5572,$E$2:$E$5572,E108) -> 3 | AG108: =IF(SUMIFS($G$2:$G$5572,$E$2:$E$5572,E108)>0,1000*Y108/SUMIFS($G$2:$G$5572,$E$2:$E$5572,E108),0) -> 0 | AH108: =12*(J108*'Programas e Observações'!$C$8+K108*'Programas e Observações'!$C$9+L108*('Programas e Observações'!$C$8+'Programas e Observações'!$C$9)+M108*'Programas e Observações'!$C$10) -> 0 | AI108: =12*(J108*'Programas e Observações'!$D$8+K108*'Programas e Observações'!$D$9+L108*('Programas e Observações'!$D$8+'Programas e Observações'!$D$9)+M108*'Programas e Observações'!$D$10) -> 0 | AJ108: 0 moradores pegam remédio de pressão ou diabetes de graça na Farmácia Popular | AK108: Sem o programa, gastariam pelo menos R$ 0 mil por ano
A109: 1302306 | B109: 130230 | C109: Jutaí | D109: AM | E109: 13009 | F109: Alto Solimões | G109: 28202 | H109: =G109<'Programas e Observações'!$C$11 -> FALSE | I109: 0 | J109: 0 | K109: 0 | L109: 0 | M109: 0 | N109: 14 | O109: 1 | P109: 0 | R109: =IF(G109>0,1000*I109/G109,0) -> 0 | S109: =IF(G109>0,1000*J109/G109,0) -> 0 | T109: =IF(G109>0,1000*K109/G109,0) -> 0 | U109: =IF(G109>0,1000*L109/G109,0) -> 0 | V109: =IF(G109>0,1000*M109/G109,0) -> 0 | W109: =IF(G109>0,1000*N109/G109,0) -> 0.49641869 | X109: =IF(G109>0,1000*O109/G109,0) -> 0.035458478 | Y109: =SUMIFS($I$2:$I$5572,$E$2:$E$5572,E109) -> 632 | Z109: =SUMIFS($J$2:$J$5572,$E$2:$E$5572,E109) -> 303 | AA109: =SUMIFS($K$2:$K$5572,$E$2:$E$5572,E109) -> 91 | AB109: =SUMIFS($L$2:$L$5572,$E$2:$E$5572,E109) -> 31 | AC109: =SUMIFS($M$2:$M$5572,$E$2:$E$5572,E109) -> 17 | AD109: =SUMIFS($N$2:$N$5572,$E$2:$E$5572,E109) -> 77 | AE109: =SUMIFS($O$2:$O$5572,$E$2:$E$5572,E109) -> 11 | AF109: =SUMIFS($P$2:$P$5572,$E$2:$E$5572,E109) -> 2 | AG109: =IF(SUMIFS($G$2:$G$5572,$E$2:$E$5572,E109)>0,1000*Y109/SUMIFS($G$2:$G$5572,$E$2:$E$5572,E109),0) -> 2.2215583 | AH109: =12*(J109*'Programas e Observações'!$C$8+K109*'Programas e Observações'!$C$9+L109*('Programas e Observações'!$C$8+'Programas e Observações'!$C$9)+M109*'Programas e Observações'!$C$10) -> 0 | AI109: =12*(J109*'Programas e Observações'!$D$8+K109*'Programas e Observações'!$D$9+L109*('Programas e Observações'!$D$8+'Programas e Observações'!$D$9)+M109*'Programas e Observações'!$D$10) -> 0 | AJ109: 0 moradores pegam remédio de pressão ou diabetes de graça na Farmácia Popular | AK109: Sem o programa, gastariam pelo menos R$ 0 mil por ano
A110: 1302405 | B110: 130240 | C110: Lábrea | D110: AM | E110: 13006 | F110: Regional Purus | G110: 49469 | H110: =G110<'Programas e Observações'!$C$11 -> FALSE | I110: 875 | J110: 530 | K110: 52 | L110: 148 | M110: 12 | N110: 23 | O110: 25 | P110: 1 | R110: =IF(G110>0,1000*I110/G110,0) -> 17.687845 | S110: =IF(G110>0,1000*J110/G110,0) -> 10.71378 | T110: =IF(G110>0,1000*K110/G110,0) -> 1.0511634 | U110: =IF(G110>0,1000*L110/G110,0) -> 2.9917726 | V110: =IF(G110>0,1000*M110/G110,0) -> 0.24257616 | W110: =IF(G110>0,1000*N110/G110,0) -> 0.46493764 | X110: =IF(G110>0,1000*O110/G110,0) -> 0.505367 | Y110: =SUMIFS($I$2:$I$5572,$E$2:$E$5572,E110) -> 875 | Z110: =SUMIFS($J$2:$J$5572,$E$2:$E$5572,E110) -> 530 | AA110: =SUMIFS($K$2:$K$5572,$E$2:$E$5572,E110) -> 52 | AB110: =SUMIFS($L$2:$L$5572,$E$2:$E$5572,E110) -> 148 | AC110: =SUMIFS($M$2:$M$5572,$E$2:$E$5572,E110) -> 12 | AD110: =SUMIFS($N$2:$N$5572,$E$2:$E$5572,E110) -> 101 | AE110: =SUMIFS($O$2:$O$5572,$E$2:$E$5572,E110) -> 48 | AF110: =SUMIFS($P$2:$P$5572,$E$2:$E$5572,E110) -> 3 | AG110: =IF(SUMIFS($G$2:$G$5572,$E$2:$E$5572,E110)>0,1000*Y110/SUMIFS($G$2:$G$5572,$E$2:$E$5572,E110),0) -> 5.9391693 | AH110: =12*(J110*'Programas e Observações'!$C$8+K110*'Programas e Observações'!$C$9+L110*('Programas e Observações'!$C$8+'Programas e Observações'!$C$9)+M110*'Programas e Observações'!$C$10) -> 242858.16 | AI110: =12*(J110*'Programas e Observações'!$D$8+K110*'Programas e Observações'!$D$9+L110*('Programas e Observações'!$D$8+'Programas e Observações'!$D$9)+M110*'Programas e Observações'!$D$10) -> 491185.44 | AJ110: 730 moradores pegam remédio de pressão ou diabetes de graça na Farmácia Popular | AK110: Sem o programa, gastariam pelo menos R$ 243 mil por ano
A111: 1302504 | B111: 130250 | C111: Manacapuru | D111: AM | E111: 13002 | F111: Rio Negro e Solimões | G111: 111751 | H111: =G111<'Programas e Observações'!$C$11 -> FALSE | I111: 1330 | J111: 163 | K111: 73 | L111: 86 | M111: 157 | N111: 152 | O111: 6 | P111: 1 | Q111: 145 | R111: =IF(G111>0,1000*I111/G111,0) -> 11.901459 | S111: =IF(G111>0,1000*J111/G111,0) -> 1.4585999 | T111: =IF(G111>0,1000*K111/G111,0) -> 0.653238 | U111: =IF(G111>0,1000*L111/G111,0) -> 0.76956806 | V111: =IF(G111>0,1000*M111/G111,0) -> 1.4049091 | W111: =IF(G111>0,1000*N111/G111,0) -> 1.3601668 | X111: =IF(G111>0,1000*O111/G111,0) -> 0.053690795 | Y111: =SUMIFS($I$2:$I$5572,$E$2:$E$5572,E111) -> 1330 | Z111: =SUMIFS($J$2:$J$5572,$E$2:$E$5572,E111) -> 163 | AA111: =SUMIFS($K$2:$K$5572,$E$2:$E$5572,E111) -> 73 | AB111: =SUMIFS($L$2:$L$5572,$E$2:$E$5572,E111) -> 86 | AC111: =SUMIFS($M$2:$M$5572,$E$2:$E$5572,E111) -> 157 | AD111: =SUMIFS($N$2:$N$5572,$E$2:$E$5572,E111) -> 322 | AE111: =SUMIFS($O$2:$O$5572,$E$2:$E$5572,E111) -> 15 | AF111: =SUMIFS($P$2:$P$5572,$E$2:$E$5572,E111) -> 3 | AG111: =IF(SUMIFS($G$2:$G$5572,$E$2:$E$5572,E111)>0,1000*Y111/SUMIFS($G$2:$G$5572,$E$2:$E$5572,E111),0) -> 4.557932 | AH111: =12*(J111*'Programas e Observações'!$C$8+K111*'Programas e Observações'!$C$9+L111*('Programas e Observações'!$C$8+'Programas e Observações'!$C$9)+M111*'Programas e Observações'!$C$10) -> 213228.96 | AI111: =12*(J111*'Programas e Observações'!$D$8+K111*'Programas e Observações'!$D$9+L111*('Programas e Observações'!$D$8+'Programas e Observações'!$D$9)+M111*'Programas e Observações'!$D$10) -> 308455.68 | AJ111: 322 moradores pegam remédio de pressão ou diabetes de graça na Farmácia Popular | AK111: Sem o programa, gastariam pelo menos R$ 213 mil por ano
A112: 1302553 | B112: 130255 | C112: Manaquiri | D112: AM | E112: 13001 | F112: Manaus, Entorno e Alto Rio Negro | G112: 16211 | H112: =G112<'Programas e Observações'!$C$11 -> TRUE | I112: 0 | J112: 0 | K112: 0 | L112: 0 | M112: 0 | N112: 29 | O112: 2 | P112: 1 | R112: =IF(G112>0,1000*I112/G112,0) -> 0 | S112: =IF(G112>0,1000*J112/G112,0) -> 0 | T112: =IF(G112>0,1000*K112/G112,0) -> 0 | U112: =IF(G112>0,1000*L112/G112,0) -> 0 | V112: =IF(G112>0,1000*M112/G112,0) -> 0 | W112: =IF(G112>0,1000*N112/G112,0) -> 1.7889088 | X112: =IF(G112>0,1000*O112/G112,0) -> 0.12337302 | Y112: =SUMIFS($I$2:$I$5572,$E$2:$E$5572,E112) -> 13707 | Z112: =SUMIFS($J$2:$J$5572,$E$2:$E$5572,E112) -> 2662 | AA112: =SUMIFS($K$2:$K$5572,$E$2:$E$5572,E112) -> 1816 | AB112: =SUMIFS($L$2:$L$5572,$E$2:$E$5572,E112) -> 1620 | AC112: =SUMIFS($M$2:$M$5572,$E$2:$E$5572,E112) -> 687 | AD112: =SUMIFS($N$2:$N$5572,$E$2:$E$5572,E112) -> 11419 | AE112: =SUMIFS($O$2:$O$5572,$E$2:$E$5572,E112) -> 592 | AF112: =SUMIFS($P$2:$P$5572,$E$2:$E$5572,E112) -> 8 | AG112: =IF(SUMIFS($G$2:$G$5572,$E$2:$E$5572,E112)>0,1000*Y112/SUMIFS($G$2:$G$5572,$E$2:$E$5572,E112),0) -> 5.1457416 | AH112: =12*(J112*'Programas e Observações'!$C$8+K112*'Programas e Observações'!$C$9+L112*('Programas e Observações'!$C$8+'Programas e Observações'!$C$9)+M112*'Programas e Observações'!$C$10) -> 0 | AI112: =12*(J112*'Programas e Observações'!$D$8+K112*'Programas e Observações'!$D$9+L112*('Programas e Observações'!$D$8+'Programas e Observações'!$D$9)+M112*'Programas e Observações'!$D$10) -> 0 | AJ112: 0 moradores pegam remédio de pressão ou diabetes de graça na Farmácia Popular | AK112: Sem o programa, gastariam pelo menos R$ 0 mil por ano
A113: 1302603 | B113: 130260 | C113: Manaus | D113: AM | E113: 13001 | F113: Manaus, Entorno e Alto Rio Negro | G113: 2303732 | H113: =G113<'Programas e Observações'!$C$11 -> FALSE | I113: 13699 | J113: 2656 | K113: 1816 | L113: 1619 | M113: 687 | N113: 10978 | O113: 574 | P113: 2 | Q113: 14672 | R113: =IF(G113>0,1000*I113/G113,0) -> 5.9464382 | S113: =IF(G113>0,1000*J113/G113,0) -> 1.1529119 | T113: =IF(G113>0,1000*K113/G113,0) -> 0.78828614 | U113: =IF(G113>0,1000*L113/G113,0) -> 0.70277272 | V113: =IF(G113>0,1000*M113/G113,0) -> 0.29821177 | W113: =IF(G113>0,1000*N113/G113,0) -> 4.7653112 | X113: =IF(G113>0,1000*O113/G113,0) -> 0.24916093 | Y113: =SUMIFS($I$2:$I$5572,$E$2:$E$5572,E113) -> 13707 | Z113: =SUMIFS($J$2:$J$5572,$E$2:$E$5572,E113) -> 2662 | AA113: =SUMIFS($K$2:$K$5572,$E$2:$E$5572,E113) -> 1816 | AB113: =SUMIFS($L$2:$L$5572,$E$2:$E$5572,E113) -> 1620 | AC113: =SUMIFS($M$2:$M$5572,$E$2:$E$5572,E113) -> 687 | AD113: =SUMIFS($N$2:$N$5572,$E$2:$E$5572,E113) -> 11419 | AE113: =SUMIFS($O$2:$O$5572,$E$2:$E$5572,E113) -> 592 | AF113: =SUMIFS($P$2:$P$5572,$E$2:$E$5572,E113) -> 8 | AG113: =IF(SUMIFS($G$2:$G$5572,$E$2:$E$5572,E113)>0,1000*Y113/SUMIFS($G$2:$G$5572,$E$2:$E$5572,E113),0) -> 5.1457416 | AH113: =12*(J113*'Programas e Observações'!$C$8+K113*'Programas e Observações'!$C$9+L113*('Programas e Observações'!$C$8+'Programas e Observações'!$C$9)+M113*'Programas e Observações'!$C$10) -> 2961045.4 | AI113: =12*(J113*'Programas e Observações'!$D$8+K113*'Programas e Observações'!$D$9+L113*('Programas e Observações'!$D$8+'Programas e Observações'!$D$9)+M113*'Programas e Observações'!$D$10) -> 4582512.7 | AJ113: 6.091 moradores pegam remédio de pressão ou diabetes de graça na Farmácia Popular | AK113: Sem o programa, gastariam pelo menos R$ 3,0 milhões por ano
A114: 1302702 | B114: 130270 | C114: Manicoré | D114: AM | E114: 13003 | F114: Rio Madeira | G114: 58018 | H114: =G114<'Programas e Observações'!$C$11 -> FALSE | I114: 0 | J114: 0 | K114: 0 | L114: 0 | M114: 0 | N114: 18 | O114: 8 | P114: 0 | Q114: 39 | R114: =IF(G114>0,1000*I114/G114,0) -> 0 | S114: =IF(G114>0,1000*J114/G114,0) -> 0 | T114: =IF(G114>0,1000*K114/G114,0) -> 0 | U114: =IF(G114>0,1000*L114/G114,0) -> 0 | V114: =IF(G114>0,1000*M114/G114,0) -> 0 | W114: =IF(G114>0,1000*N114/G114,0) -> 0.31024854 | X114: =IF(G114>0,1000*O114/G114,0) -> 0.13788824 | Y114: =SUMIFS($I$2:$I$5572,$E$2:$E$5572,E114) -> 971 | Z114: =SUMIFS($J$2:$J$5572,$E$2:$E$5572,E114) -> 454 | AA114: =SUMIFS($K$2:$K$5572,$E$2:$E$5572,E114) -> 12 | AB114: =SUMIFS($L$2:$L$5572,$E$2:$E$5572,E114) -> 289 | AC114: =SUMIFS($M$2:$M$5572,$E$2:$E$5572,E114) -> 0 | AD114: =SUMIFS($N$2:$N$5572,$E$2:$E$5572,E114) -> 185 | AE114: =SUMIFS($O$2:$O$5572,$E$2:$E$5572,E114) -> 86 | AF114: =SUMIFS($P$2:$P$5572,$E$2:$E$5572,E114) -> 2 | AG114: =IF(SUMIFS($G$2:$G$5572,$E$2:$E$5572,E114)>0,1000*Y114/SUMIFS($G$2:$G$5572,$E$2:$E$5572,E114),0) -> 4.7727418 | AH114: =12*(J114*'Programas e Observações'!$C$8+K114*'Programas e Observações'!$C$9+L114*('Programas e Observações'!$C$8+'Programas e Observações'!$C$9)+M114*'Programas e Observações'!$C$10) -> 0 | AI114: =12*(J114*'Programas e Observações'!$D$8+K114*'Programas e Observações'!$D$9+L114*('Programas e Observações'!$D$8+'Programas e Observações'!$D$9)+M114*'Programas e Observações'!$D$10) -> 0 | AJ114: 0 moradores pegam remédio de pressão ou diabetes de graça na Farmácia Popular | AK114: Sem o programa, gastariam pelo menos R$ 0 mil por ano
A115: 1302801 | B115: 130280 | C115: Maraã | D115: AM | E115: 13008 | F115: Triângulo | G115: 15815 | H115: =G115<'Programas e Observações'!$C$11 -> TRUE | I115: 0 | J115: 0 | K115: 0 | L115: 0 | M115: 0 | N115: 2 | O115: 1 | P115: 1 | R115: =IF(G115>0,1000*I115/G115,0) -> 0 | S115: =IF(G115>0,1000*J115/G115,0) -> 0 | T115: =IF(G115>0,1000*K115/G115,0) -> 0 | U115: =IF(G115>0,1000*L115/G115,0) -> 0 | V115: =IF(G115>0,1000*M115/G115,0) -> 0 | W115: =IF(G115>0,1000*N115/G115,0) -> 0.12646222 | X115: =IF(G115>0,1000*O115/G115,0) -> 0.06323111 | Y115: =SUMIFS($I$2:$I$5572,$E$2:$E$5572,E115) -> 0 | Z115: =SUMIFS($J$2:$J$5572,$E$2:$E$5572,E115) -> 0 | AA115: =SUMIFS($K$2:$K$5572,$E$2:$E$5572,E115) -> 0 | AB115: =SUMIFS($L$2:$L$5572,$E$2:$E$5572,E115) -> 0 | AC115: =SUMIFS($M$2:$M$5572,$E$2:$E$5572,E115) -> 0 | AD115: =SUMIFS($N$2:$N$5572,$E$2:$E$5572,E115) -> 64 | AE115: =SUMIFS($O$2:$O$5572,$E$2:$E$5572,E115) -> 5 | AF115: =SUMIFS($P$2:$P$5572,$E$2:$E$5572,E115) -> 3 | AG115: =IF(SUMIFS($G$2:$G$5572,$E$2:$E$5572,E115)>0,1000*Y115/SUMIFS($G$2:$G$5572,$E$2:$E$5572,E115),0) -> 0 | AH115: =12*(J115*'Programas e Observações'!$C$8+K115*'Programas e Observações'!$C$9+L115*('Programas e Observações'!$C$8+'Programas e Observações'!$C$9)+M115*'Programas e Observações'!$C$10) -> 0 | AI115: =12*(J115*'Programas e Observações'!$D$8+K115*'Programas e Observações'!$D$9+L115*('Programas e Observações'!$D$8+'Programas e Observações'!$D$9)+M115*'Programas e Observações'!$D$10) -> 0 | AJ115: 0 moradores pegam remédio de pressão ou diabetes de graça na Farmácia Popular | AK115: Sem o programa, gastariam pelo menos R$ 0 mil por ano
A116: 1302900 | B116: 130290 | C116: Maués | D116: AM | E116: 13005 | F116: Baixo Amazonas | G116: 66336 | H116: =G116<'Programas e Observações'!$C$11 -> FALSE | I116: 0 | J116: 0 | K116: 0 | L116: 0 | M116: 0 | N116: 23 | O116: 3 | P116: 1 | Q116: 69 | R116: =IF(G116>0,1000*I116/G116,0) -> 0 | S116: =IF(G116>0,1000*J116/G116,0) -> 0 | T116: =IF(G116>0,1000*K116/G116,0) -> 0 | U116: =IF(G116>0,1000*L116/G116,0) -> 0 | V116: =IF(G116>0,1000*M116/G116,0) -> 0 | W116: =IF(G116>0,1000*N116/G116,0) -> 0.34671973 | X116: =IF(G116>0,1000*O116/G116,0) -> 0.045224313 | Y116: =SUMIFS($I$2:$I$5572,$E$2:$E$5572,E116) -> 0 | Z116: =SUMIFS($J$2:$J$5572,$E$2:$E$5572,E116) -> 0 | AA116: =SUMIFS($K$2:$K$5572,$E$2:$E$5572,E116) -> 0 | AB116: =SUMIFS($L$2:$L$5572,$E$2:$E$5572,E116) -> 0 | AC116: =SUMIFS($M$2:$M$5572,$E$2:$E$5572,E116) -> 0 | AD116: =SUMIFS($N$2:$N$5572,$E$2:$E$5572,E116) -> 483 | AE116: =SUMIFS($O$2:$O$5572,$E$2:$E$5572,E116) -> 13 | AF116: =SUMIFS($P$2:$P$5572,$E$2:$E$5572,E116) -> 2 | AG116: =IF(SUMIFS($G$2:$G$5572,$E$2:$E$5572,E116)>0,1000*Y116/SUMIFS($G$2:$G$5572,$E$2:$E$5572,E116),0) -> 0 | AH116: =12*(J116*'Programas e Observações'!$C$8+K116*'Programas e Observações'!$C$9+L116*('Programas e Observações'!$C$8+'Programas e Observações'!$C$9)+M116*'Programas e Observações'!$C$10) -> 0 | AI116: =12*(J116*'Programas e Observações'!$D$8+K116*'Programas e Observações'!$D$9+L116*('Programas e Observações'!$D$8+'Programas e Observações'!$D$9)+M116*'Programas e Observações'!$D$10) -> 0 | AJ116: 0 moradores pegam remédio de pressão ou diabetes de graça na Farmácia Popular | AK116: Sem o programa, gastariam pelo menos R$ 0 mil por ano
A117: 1303007 | B117: 130300 | C117: Nhamundá | D117: AM | E117: 13005 | F117: Baixo Amazonas | G117: 21251 | H117: =G117<'Programas e Observações'!$C$11 -> FALSE | I117: 0 | J117: 0 | K117: 0 | L117: 0 | M117: 0 | N117: 9 | O117: 2 | P117: 0 | R117: =IF(G117>0,1000*I117/G117,0) -> 0 | S117: =IF(G117>0,1000*J117/G117,0) -> 0 | T117: =IF(G117>0,1000*K117/G117,0) -> 0 | U117: =IF(G117>0,1000*L117/G117,0) -> 0 | V117: =IF(G117>0,1000*M117/G117,0) -> 0 | W117: =IF(G117>0,1000*N117/G117,0) -> 0.42350948 | X117: =IF(G117>0,1000*O117/G117,0) -> 0.094113218 | Y117: =SUMIFS($I$2:$I$5572,$E$2:$E$5572,E117) -> 0 | Z117: =SUMIFS($J$2:$J$5572,$E$2:$E$5572,E117) -> 0 | AA117: =SUMIFS($K$2:$K$5572,$E$2:$E$5572,E117) -> 0 | AB117: =SUMIFS($L$2:$L$5572,$E$2:$E$5572,E117) -> 0 | AC117: =SUMIFS($M$2:$M$5572,$E$2:$E$5572,E117) -> 0 | AD117: =SUMIFS($N$2:$N$5572,$E$2:$E$5572,E117) -> 483 | AE117: =SUMIFS($O$2:$O$5572,$E$2:$E$5572,E117) -> 13 | AF117: =SUMIFS($P$2:$P$5572,$E$2:$E$5572,E117) -> 2 | AG117: =IF(SUMIFS($G$2:$G$5572,$E$2:$E$5572,E117)>0,1000*Y117/SUMIFS($G$2:$G$5572,$E$2:$E$5572,E117),0) -> 0 | AH117: =12*(J117*'Programas e Observações'!$C$8+K117*'Programas e Observações'!$C$9+L117*('Programas e Observações'!$C$8+'Programas e Observações'!$C$9)+M117*'Programas e Observações'!$C$10) -> 0 | AI117: =12*(J117*'Programas e Observações'!$D$8+K117*'Programas e Observações'!$D$9+L117*('Programas e Observações'!$D$8+'Programas e Observações'!$D$9)+M117*'Programas e Observações'!$D$10) -> 0 | AJ117: 0 moradores pegam remédio de pressão ou diabetes de graça na Farmácia Popular | AK117: Sem o programa, gastariam pelo menos R$ 0 mil por ano
A118: 1303106 | B118: 130310 | C118: Nova Olinda do Norte | D118: AM | E118: 13001 | F118: Manaus, Entorno e Alto Rio Negro | G118: 28123 | H118: =G118<'Programas e Observações'!$C$11 -> FALSE | I118: 0 | J118: 0 | K118: 0 | L118: 0 | M118: 0 | N118: 13 | O118: 0 | P118: 1 | R118: =IF(G118>0,1000*I118/G118,0) -> 0 | S118: =IF(G118>0,1000*J118/G118,0) -> 0 | T118: =IF(G118>0,1000*K118/G118,0) -> 0 | U118: =IF(G118>0,1000*L118/G118,0) -> 0 | V118: =IF(G118>0,1000*M118/G118,0) -> 0 | W118: =IF(G118>0,1000*N118/G118,0) -> 0.46225509 | X118: =IF(G118>0,1000*O118/G118,0) -> 0 | Y118: =SUMIFS($I$2:$I$5572,$E$2:$E$5572,E118) -> 13707 | Z118: =SUMIFS($J$2:$J$5572,$E$2:$E$5572,E118) -> 2662 | AA118: =SUMIFS($K$2:$K$5572,$E$2:$E$5572,E118) -> 1816 | AB118: =SUMIFS($L$2:$L$5572,$E$2:$E$5572,E118) -> 1620 | AC118: =SUMIFS($M$2:$M$5572,$E$2:$E$5572,E118) -> 687 | AD118: =SUMIFS($N$2:$N$5572,$E$2:$E$5572,E118) -> 11419 | AE118: =SUMIFS($O$2:$O$5572,$E$2:$E$5572,E118) -> 592 | AF118: =SUMIFS($P$2:$P$5572,$E$2:$E$5572,E118) -> 8 | AG118: =IF(SUMIFS($G$2:$G$5572,$E$2:$E$5572,E118)>0,1000*Y118/SUMIFS($G$2:$G$5572,$E$2:$E$5572,E118),0) -> 5.1457416 | AH118: =12*(J118*'Programas e Observações'!$C$8+K118*'Programas e Observações'!$C$9+L118*('Programas e Observações'!$C$8+'Programas e Observações'!$C$9)+M118*'Programas e Observações'!$C$10) -> 0 | AI118: =12*(J118*'Programas e Observações'!$D$8+K118*'Programas e Observações'!$D$9+L118*('Programas e Observações'!$D$8+'Programas e Observações'!$D$9)+M118*'Programas e Observações'!$D$10) -> 0 | AJ118: 0 moradores pegam remédio de pressão ou diabetes de graça na Farmácia Popular | AK118: Sem o programa, gastariam pelo menos R$ 0 mil por ano
A119: 1303205 | B119: 130320 | C119: Novo Airão | D119: AM | E119: 13002 | F119: Rio Negro e Solimões | G119: 16562 | H119: =G119<'Programas e Observações'!$C$11 -> TRUE | I119: 0 | J119: 0 | K119: 0 | L119: 0 | M119: 0 | N119: 23 | O119: 1 | P119: 0 | R119: =IF(G119>0,1000*I119/G119,0) -> 0 | S119: =IF(G119>0,1000*J119/G119,0) -> 0 | T119: =IF(G119>0,1000*K119/G119,0) -> 0 | U119: =IF(G119>0,1000*L119/G119,0) -> 0 | V119: =IF(G119>0,1000*M119/G119,0) -> 0 | W119: =IF(G119>0,1000*N119/G119,0) -> 1.3887212 | X119: =IF(G119>0,1000*O119/G119,0) -> 0.060379181 | Y119: =SUMIFS($I$2:$I$5572,$E$2:$E$5572,E119) -> 1330 | Z119: =SUMIFS($J$2:$J$5572,$E$2:$E$5572,E119) -> 163 | AA119: =SUMIFS($K$2:$K$5572,$E$2:$E$5572,E119) -> 73 | AB119: =SUMIFS($L$2:$L$5572,$E$2:$E$5572,E119) -> 86 | AC119: =SUMIFS($M$2:$M$5572,$E$2:$E$5572,E119) -> 157 | AD119: =SUMIFS($N$2:$N$5572,$E$2:$E$5572,E119) -> 322 | AE119: =SUMIFS($O$2:$O$5572,$E$2:$E$5572,E119) -> 15 | AF119: =SUMIFS($P$2:$P$5572,$E$2:$E$5572,E119) -> 3 | AG119: =IF(SUMIFS($G$2:$G$5572,$E$2:$E$5572,E119)>0,1000*Y119/SUMIFS($G$2:$G$5572,$E$2:$E$5572,E119),0) -> 4.557932 | AH119: =12*(J119*'Programas e Observações'!$C$8+K119*'Programas e Observações'!$C$9+L119*('Programas e Observações'!$C$8+'Programas e Observações'!$C$9)+M119*'Programas e Observações'!$C$10) -> 0 | AI119: =12*(J119*'Programas e Observações'!$D$8+K119*'Programas e Observações'!$D$9+L119*('Programas e Observações'!$D$8+'Programas e Observações'!$D$9)+M119*'Programas e Observações'!$D$10) -> 0 | AJ119: 0 moradores pegam remédio de pressão ou diabetes de graça na Farmácia Popular | AK119: Sem o programa, gastariam pelo menos R$ 0 mil por ano
A120: 1303304 | B120: 130330 | C120: Novo Aripuanã | D120: AM | E120: 13003 | F120: Rio Madeira | G120: 25325 | H120: =G120<'Programas e Observações'!$C$11 -> FALSE | I120: 0 | J120: 0 | K120: 0 | L120: 0 | M120: 0 | N120: 12 | O120: 1 | P120: 0 | R120: =IF(G120>0,1000*I120/G120,0) -> 0 | S120: =IF(G120>0,1000*J120/G120,0) -> 0 | T120: =IF(G120>0,1000*K120/G120,0) -> 0 | U120: =IF(G120>0,1000*L120/G120,0) -> 0 | V120: =IF(G120>0,1000*M120/G120,0) -> 0 | W120: =IF(G120>0,1000*N120/G120,0) -> 0.47384008 | X120: =IF(G120>0,1000*O120/G120,0) -> 0.039486673 | Y120: =SUMIFS($I$2:$I$5572,$E$2:$E$5572,E120) -> 971 | Z120: =SUMIFS($J$2:$J$5572,$E$2:$E$5572,E120) -> 454 | AA120: =SUMIFS($K$2:$K$5572,$E$2:$E$5572,E120) -> 12 | AB120: =SUMIFS($L$2:$L$5572,$E$2:$E$5572,E120) -> 289 | AC120: =SUMIFS($M$2:$M$5572,$E$2:$E$5572,E120) -> 0 | AD120: =SUMIFS($N$2:$N$5572,$E$2:$E$5572,E120) -> 185 | AE120: =SUMIFS($O$2:$O$5572,$E$2:$E$5572,E120) -> 86 | AF120: =SUMIFS($P$2:$P$5572,$E$2:$E$5572,E120) -> 2 | AG120: =IF(SUMIFS($G$2:$G$5572,$E$2:$E$5572,E120)>0,1000*Y120/SUMIFS($G$2:$G$5572,$E$2:$E$5572,E120),0) -> 4.7727418 | AH120: =12*(J120*'Programas e Observações'!$C$8+K120*'Programas e Observações'!$C$9+L120*('Programas e Observações'!$C$8+'Programas e Observações'!$C$9)+M120*'Programas e Observações'!$C$10) -> 0 | AI120: =12*(J120*'Programas e Observações'!$D$8+K120*'Programas e Observações'!$D$9+L120*('Programas e Observações'!$D$8+'Programas e Observações'!$D$9)+M120*'Programas e Observações'!$D$10) -> 0 | AJ120: 0 moradores pegam remédio de pressão ou diabetes de graça na Farmácia Popular | AK120: Sem o programa, gastariam pelo menos R$ 0 mil por ano
A121: 1303403 | B121: 130340 | C121: Parintins | D121: AM | E121: 13005 | F121: Baixo Amazonas | G121: 101855 | H121: =G121<'Programas e Observações'!$C$11 -> FALSE | I121: 0 | J121: 0 | K121: 0 | L121: 0 | M121: 0 | N121: 431 | O121: 5 | P121: 1 | Q121: 297 | R121: =IF(G121>0,1000*I121/G121,0) -> 0 | S121: =IF(G121>0,1000*J121/G121,0) -> 0 | T121: =IF(G121>0,1000*K121/G121,0) -> 0 | U121: =IF(G121>0,1000*L121/G121,0) -> 0 | V121: =IF(G121>0,1000*M121/G121,0) -> 0 | W121: =IF(G121>0,1000*N121/G121,0) -> 4.2315056 | X121: =IF(G121>0,1000*O121/G121,0) -> 0.049089392 | Y121: =SUMIFS($I$2:$I$5572,$E$2:$E$5572,E121) -> 0 | Z121: =SUMIFS($J$2:$J$5572,$E$2:$E$5572,E121) -> 0 | AA121: =SUMIFS($K$2:$K$5572,$E$2:$E$5572,E121) -> 0 | AB121: =SUMIFS($L$2:$L$5572,$E$2:$E$5572,E121) -> 0 | AC121: =SUMIFS($M$2:$M$5572,$E$2:$E$5572,E121) -> 0 | AD121: =SUMIFS($N$2:$N$5572,$E$2:$E$5572,E121) -> 483 | AE121: =SUMIFS($O$2:$O$5572,$E$2:$E$5572,E121) -> 13 | AF121: =SUMIFS($P$2:$P$5572,$E$2:$E$5572,E121) -> 2 | AG121: =IF(SUMIFS($G$2:$G$5572,$E$2:$E$5572,E121)>0,1000*Y121/SUMIFS($G$2:$G$5572,$E$2:$E$5572,E121),0) -> 0 | AH121: =12*(J121*'Programas e Observações'!$C$8+K121*'Programas e Observações'!$C$9+L121*('Programas e Observações'!$C$8+'Programas e Observações'!$C$9)+M121*'Programas e Observações'!$C$10) -> 0 | AI121: =12*(J121*'Programas e Observações'!$D$8+K121*'Programas e Observações'!$D$9+L121*('Programas e Observações'!$D$8+'Programas e Observações'!$D$9)+M121*'Programas e Observações'!$D$10) -> 0 | AJ121: 0 moradores pegam remédio de pressão ou diabetes de graça na Farmácia Popular | AK121: Sem o programa, gastariam pelo menos R$ 0 mil por ano
A122: 1303502 | B122: 130350 | C122: Pauini | D122: AM | E122: 13006 | F122: Regional Purus | G122: 20229 | H122: =G122<'Programas e Observações'!$C$11 -> FALSE | I122: 0 | J122: 0 | K122: 0 | L122: 0 | M122: 0 | N122: 9 | O122: 6 | P122: 0 | R122: =IF(G122>0,1000*I122/G122,0) -> 0 | S122: =IF(G122>0,1000*J122/G122,0) -> 0 | T122: =IF(G122>0,1000*K122/G122,0) -> 0 | U122: =IF(G122>0,1000*L122/G122,0) -> 0 | V122: =IF(G122>0,1000*M122/G122,0) -> 0 | W122: =IF(G122>0,1000*N122/G122,0) -> 0.44490583 | X122: =IF(G122>0,1000*O122/G122,0) -> 0.29660389 | Y122: =SUMIFS($I$2:$I$5572,$E$2:$E$5572,E122) -> 875 | Z122: =SUMIFS($J$2:$J$5572,$E$2:$E$5572,E122) -> 530 | AA122: =SUMIFS($K$2:$K$5572,$E$2:$E$5572,E122) -> 52 | AB122: =SUMIFS($L$2:$L$5572,$E$2:$E$5572,E122) -> 148 | AC122: =SUMIFS($M$2:$M$5572,$E$2:$E$5572,E122) -> 12 | AD122: =SUMIFS($N$2:$N$5572,$E$2:$E$5572,E122) -> 101 | AE122: =SUMIFS($O$2:$O$5572,$E$2:$E$5572,E122) -> 48 | AF122: =SUMIFS($P$2:$P$5572,$E$2:$E$5572,E122) -> 3 | AG122: =IF(SUMIFS($G$2:$G$5572,$E$2:$E$5572,E122)>0,1000*Y122/SUMIFS($G$2:$G$5572,$E$2:$E$5572,E122),0) -> 5.9391693 | AH122: =12*(J122*'Programas e Observações'!$C$8+K122*'Programas e Observações'!$C$9+L122*('Programas e Observações'!$C$8+'Programas e Observações'!$C$9)+M122*'Programas e Observações'!$C$10) -> 0 | AI122: =12*(J122*'Programas e Observações'!$D$8+K122*'Programas e Observações'!$D$9+L122*('Programas e Observações'!$D$8+'Programas e Observações'!$D$9)+M122*'Programas e Observações'!$D$10) -> 0 | AJ122: 0 moradores pegam remédio de pressão ou diabetes de graça na Farmácia Popular | AK122: Sem o programa, gastariam pelo menos R$ 0 mil por ano
A123: 1303536 | B123: 130353 | C123: Presidente Figueiredo | D123: AM | E123: 13001 | F123: Manaus, Entorno e Alto Rio Negro | G123: 33291 | H123: =G123<'Programas e Observações'!$C$11 -> FALSE | I123: 0 | J123: 0 | K123: 0 | L123: 0 | M123: 0 | N123: 60 | O123: 3 | P123: 1 | R123: =IF(G123>0,1000*I123/G123,0) -> 0 | S123: =IF(G123>0,1000*J123/G123,0) -> 0 | T123: =IF(G123>0,1000*K123/G123,0) -> 0 | U123: =IF(G123>0,1000*L123/G123,0) -> 0 | V123: =IF(G123>0,1000*M123/G123,0) -> 0 | W123: =IF(G123>0,1000*N123/G123,0) -> 1.8022889 | X123: =IF(G123>0,1000*O123/G123,0) -> 0.090114445 | Y123: =SUMIFS($I$2:$I$5572,$E$2:$E$5572,E123) -> 13707 | Z123: =SUMIFS($J$2:$J$5572,$E$2:$E$5572,E123) -> 2662 | AA123: =SUMIFS($K$2:$K$5572,$E$2:$E$5572,E123) -> 1816 | AB123: =SUMIFS($L$2:$L$5572,$E$2:$E$5572,E123) -> 1620 | AC123: =SUMIFS($M$2:$M$5572,$E$2:$E$5572,E123) -> 687 | AD123: =SUMIFS($N$2:$N$5572,$E$2:$E$5572,E123) -> 11419 | AE123: =SUMIFS($O$2:$O$5572,$E$2:$E$5572,E123) -> 592 | AF123: =SUMIFS($P$2:$P$5572,$E$2:$E$5572,E123) -> 8 | AG123: =IF(SUMIFS($G$2:$G$5572,$E$2:$E$5572,E123)>0,1000*Y123/SUMIFS($G$2:$G$5572,$E$2:$E$5572,E123),0) -> 5.1457416 | AH123: =12*(J123*'Programas e Observações'!$C$8+K123*'Programas e Observações'!$C$9+L123*('Programas e Observações'!$C$8+'Programas e Observações'!$C$9)+M123*'Programas e Observações'!$C$10) -> 0 | AI123: =12*(J123*'Programas e Observações'!$D$8+K123*'Programas e Observações'!$D$9+L123*('Programas e Observações'!$D$8+'Programas e Observações'!$D$9)+M123*'Programas e Observações'!$D$10) -> 0 | AJ123: 0 moradores pegam remédio de pressão ou diabetes de graça na Farmácia Popular | AK123: Sem o programa, gastariam pelo menos R$ 0 mil por ano
A124: 1303569 | B124: 130356 | C124: Rio Preto da Eva | D124: AM | E124: 13001 | F124: Manaus, Entorno e Alto Rio Negro | G124: 25364 | H124: =G124<'Programas e Observações'!$C$11 -> FALSE | I124: 0 | J124: 0 | K124: 0 | L124: 0 | M124: 0 | N124: 55 | O124: 6 | P124: 0 | R124: =IF(G124>0,1000*I124/G124,0) -> 0 | S124: =IF(G124>0,1000*J124/G124,0) -> 0 | T124: =IF(G124>0,1000*K124/G124,0) -> 0 | U124: =IF(G124>0,1000*L124/G124,0) -> 0 | V124: =IF(G124>0,1000*M124/G124,0) -> 0 | W124: =IF(G124>0,1000*N124/G124,0) -> 2.1684277 | X124: =IF(G124>0,1000*O124/G124,0) -> 0.23655575 | Y124: =SUMIFS($I$2:$I$5572,$E$2:$E$5572,E124) -> 13707 | Z124: =SUMIFS($J$2:$J$5572,$E$2:$E$5572,E124) -> 2662 | AA124: =SUMIFS($K$2:$K$5572,$E$2:$E$5572,E124) -> 1816 | AB124: =SUMIFS($L$2:$L$5572,$E$2:$E$5572,E124) -> 1620 | AC124: =SUMIFS($M$2:$M$5572,$E$2:$E$5572,E124) -> 687 | AD124: =SUMIFS($N$2:$N$5572,$E$2:$E$5572,E124) -> 11419 | AE124: =SUMIFS($O$2:$O$5572,$E$2:$E$5572,E124) -> 592 | AF124: =SUMIFS($P$2:$P$5572,$E$2:$E$5572,E124) -> 8 | AG124: =IF(SUMIFS($G$2:$G$5572,$E$2:$E$5572,E124)>0,1000*Y124/SUMIFS($G$2:$G$5572,$E$2:$E$5572,E124),0) -> 5.1457416 | AH124: =12*(J124*'Programas e Observações'!$C$8+K124*'Programas e Observações'!$C$9+L124*('Programas e Observações'!$C$8+'Programas e Observações'!$C$9)+M124*'Programas e Observações'!$C$10) -> 0 | AI124: =12*(J124*'Programas e Observações'!$D$8+K124*'Programas e Observações'!$D$9+L124*('Programas e Observações'!$D$8+'Programas e Observações'!$D$9)+M124*'Programas e Observações'!$D$10) -> 0 | AJ124: 0 moradores pegam remédio de pressão ou diabetes de graça na Farmácia Popular | AK124: Sem o programa, gastariam pelo menos R$ 0 mil por ano
A125: 1303601 | B125: 130360 | C125: Santa Isabel do Rio Negro | D125: AM | E125: 13001 | F125: Manaus, Entorno e Alto Rio Negro | G125: 13947 | H125: =G125<'Programas e Observações'!$C$11 -> TRUE | I125: 0 | J125: 0 | K125: 0 | L125: 0 | M125: 0 | N125: 3 | O125: 0 | P125: 0 | R125: =IF(G125>0,1000*I125/G125,0) -> 0 | S125: =IF(G125>0,1000*J125/G125,0) -> 0 | T125: =IF(G125>0,1000*K125/G125,0) -> 0 | U125: =IF(G125>0,1000*L125/G125,0) -> 0 | V125: =IF(G125>0,1000*M125/G125,0) -> 0 | W125: =IF(G125>0,1000*N125/G125,0) -> 0.21510002 | X125: =IF(G125>0,1000*O125/G125,0) -> 0 | Y125: =SUMIFS($I$2:$I$5572,$E$2:$E$5572,E125) -> 13707 | Z125: =SUMIFS($J$2:$J$5572,$E$2:$E$5572,E125) -> 2662 | AA125: =SUMIFS($K$2:$K$5572,$E$2:$E$5572,E125) -> 1816 | AB125: =SUMIFS($L$2:$L$5572,$E$2:$E$5572,E125) -> 1620 | AC125: =SUMIFS($M$2:$M$5572,$E$2:$E$5572,E125) -> 687 | AD125: =SUMIFS($N$2:$N$5572,$E$2:$E$5572,E125) -> 11419 | AE125: =SUMIFS($O$2:$O$5572,$E$2:$E$5572,E125) -> 592 | AF125: =SUMIFS($P$2:$P$5572,$E$2:$E$5572,E125) -> 8 | AG125: =IF(SUMIFS($G$2:$G$5572,$E$2:$E$5572,E125)>0,1000*Y125/SUMIFS($G$2:$G$5572,$E$2:$E$5572,E125),0) -> 5.1457416 | AH125: =12*(J125*'Programas e Observações'!$C$8+K125*'Programas e Observações'!$C$9+L125*('Programas e Observações'!$C$8+'Programas e Observações'!$C$9)+M125*'Programas e Observações'!$C$10) -> 0 | AI125: =12*(J125*'Programas e Observações'!$D$8+K125*'Programas e Observações'!$D$9+L125*('Programas e Observações'!$D$8+'Programas e Observações'!$D$9)+M125*'Programas e Observações'!$D$10) -> 0 | AJ125: 0 moradores pegam remédio de pressão ou diabetes de graça na Farmácia Popular | AK125: Sem o programa, gastariam pelo menos R$ 0 mil por ano
A126: 1303700 | B126: 130370 | C126: Santo Antônio do Içá | D126: AM | E126: 13009 | F126: Alto Solimões | G126: 30679 | H126: =G126<'Programas e Observações'!$C$11 -> FALSE | I126: 0 | J126: 0 | K126: 0 | L126: 0 | M126: 0 | N126: 6 | O126: 0 | P126: 0 | R126: =IF(G126>0,1000*I126/G126,0) -> 0 | S126: =IF(G126>0,1000*J126/G126,0) -> 0 | T126: =IF(G126>0,1000*K126/G126,0) -> 0 | U126: =IF(G126>0,1000*L126/G126,0) -> 0 | V126: =IF(G126>0,1000*M126/G126,0) -> 0 | W126: =IF(G126>0,1000*N126/G126,0) -> 0.19557352 | X126: =IF(G126>0,1000*O126/G126,0) -> 0 | Y126: =SUMIFS($I$2:$I$5572,$E$2:$E$5572,E126) -> 632 | Z126: =SUMIFS($J$2:$J$5572,$E$2:$E$5572,E126) -> 303 | AA126: =SUMIFS($K$2:$K$5572,$E$2:$E$5572,E126) -> 91 | AB126: =SUMIFS($L$2:$L$5572,$E$2:$E$5572,E126) -> 31 | AC126: =SUMIFS($M$2:$M$5572,$E$2:$E$5572,E126) -> 17 | AD126: =SUMIFS($N$2:$N$5572,$E$2:$E$5572,E126) -> 77 | AE126: =SUMIFS($O$2:$O$5572,$E$2:$E$5572,E126) -> 11 | AF126: =SUMIFS($P$2:$P$5572,$E$2:$E$5572,E126) -> 2 | AG126: =IF(SUMIFS($G$2:$G$5572,$E$2:$E$5572,E126)>0,1000*Y126/SUMIFS($G$2:$G$5572,$E$2:$E$5572,E126),0) -> 2.2215583 | AH126: =12*(J126*'Programas e Observações'!$C$8+K126*'Programas e Observações'!$C$9+L126*('Programas e Observações'!$C$8+'Programas e Observações'!$C$9)+M126*'Programas e Observações'!$C$10) -> 0 | AI126: =12*(J126*'Programas e Observações'!$D$8+K126*'Programas e Observações'!$D$9+L126*('Programas e Observações'!$D$8+'Programas e Observações'!$D$9)+M126*'Programas e Observações'!$D$10) -> 0 | AJ126: 0 moradores pegam remédio de pressão ou diabetes de graça na Farmácia Popular | AK126: Sem o programa, gastariam pelo menos R$ 0 mil por ano
A127: 1303809 | B127: 130380 | C127: São Gabriel da Cachoeira | D127: AM | E127: 13001 | F127: Manaus, Entorno e Alto Rio Negro | G127: 57396 | H127: =G127<'Programas e Observações'!$C$11 -> FALSE | I127: 7 | J127: 5 | K127: 0 | L127: 1 | M127: 0 | N127: 18 | O127: 1 | P127: 0 | R127: =IF(G127>0,1000*I127/G127,0) -> 0.12195972 | S127: =IF(G127>0,1000*J127/G127,0) -> 0.087114085 | T127: =IF(G127>0,1000*K127/G127,0) -> 0 | U127: =IF(G127>0,1000*L127/G127,0) -> 0.017422817 | V127: =IF(G127>0,1000*M127/G127,0) -> 0 | W127: =IF(G127>0,1000*N127/G127,0) -> 0.3136107 | X127: =IF(G127>0,1000*O127/G127,0) -> 0.017422817 | Y127: =SUMIFS($I$2:$I$5572,$E$2:$E$5572,E127) -> 13707 | Z127: =SUMIFS($J$2:$J$5572,$E$2:$E$5572,E127) -> 2662 | AA127: =SUMIFS($K$2:$K$5572,$E$2:$E$5572,E127) -> 1816 | AB127: =SUMIFS($L$2:$L$5572,$E$2:$E$5572,E127) -> 1620 | AC127: =SUMIFS($M$2:$M$5572,$E$2:$E$5572,E127) -> 687 | AD127: =SUMIFS($N$2:$N$5572,$E$2:$E$5572,E127) -> 11419 | AE127: =SUMIFS($O$2:$O$5572,$E$2:$E$5572,E127) -> 592 | AF127: =SUMIFS($P$2:$P$5572,$E$2:$E$5572,E127) -> 8 | AG127: =IF(SUMIFS($G$2:$G$5572,$E$2:$E$5572,E127)>0,1000*Y127/SUMIFS($G$2:$G$5572,$E$2:$E$5572,E127),0) -> 5.1457416 | AH127: =12*(J127*'Programas e Observações'!$C$8+K127*'Programas e Observações'!$C$9+L127*('Programas e Observações'!$C$8+'Programas e Observações'!$C$9)+M127*'Programas e Observações'!$C$10) -> 1701 | AI127: =12*(J127*'Programas e Observações'!$D$8+K127*'Programas e Observações'!$D$9+L127*('Programas e Observações'!$D$8+'Programas e Observações'!$D$9)+M127*'Programas e Observações'!$D$10) -> 3880.44 | AJ127: 6 moradores pegam remédio de pressão ou diabetes de graça na Farmácia Popular | AK127: Sem o programa, gastariam pelo menos R$ 2 mil por ano
A128: 1303908 | B128: 130390 | C128: São Paulo de Olivença | D128: AM | E128: 13009 | F128: Alto Solimões | G128: 35442 | H128: =G128<'Programas e Observações'!$C$11 -> FALSE | I128: 0 | J128: 0 | K128: 0 | L128: 0 | M128: 0 | N128: 6 | O128: 1 | P128: 1 | R128: =IF(G128>0,1000*I128/G128,0) -> 0 | S128: =IF(G128>0,1000*J128/G128,0) -> 0 | T128: =IF(G128>0,1000*K128/G128,0) -> 0 | U128: =IF(G128>0,1000*L128/G128,0) -> 0 | V128: =IF(G128>0,1000*M128/G128,0) -> 0 | W128: =IF(G128>0,1000*N128/G128,0) -> 0.16929067 | X128: =IF(G128>0,1000*O128/G128,0) -> 0.028215112 | Y128: =SUMIFS($I$2:$I$5572,$E$2:$E$5572,E128) -> 632 | Z128: =SUMIFS($J$2:$J$5572,$E$2:$E$5572,E128) -> 303 | AA128: =SUMIFS($K$2:$K$5572,$E$2:$E$5572,E128) -> 91 | AB128: =SUMIFS($L$2:$L$5572,$E$2:$E$5572,E128) -> 31 | AC128: =SUMIFS($M$2:$M$5572,$E$2:$E$5572,E128) -> 17 | AD128: =SUMIFS($N$2:$N$5572,$E$2:$E$5572,E128) -> 77 | AE128: =SUMIFS($O$2:$O$5572,$E$2:$E$5572,E128) -> 11 | AF128: =SUMIFS($P$2:$P$5572,$E$2:$E$5572,E128) -> 2 | AG128: =IF(SUMIFS($G$2:$G$5572,$E$2:$E$5572,E128)>0,1000*Y128/SUMIFS($G$2:$G$5572,$E$2:$E$5572,E128),0) -> 2.2215583 | AH128: =12*(J128*'Programas e Observações'!$C$8+K128*'Programas e Observações'!$C$9+L128*('Programas e Observações'!$C$8+'Programas e Observações'!$C$9)+M128*'Programas e Observações'!$C$10) -> 0 | AI128: =12*(J128*'Programas e Observações'!$D$8+K128*'Programas e Observações'!$D$9+L128*('Programas e Observações'!$D$8+'Programas e Observações'!$D$9)+M128*'Programas e Observações'!$D$10) -> 0 | AJ128: 0 moradores pegam remédio de pressão ou diabetes de graça na Farmácia Popular | AK128: Sem o programa, gastariam pelo menos R$ 0 mil por ano
A129: 1303957 | B129: 130395 | C129: São Sebastião do Uatumã | D129: AM | E129: 13004 | F129: Médio Amazonas | G129: 12338 | H129: =G129<'Programas e Observações'!$C$11 -> TRUE | I129: 0 | J129: 0 | K129: 0 | L129: 0 | M129: 0 | N129: 8 | O129: 2 | P129: 0 | R129: =IF(G129>0,1000*I129/G129,0) -> 0 | S129: =IF(G129>0,1000*J129/G129,0) -> 0 | T129: =IF(G129>0,1000*K129/G129,0) -> 0 | U129: =IF(G129>0,1000*L129/G129,0) -> 0 | V129: =IF(G129>0,1000*M129/G129,0) -> 0 | W129: =IF(G129>0,1000*N129/G129,0) -> 0.64840331 | X129: =IF(G129>0,1000*O129/G129,0) -> 0.16210083 | Y129: =SUMIFS($I$2:$I$5572,$E$2:$E$5572,E129) -> 0 | Z129: =SUMIFS($J$2:$J$5572,$E$2:$E$5572,E129) -> 0 | AA129: =SUMIFS($K$2:$K$5572,$E$2:$E$5572,E129) -> 0 | AB129: =SUMIFS($L$2:$L$5572,$E$2:$E$5572,E129) -> 0 | AC129: =SUMIFS($M$2:$M$5572,$E$2:$E$5572,E129) -> 0 | AD129: =SUMIFS($N$2:$N$5572,$E$2:$E$5572,E129) -> 265 | AE129: =SUMIFS($O$2:$O$5572,$E$2:$E$5572,E129) -> 10 | AF129: =SUMIFS($P$2:$P$5572,$E$2:$E$5572,E129) -> 2 | AG129: =IF(SUMIFS($G$2:$G$5572,$E$2:$E$5572,E129)>0,1000*Y129/SUMIFS($G$2:$G$5572,$E$2:$E$5572,E129),0) -> 0 | AH129: =12*(J129*'Programas e Observações'!$C$8+K129*'Programas e Observações'!$C$9+L129*('Programas e Observações'!$C$8+'Programas e Observações'!$C$9)+M129*'Programas e Observações'!$C$10) -> 0 | AI129: =12*(J129*'Programas e Observações'!$D$8+K129*'Programas e Observações'!$D$9+L129*('Programas e Observações'!$D$8+'Programas e Observações'!$D$9)+M129*'Programas e Observações'!$D$10) -> 0 | AJ129: 0 moradores pegam remédio de pressão ou diabetes de graça na Farmácia Popular | AK129: Sem o programa, gastariam pelo menos R$ 0 mil por ano
A130: 1304005 | B130: 130400 | C130: Silves | D130: AM | E130: 13004 | F130: Médio Amazonas | G130: 12619 | H130: =G130<'Programas e Observações'!$C$11 -> TRUE | I130: 0 | J130: 0 | K130: 0 | L130: 0 | M130: 0 | N130: 13 | O130: 0 | P130: 0 | R130: =IF(G130>0,1000*I130/G130,0) -> 0 | S130: =IF(G130>0,1000*J130/G130,0) -> 0 | T130: =IF(G130>0,1000*K130/G130,0) -> 0 | U130: =IF(G130>0,1000*L130/G130,0) -> 0 | V130: =IF(G130>0,1000*M130/G130,0) -> 0 | W130: =IF(G130>0,1000*N130/G130,0) -> 1.0301926 | X130: =IF(G130>0,1000*O130/G130,0) -> 0 | Y130: =SUMIFS($I$2:$I$5572,$E$2:$E$5572,E130) -> 0 | Z130: =SUMIFS($J$2:$J$5572,$E$2:$E$5572,E130) -> 0 | AA130: =SUMIFS($K$2:$K$5572,$E$2:$E$5572,E130) -> 0 | AB130: =SUMIFS($L$2:$L$5572,$E$2:$E$5572,E130) -> 0 | AC130: =SUMIFS($M$2:$M$5572,$E$2:$E$5572,E130) -> 0 | AD130: =SUMIFS($N$2:$N$5572,$E$2:$E$5572,E130) -> 265 | AE130: =SUMIFS($O$2:$O$5572,$E$2:$E$5572,E130) -> 10 | AF130: =SUMIFS($P$2:$P$5572,$E$2:$E$5572,E130) -> 2 | AG130: =IF(SUMIFS($G$2:$G$5572,$E$2:$E$5572,E130)>0,1000*Y130/SUMIFS($G$2:$G$5572,$E$2:$E$5572,E130),0) -> 0 | AH130: =12*(J130*'Programas e Observações'!$C$8+K130*'Programas e Observações'!$C$9+L130*('Programas e Observações'!$C$8+'Programas e Observações'!$C$9)+M130*'Programas e Observações'!$C$10) -> 0 | AI130: =12*(J130*'Programas e Observações'!$D$8+K130*'Programas e Observações'!$D$9+L130*('Programas e Observações'!$D$8+'Programas e Observações'!$D$9)+M130*'Programas e Observações'!$D$10) -> 0 | AJ130: 0 moradores pegam remédio de pressão ou diabetes de graça na Farmácia Popular | AK130: Sem o programa, gastariam pelo menos R$ 0 mil por ano
A131: 1304062 | B131: 130406 | C131: Tabatinga | D131: AM | E131: 13009 | F131: Alto Solimões | G131: 73348 | H131: =G131<'Programas e Observações'!$C$11 -> FALSE | I131: 632 | J131: 303 | K131: 91 | L131: 31 | M131: 17 | N131: 19 | O131: 1 | P131: 0 | Q131: 202 | R131: =IF(G131>0,1000*I131/G131,0) -> 8.6164585 | S131: =IF(G131>0,1000*J131/G131,0) -> 4.130992 | T131: =IF(G131>0,1000*K131/G131,0) -> 1.240661 | U131: =IF(G131>0,1000*L131/G131,0) -> 0.42264274 | V131: =IF(G131>0,1000*M131/G131,0) -> 0.23177183 | W131: =IF(G131>0,1000*N131/G131,0) -> 0.2590391 | X131: =IF(G131>0,1000*O131/G131,0) -> 0.013633637 | Y131: =SUMIFS($I$2:$I$5572,$E$2:$E$5572,E131) -> 632 | Z131: =SUMIFS($J$2:$J$5572,$E$2:$E$5572,E131) -> 303 | AA131: =SUMIFS($K$2:$K$5572,$E$2:$E$5572,E131) -> 91 | AB131: =SUMIFS($L$2:$L$5572,$E$2:$E$5572,E131) -> 31 | AC131: =SUMIFS($M$2:$M$5572,$E$2:$E$5572,E131) -> 17 | AD131: =SUMIFS($N$2:$N$5572,$E$2:$E$5572,E131) -> 77 | AE131: =SUMIFS($O$2:$O$5572,$E$2:$E$5572,E131) -> 11 | AF131: =SUMIFS($P$2:$P$5572,$E$2:$E$5572,E131) -> 2 | AG131: =IF(SUMIFS($G$2:$G$5572,$E$2:$E$5572,E131)>0,1000*Y131/SUMIFS($G$2:$G$5572,$E$2:$E$5572,E131),0) -> 2.2215583 | AH131: =12*(J131*'Programas e Observações'!$C$8+K131*'Programas e Observações'!$C$9+L131*('Programas e Observações'!$C$8+'Programas e Observações'!$C$9)+M131*'Programas e Observações'!$C$10) -> 137442.96 | AI131: =12*(J131*'Programas e Observações'!$D$8+K131*'Programas e Observações'!$D$9+L131*('Programas e Observações'!$D$8+'Programas e Observações'!$D$9)+M131*'Programas e Observações'!$D$10) -> 260440.68 | AJ131: 425 moradores pegam remédio de pressão ou diabetes de graça na Farmácia Popular | AK131: Sem o programa, gastariam pelo menos R$ 137 mil por ano
A132: 1304104 | B132: 130410 | C132: Tapauá | D132: AM | E132: 13006 | F132: Regional Purus | G132: 20728 | H132: =G132<'Programas e Observações'!$C$11 -> FALSE | I132: 0 | J132: 0 | K132: 0 | L132: 0 | M132: 0 | N132: 15 | O132: 0 | P132: 0 | R132: =IF(G132>0,1000*I132/G132,0) -> 0 | S132: =IF(G132>0,1000*J132/G132,0) -> 0 | T132: =IF(G132>0,1000*K132/G132,0) -> 0 | U132: =IF(G132>0,1000*L132/G132,0) -> 0 | V132: =IF(G132>0,1000*M132/G132,0) -> 0 | W132: =IF(G132>0,1000*N132/G132,0) -> 0.72365882 | X132: =IF(G132>0,1000*O132/G132,0) -> 0 | Y132: =SUMIFS($I$2:$I$5572,$E$2:$E$5572,E132) -> 875 | Z132: =SUMIFS($J$2:$J$5572,$E$2:$E$5572,E132) -> 530 | AA132: =SUMIFS($K$2:$K$5572,$E$2:$E$5572,E132) -> 52 | AB132: =SUMIFS($L$2:$L$5572,$E$2:$E$5572,E132) -> 148 | AC132: =SUMIFS($M$2:$M$5572,$E$2:$E$5572,E132) -> 12 | AD132: =SUMIFS($N$2:$N$5572,$E$2:$E$5572,E132) -> 101 | AE132: =SUMIFS($O$2:$O$5572,$E$2:$E$5572,E132) -> 48 | AF132: =SUMIFS($P$2:$P$5572,$E$2:$E$5572,E132) -> 3 | AG132: =IF(SUMIFS($G$2:$G$5572,$E$2:$E$5572,E132)>0,1000*Y132/SUMIFS($G$2:$G$5572,$E$2:$E$5572,E132),0) -> 5.9391693 | AH132: =12*(J132*'Programas e Observações'!$C$8+K132*'Programas e Observações'!$C$9+L132*('Programas e Observações'!$C$8+'Programas e Observações'!$C$9)+M132*'Programas e Observações'!$C$10) -> 0 | AI132: =12*(J132*'Programas e Observações'!$D$8+K132*'Programas e Observações'!$D$9+L132*('Programas e Observações'!$D$8+'Programas e Observações'!$D$9)+M132*'Programas e Observações'!$D$10) -> 0 | AJ132: 0 moradores pegam remédio de pressão ou diabetes de graça na Farmácia Popular | AK132: Sem o programa, gastariam pelo menos R$ 0 mil por ano
A133: 1304203 | B133: 130420 | C133: Tefé | D133: AM | E133: 13008 | F133: Triângulo | G133: 80137 | H133: =G133<'Programas e Observações'!$C$11 -> FALSE | I133: 0 | J133: 0 | K133: 0 | L133: 0 | M133: 0 | N133: 36 | O133: 1 | P133: 1 | Q133: 165 | R133: =IF(G133>0,1000*I133/G133,0) -> 0 | S133: =IF(G133>0,1000*J133/G133,0) -> 0 | T133: =IF(G133>0,1000*K133/G133,0) -> 0 | U133: =IF(G133>0,1000*L133/G133,0) -> 0 | V133: =IF(G133>0,1000*M133/G133,0) -> 0 | W133: =IF(G133>0,1000*N133/G133,0) -> 0.44923069 | X133: =IF(G133>0,1000*O133/G133,0) -> 0.01247863 | Y133: =SUMIFS($I$2:$I$5572,$E$2:$E$5572,E133) -> 0 | Z133: =SUMIFS($J$2:$J$5572,$E$2:$E$5572,E133) -> 0 | AA133: =SUMIFS($K$2:$K$5572,$E$2:$E$5572,E133) -> 0 | AB133: =SUMIFS($L$2:$L$5572,$E$2:$E$5572,E133) -> 0 | AC133: =SUMIFS($M$2:$M$5572,$E$2:$E$5572,E133) -> 0 | AD133: =SUMIFS($N$2:$N$5572,$E$2:$E$5572,E133) -> 64 | AE133: =SUMIFS($O$2:$O$5572,$E$2:$E$5572,E133) -> 5 | AF133: =SUMIFS($P$2:$P$5572,$E$2:$E$5572,E133) -> 3 | AG133: =IF(SUMIFS($G$2:$G$5572,$E$2:$E$5572,E133)>0,1000*Y133/SUMIFS($G$2:$G$5572,$E$2:$E$5572,E133),0) -> 0 | AH133: =12*(J133*'Programas e Observações'!$C$8+K133*'Programas e Observações'!$C$9+L133*('Programas e Observações'!$C$8+'Programas e Observações'!$C$9)+M133*'Programas e Observações'!$C$10) -> 0 | AI133: =12*(J133*'Programas e Observações'!$D$8+K133*'Programas e Observações'!$D$9+L133*('Programas e Observações'!$D$8+'Programas e Observações'!$D$9)+M133*'Programas e Observações'!$D$10) -> 0 | AJ133: 0 moradores pegam remédio de pressão ou diabetes de graça na Farmácia Popular | AK133: Sem o programa, gastariam pelo menos R$ 0 mil por ano
A134: 1304237 | B134: 130423 | C134: Tonantins | D134: AM | E134: 13009 | F134: Alto Solimões | G134: 20257 | H134: =G134<'Programas e Observações'!$C$11 -> FALSE | I134: 0 | J134: 0 | K134: 0 | L134: 0 | M134: 0 | N134: 5 | O134: 1 | P134: 0 | R134: =IF(G134>0,1000*I134/G134,0) -> 0 | S134: =IF(G134>0,1000*J134/G134,0) -> 0 | T134: =IF(G134>0,1000*K134/G134,0) -> 0 | U134: =IF(G134>0,1000*L134/G134,0) -> 0 | V134: =IF(G134>0,1000*M134/G134,0) -> 0 | W134: =IF(G134>0,1000*N134/G134,0) -> 0.24682826 | X134: =IF(G134>0,1000*O134/G134,0) -> 0.049365651 | Y134: =SUMIFS($I$2:$I$5572,$E$2:$E$5572,E134) -> 632 | Z134: =SUMIFS($J$2:$J$5572,$E$2:$E$5572,E134) -> 303 | AA134: =SUMIFS($K$2:$K$5572,$E$2:$E$5572,E134) -> 91 | AB134: =SUMIFS($L$2:$L$5572,$E$2:$E$5572,E134) -> 31 | AC134: =SUMIFS($M$2:$M$5572,$E$2:$E$5572,E134) -> 17 | AD134: =SUMIFS($N$2:$N$5572,$E$2:$E$5572,E134) -> 77 | AE134: =SUMIFS($O$2:$O$5572,$E$2:$E$5572,E134) -> 11 | AF134: =SUMIFS($P$2:$P$5572,$E$2:$E$5572,E134) -> 2 | AG134: =IF(SUMIFS($G$2:$G$5572,$E$2:$E$5572,E134)>0,1000*Y134/SUMIFS($G$2:$G$5572,$E$2:$E$5572,E134),0) -> 2.2215583 | AH134: =12*(J134*'Programas e Observações'!$C$8+K134*'Programas e Observações'!$C$9+L134*('Programas e Observações'!$C$8+'Programas e Observações'!$C$9)+M134*'Programas e Observações'!$C$10) -> 0 | AI134: =12*(J134*'Programas e Observações'!$D$8+K134*'Programas e Observações'!$D$9+L134*('Programas e Observações'!$D$8+'Programas e Observações'!$D$9)+M134*'Programas e Observações'!$D$10) -> 0 | AJ134: 0 moradores pegam remédio de pressão ou diabetes de graça na Farmácia Popular | AK134: Sem o programa, gastariam pelo menos R$ 0 mil por ano
A135: 1304260 | B135: 130426 | C135: Uarini | D135: AM | E135: 13008 | F135: Triângulo | G135: 15640 | H135: =G135<'Programas e Observações'!$C$11 -> TRUE | I135: 0 | J135: 0 | K135: 0 | L135: 0 | M135: 0 | N135: 2 | O135: 1 | P135: 0 | R135: =IF(G135>0,1000*I135/G135,0) -> 0 | S135: =IF(G135>0,1000*J135/G135,0) -> 0 | T135: =IF(G135>0,1000*K135/G135,0) -> 0 | U135: =IF(G135>0,1000*L135/G135,0) -> 0 | V135: =IF(G135>0,1000*M135/G135,0) -> 0 | W135: =IF(G135>0,1000*N135/G135,0) -> 0.12787724 | X135: =IF(G135>0,1000*O135/G135,0) -> 0.063938619 | Y135: =SUMIFS($I$2:$I$5572,$E$2:$E$5572,E135) -> 0 | Z135: =SUMIFS($J$2:$J$5572,$E$2:$E$5572,E135) -> 0 | AA135: =SUMIFS($K$2:$K$5572,$E$2:$E$5572,E135) -> 0 | AB135: =SUMIFS($L$2:$L$5572,$E$2:$E$5572,E135) -> 0 | AC135: =SUMIFS($M$2:$M$5572,$E$2:$E$5572,E135) -> 0 | AD135: =SUMIFS($N$2:$N$5572,$E$2:$E$5572,E135) -> 64 | AE135: =SUMIFS($O$2:$O$5572,$E$2:$E$5572,E135) -> 5 | AF135: =SUMIFS($P$2:$P$5572,$E$2:$E$5572,E135) -> 3 | AG135: =IF(SUMIFS($G$2:$G$5572,$E$2:$E$5572,E135)>0,1000*Y135/SUMIFS($G$2:$G$5572,$E$2:$E$5572,E135),0) -> 0 | AH135: =12*(J135*'Programas e Observações'!$C$8+K135*'Programas e Observações'!$C$9+L135*('Programas e Observações'!$C$8+'Programas e Observações'!$C$9)+M135*'Programas e Observações'!$C$10) -> 0 | AI135: =12*(J135*'Programas e Observações'!$D$8+K135*'Programas e Observações'!$D$9+L135*('Programas e Observações'!$D$8+'Programas e Observações'!$D$9)+M135*'Programas e Observações'!$D$10) -> 0 | AJ135: 0 moradores pegam remédio de pressão ou diabetes de graça na Farmácia Popular | AK135: Sem o programa, gastariam pelo menos R$ 0 mil por ano
...

Sheet Dicionário de Dados
A1: Coluna | B1: Descrição | C1: Tipo | D1: Unidade | E1: Fonte | F1: Período / referência
A2: cod_ibge7 | B2: Código IBGE do município com 7 dígitos (chave para cruzar com outras bases do IBGE). | C2: Identificação | D2: código | E2: IBGE | F2: —
A3: cod_ibge6 | B3: Código IBGE com 6 dígitos (sem o dígito verificador), usado pelo DataSUS e pelo Ministério da Saúde. | C3: Identificação | D3: código | E3: IBGE | F3: —
A4: municipio | B4: Nome do município. | C4: Identificação | D4: texto | E4: IBGE | F4: —
A5: uf | B5: Sigla do estado. | C5: Identificação | D5: texto | E5: IBGE | F5: —
A6: co_regiao_saude | B6: Código da região de saúde a que o município pertence (439 regiões no país). | C6: Identificação | D6: código | E6: Ministério da Saúde · Portal de Dados Abertos do SUS · Programa Farmácia Popular do Brasil | F6: 08/2026
A7: no_regiao_saude | B7: Nome da região de saúde. | C7: Identificação | D7: texto | E7: Ministério da Saúde · Portal de Dados Abertos do SUS · Programa Farmácia Popular do Brasil | F7: 08/2026
A8: populacao_2025 | B8: População residente estimada. | C8: Dado | D8: pessoas | E8: IBGE · Estimativas de população (POP2025_20260828) | F8: 1º/07/2025
A9: municipio_pequeno | B9: VERDADEIRO se a população for menor que o limite da aba Programas e Observações (padrão: 20.000 habitantes). Nesses municípios. prefira os totais da região de saúde. | C9: Fórmula | D9: sim/não | E9: Calculado nesta planilha | F9: —
A10: fp_total | B10: Pessoas atendidas pela Farmácia Popular no mês, em qualquer medicamento ou insumo. Contadas no município da FARMÁCIA, não da residência. | C10: Dado | D10: pessoas/mês | E10: Ministério da Saúde · Portal de Dados Abertos do SUS · Programa Farmácia Popular do Brasil (pfpbben) | F10: 08/2026
A11: fp_so_hipertensao | B11: Pessoas atendidas com remédio gratuito apenas para hipertensão. | C11: Dado | D11: pessoas/mês | E11: Ministério da Saúde · Portal de Dados Abertos do SUS · Programa Farmácia Popular do Brasil (sntpbh) | F11: 08/2026
A12: fp_so_diabetes | B12: Pessoas atendidas com remédio gratuito apenas para diabetes. | C12: Dado | D12: pessoas/mês | E12: Ministério da Saúde · Portal de Dados Abertos do SUS · Programa Farmácia Popular do Brasil (sntpbd) | F12: 08/2026
... A38: txt_bolso | B38: Frase pronta com o gasto anual mínimo. É texto fixo: NÃO se atualiza se os preços da aba de programas forem alterados. | C38: Texto | D38: texto | E38: Gerado a partir do cenário mínimo com os preços originais | F38: —

Sheet Programas e Observações
A1: Saúde e remédios por município · programas, parâmetros e observações
A3: Gerado em | B3: 15/10/2026. Uma linha por município (5.571) na aba Dados; descrição de cada coluna na aba Dicionário de Dados.
A4: Como usar | B4: Células com fundo amarelo e texto azul são parâmetros e podem ser alteradas: a aba Dados recalcula sozinha. Todos os números são agregados por município; nenhum dado individual foi usado.
A6: 1. Parâmetros editáveis
A7: Parâmetro | B7: Descrição | C7: Mínimo (R$/mês) | D7: Mediano (R$/mês) | E7: Fonte
A8: Custo mensal · Hipertensão | B8: losartana potássica 50 mg, 1 comprimido/dia (caixa com 30) | C8: 16.55 | D8: 46.52 | E8: Anvisa · Lista CMED de preço máximo ao consumidor (PMC), 09/10/2026, ICMS 18%
A9: Custo mensal · Diabetes | B9: metformina 850 mg, 2 comprimidos/dia (caixa com 60) | C9: 42.45 | D9: 44.25 | E9: Anvisa · Lista CMED de preço máximo ao consumidor (PMC), 09/10/2026, ICMS 18%
A10: Custo mensal · Asma | B10: beclometasona 250 mcg, 2 jatos 2x/dia = 120 doses (0,6 frasco de 200 doses) | C10: 43.94 | D10: 45.13 | E10: Anvisa · Lista CMED de preço máximo ao consumidor (PMC), 09/10/2026, ICMS 18%
A11: Limite de município pequeno | B11: Abaixo desta população, os números de câncer e alto custo são baixos e oscilam; use os totais da região de saúde. | C11: 20000 | E11: Definição do time (instrução recebida em 15/10/2026)
A13: 2. Totais do Brasil (calculados a partir da aba Dados)
A14: Indicador | B14: Descrição | C14: Total | E14: Período
A15: Farmácia Popular · total | B15: Pessoas atendidas no mês | C15: =SUM(Dados!I2:I5572) -> 12957809 | E15: 08/2026
A16: Farmácia Popular · só hipertensão | B16: Pessoas atendidas no mês | C16: =SUM(Dados!J2:J5572) -> 4962509 | E16: 08/2026
A17: Farmácia Popular · só diabetes | B17: Pessoas atendidas no mês | C17: =SUM(Dados!K2:K5572) -> 1808126 | E17: 08/2026
A18: Farmácia Popular · hipertensão e diabetes | B18: Pessoas atendidas no mês | C18: =SUM(Dados!L2:L5572) -> 3239501 | E18: 08/2026
A19: Farmácia Popular · asma | B19: Pessoas atendidas no mês | C19: =SUM(Dados!M2:M5572) -> 875033 | E19: 08/2026
A20: Alto custo (CEAF) | B20: Pacientes estimados | C20: =SUM(Dados!N2:N5572) -> 3284659 | E20: 06/2026
A21: Quimioterapia | B21: Pacientes estimados | C21: =SUM(Dados!O2:O5572) -> 361331 | E21: 06/2026
A22: Radioterapia | B22: Pacientes estimados | C22: =SUM(Dados!P2:P5572) -> 8987 | E22: 06/2026
A23: HIV em tratamento | B23: Pessoas em TARV (713 municípios publicados) | C23: =SUM(Dados!Q2:Q5572) -> 622363 | E23: 2022
A24: Gasto do bolso · mínimo | B24: R$ por ano sem a Farmácia Popular | C24: =SUM(Dados!AH2:AH5572) -> 4661567780 | E24: preços de 09/10/2026
A25: Gasto do bolso · mediano | B25: R$ por ano sem a Farmácia Popular | C25: =SUM(Dados!AI2:AI5572) -> 7732862871 | E25: preços de 09/10/2026
A27: 3. Programas e bases incluídas
A28: Programa | B28: O que é e como contamos | C28: Fonte | D28: Período | E28: Observações e limites
A29: Farmácia Popular do Brasil | B29: Remédios gratuitos em farmácias privadas credenciadas ('Aqui Tem Farmácia Popular'). Desde 02/2025 todos os itens são gratuitos. A planilha usa as pessoas atendidas no mês, já separadas pelo Ministério em: só hipertensão, só diabetes, hipertensão e diabetes, e asma. | C29: Portal de Dados Abertos do SUS · conjunto [MGDI] Programa Farmácia Popular do Brasil | D29: 08/2026 (mês mais recente) | E29: Contado no município da FARMÁCIA. 1.065 municípios não têm farmácia credenciada e aparecem com zero; cidades pequenas com farmácia atendem vizinhos (ex.: Pedranópolis/SP, 439 por mil hab.). Para comparar, use as colunas da região de saúde.
A30: Componente Especializado (alto custo, CEAF) | B30: Remédios caros para doenças crônicas graves (Alzheimer, Parkinson, artrite, esclerose, transplantes etc.), retirados nas farmácias do estado. Contamos os moradores de cada município pelo campo de residência do paciente (AP_MUNPCN). | C30: DataSUS · SIA/SUS · APAC de medicamentos (arquivos AM, 27 estados) | D30: Movimento de 06/2026 | E30: Entregues em só 210 municípios, mas os pacientes moram em 5.480. O cartão SUS anonimizado vem vazio em 43% dos registros: pacientes = cartões únicos + registros sem cartão × (cartões únicos ÷ registros com cartão, no país).
A31: Oncologia · quimioterapia | B31: Pacientes em quimioterapia pelo SUS, por município de residência. | C31: DataSUS · SIA/SUS · APAC de quimioterapia (arquivos AQ, 27 estados) | D31: Movimento de 06/2026 | E31: Tratamento concentrado em hospitais habilitados (CACON/UNACON). Cartão vazio em 22% dos registros; mesma estimativa do alto custo.
A32: Oncologia · radioterapia | B32: Pacientes em radioterapia pelo SUS, por município de residência. | C32: DataSUS · SIA/SUS · APAC de radioterapia (arquivos AR, 26 estados) | D32: Movimento de 06/2026 | E32: Roraima não tem arquivo de radioterapia no servidor. Cartão vazio em 72% dos registros; números pequenos, use com cautela.
A33: HIV/Aids · tratamento antirretroviral | B33: Pessoas vivendo com HIV em tratamento (TARV) por município. | C33: Ministério da Saúde · Dathi · Indicadores Clínicos (planilha de todos os municípios) | D33: 2022 (último ano publicado) | E33: Só 713 municípios aparecem (87% das pessoas em tratamento no país); os demais ficam vazios.
A34: População | B34: Base para os indicadores por mil habitantes. | C34: IBGE · Estimativas de população | D34: 1º/07/2025 | E34: —
A36: 4. Bases avaliadas e não incluídas
A37: Base | B37: Motivo | C37: Fonte | D37: Período | E37: Situação
A38: Estoques de remédios (BNAFAR) | B38: Só 3.114 dos 5.571 municípios aparecem; 34% dos lotes registrados estão vencidos; o próprio Ministério marca a base como 'em manutenção'. | C38: Portal de Dados Abertos do SUS · BNAFAR Posição de Estoque | D38: 06/06/2026 | E38: Fora até a base ser corrigida
A39: Agentes Comunitários de Saúde | B39: Relatório público do e-Gestor AB, gerado por formulário. | C39: e-Gestor AB | D39: — | E39: Pendente
A40: Repasse do postinho (CBAF) | B40: Valor fixo por habitante (R$ 8,20 a R$ 9,05/ano conforme o IDHM); mede sobretudo o tamanho da população. | C40: Portaria GM/MS nº 9.887/2025 · Fundo Nacional de Saúde | D40: 2026 | E40: Pendente
A42: 5. Observações importantes
A43: Leitura correta | B43: Os números descrevem municípios, não pessoas. 'Gasto do bolso' é uma estimativa do que as famílias pagariam sem o programa, não uma previsão.
A44: Por que não R$ 180/mês | B44: O guia técnico sugeria R$ 180 por mês por idoso, sem fonte. Pela tabela oficial da CMED, o tratamento mais barato custa R$ 16,55 (pressão) e R$ 59,00 (pressão e diabetes). Com R$ 180, o total anual passaria de R$ 20 bilhões e seria facilmente contestado.
A45: Cenário conservador | B45: Os preços consideram um remédio por doença, na dose mais comum. Quem usa doses maiores ou mais de um remédio gastaria mais; o valor real tende a ficar acima do mínimo.
A46: Sem dupla contagem | B46: As colunas de hipertensão e diabetes são excludentes: quem tem as duas doenças está só em fp_hipertensao_e_diabetes. Por isso não há fator de desduplicação.
A47: Município de residência | B47: Alto custo e câncer usam o município onde o paciente mora (AP_MUNPCN). Usar o município do estabelecimento (AP_UFMUN) zeraria quase todo o país.
A48: Distrito Federal | B48: Parte dos registros do DataSUS traz o código da região administrativa (53xxxx); todos foram somados a Brasília.
A49: Frases prontas | B49: A coluna txt_bolso é texto fixo, gerado com os preços originais. Se os preços forem alterados, ela não muda.
